{"league":{"alias":"MLB","name":"Major League Baseball","id":"2fa448bc-fc17-4d3d-be03-e60e080fdc26","date":"2015-09-28","games":[{"game":{"id":"280d6793-ecb1-43c7-8c31-13a271c6a5a7","status":"closed","coverage":"full","game_number":1,"day_night":"N","scheduled":"2015-09-29T02:05:00+00:00","home_team":"4f735188-37c8-473d-ae32-1f7e34ccf892","away_team":"27a59d3b-ff7c-48ea-b016-4798f560f5e1","attendance":31858,"double_header":false,"venue":{"name":"Angel Stadium of Anaheim","market":"Los Angeles","capacity":45050,"surface":"grass","address":"2000 Gene Autry Way","city":"Anaheim","state":"CA","zip":"92806","country":"USA","id":"60732da9-ad03-4feb-9a36-aee3e98c7a2b","field_orientation":"NE","stadium_type":"outdoor","location":{"lat":"33.7996617","lng":"-117.8834384"}},"broadcast":{"network":"FS-W"},"final":{"inning":9,"inning_half":"B"},"home":{"name":"Angels","market":"Los Angeles","abbr":"LAA","id":"4f735188-37c8-473d-ae32-1f7e34ccf892","runs":5,"hits":7,"errors":2,"win":81,"loss":74,"probable_pitcher":{"preferred_name":"Héctor","first_name":"Héctor","last_name":"Santiago","jersey_number":"53","id":"3c0813bf-0d4b-4ec7-9ecb-4a3db0936de4","win":9,"loss":9,"era":3.474},"starting_pitcher":{"preferred_name":"Héctor","first_name":"Héctor","last_name":"Santiago","jersey_number":"53","id":"3c0813bf-0d4b-4ec7-9ecb-4a3db0936de4","win":9,"loss":9,"era":3.474},"scoring":[{"number":1,"sequence":1,"runs":0,"hits":0,"errors":0,"type":"inning"},{"number":2,"sequence":2,"runs":0,"hits":1,"errors":0,"type":"inning"},{"number":3,"sequence":3,"runs":2,"hits":2,"errors":1,"type":"inning"},{"number":4,"sequence":4,"runs":1,"hits":1,"errors":0,"type":"inning"},{"number":5,"sequence":5,"runs":0,"hits":0,"errors":0,"type":"inning"},{"number":6,"sequence":6,"runs":1,"hits":1,"errors":0,"type":"inning"},{"number":7,"sequence":7,"runs":0,"hits":0,"errors":0,"type":"inning"},{"number":8,"sequence":8,"runs":0,"hits":0,"errors":0,"type":"inning"},{"number":9,"sequence":9,"runs":1,"hits":2,"errors":1,"type":"inning"}],"events":[{"hitter_id":"ede4c708-77f4-4c26-ba7b-c8e205745ddb","pitcher_id":"b5a61195-d81a-4994-9d42-45f68fb425ba","inning":3,"inning_half":"B","type":"pitch","hitter_outcome":"aDAD3","id":"efee37a0-f154-4dd0-8569-7009de89fe01","runners":[{"starting_base":1,"first_name":"Christopher","last_name":"Iannetta","preferred_name":"Chris","jersey_number":"17","id":"e39fe9ea-bc67-442e-a178-50a5c0a81b9d"}]},{"hitter_id":"9ebd933f-8400-4f1f-93fd-61d4055237f2","pitcher_id":"b5a61195-d81a-4994-9d42-45f68fb425ba","inning":3,"inning_half":"B","type":"pitch","hitter_outcome":"aD","id":"88b3ac55-dbaf-4fb0-82ed-4eb183b17826","runners":[{"starting_base":3,"first_name":"Johnny","last_name":"Giavotella","preferred_name":"Johnny","jersey_number":"12","id":"ede4c708-77f4-4c26-ba7b-c8e205745ddb"}]},{"hitter_id":"e39fe9ea-bc67-442e-a178-50a5c0a81b9d","pitcher_id":"b5a61195-d81a-4994-9d42-45f68fb425ba","inning":4,"inning_half":"B","type":"pitch","hitter_outcome":"oSF","id":"354c1412-64e2-4caa-a96e-0abe0a417764","runners":[{"starting_base":3,"first_name":"Christopher","last_name":"Cron","preferred_name":"C.J.","jersey_number":"24","id":"08947680-7840-4281-8896-07ec06319d0c"}]},{"hitter_id":"fb061c77-5253-4181-ad7b-c68ef18aa511","pitcher_id":"b5a61195-d81a-4994-9d42-45f68fb425ba","inning":6,"inning_half":"B","type":"pitch","hitter_outcome":"aHR","id":"5bb774f0-8d63-48e1-880b-b7bc5ed98ae0","runners":[{"starting_base":0,"first_name":"Jose","last_name":"Pujols","preferred_name":"Albert","jersey_number":"5","id":"fb061c77-5253-4181-ad7b-c68ef18aa511"}]},{"hitter_id":"3a82a712-bafd-474d-8556-23eb0c5ad649","pitcher_id":"deb5cf04-4ba3-4d6d-922a-0d4b97b71b45","inning":9,"inning_half":"B","type":"pitch","hitter_outcome":"aS","id":"647fed90-2ce3-4324-934e-2ac12648c23b","runners":[{"starting_base":3,"first_name":"Collin","last_name":"Cowgill","preferred_name":"Collin","jersey_number":"7","id":"03679c2e-6c76-4ccb-9ba4-c10edac8f691"}]}]},"away":{"name":"Athletics","market":"Oakland","abbr":"OAK","id":"27a59d3b-ff7c-48ea-b016-4798f560f5e1","runs":4,"hits":7,"errors":2,"win":65,"loss":91,"probable_pitcher":{"preferred_name":"Felix","first_name":"Felix","last_name":"Doubront","id":"b5a61195-d81a-4994-9d42-45f68fb425ba","win":3,"loss":3,"era":5.532},"starting_pitcher":{"preferred_name":"Felix","first_name":"Felix","last_name":"Doubront","id":"b5a61195-d81a-4994-9d42-45f68fb425ba","win":3,"loss":3,"era":5.532},"scoring":[{"number":1,"sequence":1,"runs":1,"hits":1,"errors":1,"type":"inning"},{"number":2,"sequence":2,"runs":0,"hits":0,"errors":0,"type":"inning"},{"number":3,"sequence":3,"runs":0,"hits":0,"errors":0,"type":"inning"},{"number":4,"sequence":4,"runs":1,"hits":1,"errors":1,"type":"inning"},{"number":5,"sequence":5,"runs":0,"hits":0,"errors":0,"type":"inning"},{"number":6,"sequence":6,"runs":2,"hits":2,"errors":0,"type":"inning"},{"number":7,"sequence":7,"runs":0,"hits":1,"errors":0,"type":"inning"},{"number":8,"sequence":8,"runs":0,"hits":1,"errors":0,"type":"inning"},{"number":9,"sequence":9,"runs":0,"hits":1,"errors":0,"type":"inning"}],"events":[{"hitter_id":"1b2abf1a-9d4f-4893-b238-ff38b8aaf05d","pitcher_id":"3c0813bf-0d4b-4ec7-9ecb-4a3db0936de4","inning":1,"inning_half":"T","type":"pitch","hitter_outcome":"oFO","id":"13483562-aa2d-4ff9-a4d7-d254364142d6","runners":[{"starting_base":3,"first_name":"William","last_name":"Burns","preferred_name":"Billy","jersey_number":"1","id":"edde7453-f220-4697-8735-7f171a51d7cd"}]},{"hitter_id":"c2d72221-932c-4155-9121-eaa87cfed176","pitcher_id":"3c0813bf-0d4b-4ec7-9ecb-4a3db0936de4","inning":4,"inning_half":"T","type":"pitch","hitter_outcome":"aHR","id":"b5d03ed3-5214-454a-badc-34c8181c039c","runners":[{"starting_base":0,"first_name":"Marcus","last_name":"Semien","preferred_name":"Marcus","jersey_number":"10","id":"c2d72221-932c-4155-9121-eaa87cfed176"}]},{"hitter_id":"d1387a94-a423-48fa-985e-6fe70f562be9","pitcher_id":"3c0813bf-0d4b-4ec7-9ecb-4a3db0936de4","inning":6,"inning_half":"T","type":"pitch","hitter_outcome":"oSF","id":"8488c0ac-d31e-4f0c-882b-bb0381b4533f","runners":[{"starting_base":3,"first_name":"Brett","last_name":"Lawrie","preferred_name":"Brett","jersey_number":"15","id":"6ac6fa53-ea9b-467d-87aa-6429a6bcb90c"}]},{"hitter_id":"c7a870c6-ad3e-4bda-abe8-cc9e17aa901b","pitcher_id":"e5ed202a-fc37-4e5a-98b7-b607cb7d8a09","inning":6,"inning_half":"T","type":"pitch","hitter_outcome":"aS","id":"aea94d0e-406e-429c-9979-8108711ad1fe","runners":[{"starting_base":3,"first_name":"Billy","last_name":"Butler","preferred_name":"Billy","jersey_number":"16","id":"1b2abf1a-9d4f-4893-b238-ff38b8aaf05d"}]}]},"pitching":{"win":{"preferred_name":"Trevor","first_name":"Trevor","last_name":"Gott","jersey_number":"26","status":"A","position":"P","primary_position":"RP","id":"a1989569-fdf0-4ff6-b9f7-a9e141ab0251","win":4,"loss":2,"save":0,"hold":14,"blown_save":3},"loss":{"preferred_name":"Edward","first_name":"Edward","last_name":"Mujica","status":"MIN","position":"P","primary_position":"RP","id":"f623b422-4fb9-499d-97f6-0697bd8d64b4","win":3,"loss":5,"save":1,"hold":4,"blown_save":3}}}},{"game":{"id":"c7190428-d556-44b8-951f-5a6b2115177f","status":"closed","coverage":"full","game_number":1,"day_night":"D","scheduled":"2015-09-28T19:05:00+00:00","home_team":"d89bed32-3aee-4407-99e3-4103641b999a","away_team":"c874a065-c115-4e7d-b0f0-235584fb0e6f","attendance":24420,"double_header":false,"venue":{"name":"Nationals Park","market":"Washington","capacity":41313,"surface":"grass","address":"1500 South Capitol Street SE","city":"Washington","state":"DC","zip":"20003","country":"USA","id":"bb062fb1-e268-412e-b3d2-2ddb6acc1822","field_orientation":"N","stadium_type":"outdoor","location":{"lat":"38.8730933","lng":"-77.0075727"}},"broadcast":{"network":"MASN"},"rescheduled":[{"from":"2015-07-08T23:05:00+00:00","reason":"postponed"}],"final":{"inning":9,"inning_half":"T"},"home":{"name":"Nationals","market":"Washington","abbr":"WSH","id":"d89bed32-3aee-4407-99e3-4103641b999a","runs":5,"hits":12,"errors":0,"win":79,"loss":76,"probable_pitcher":{"preferred_name":"Max","first_name":"Maxwell","last_name":"Scherzer","jersey_number":"31","id":"2527770b-cf48-42b9-81fa-9323756fb311","win":12,"loss":12,"era":2.976},"starting_pitcher":{"preferred_name":"Max","first_name":"Maxwell","last_name":"Scherzer","jersey_number":"31","id":"2527770b-cf48-42b9-81fa-9323756fb311","win":12,"loss":12,"era":2.976},"scoring":[{"number":1,"sequence":1,"runs":0,"hits":1,"errors":0,"type":"inning"},{"number":2,"sequence":2,"runs":0,"hits":1,"errors":1,"type":"inning"},{"number":3,"sequence":3,"runs":0,"hits":1,"errors":0,"type":"inning"},{"number":4,"sequence":4,"runs":2,"hits":4,"errors":0,"type":"inning"},{"number":5,"sequence":5,"runs":1,"hits":1,"errors":0,"type":"inning"},{"number":6,"sequence":6,"runs":1,"hits":2,"errors":0,"type":"inning"},{"number":7,"sequence":7,"runs":0,"hits":1,"errors":0,"type":"inning"},{"number":8,"sequence":8,"runs":1,"hits":1,"errors":0,"type":"inning"}],"events":[{"hitter_id":"c3031f0f-6101-4d7b-b8db-9cb2ab809082","pitcher_id":"d3bafaff-56a9-4998-8068-dade411976c6","inning":4,"inning_half":"B","type":"pitch","hitter_outcome":"oDT3","id":"c2e17d61-8b80-4f76-9bb6-d2e82a60b4cc","runners":[{"starting_base":1,"first_name":"Tyler","last_name":"Moore","preferred_name":"Tyler","jersey_number":"12","id":"cb637cd4-dc88-496f-8be4-4773c09f0a9f"}]},{"hitter_id":"9fd5e31f-8188-48bf-a93b-c9d9dbd29265","pitcher_id":"d3bafaff-56a9-4998-8068-dade411976c6","inning":4,"inning_half":"B","type":"pitch","hitter_outcome":"aS","id":"e6d337ba-92e1-4600-ac5a-b384af90e067","runners":[{"starting_base":2,"first_name":"Daniel","last_name":"Uggla","preferred_name":"Dan","jersey_number":"26","id":"58943439-148f-4c43-9d88-9dab2c29a6ca"}]},{"hitter_id":"7566a63c-6c8e-4d49-bac9-592d82f12ea2","pitcher_id":"d3bafaff-56a9-4998-8068-dade411976c6","inning":5,"inning_half":"B","type":"pitch","hitter_outcome":"aHR","id":"0f9179cd-5314-4fce-bd55-4bffccc8d316","runners":[{"starting_base":0,"first_name":"Wilson","last_name":"Ramos","preferred_name":"Wilson","jersey_number":"40","id":"7566a63c-6c8e-4d49-bac9-592d82f12ea2"}]},{"hitter_id":"c3031f0f-6101-4d7b-b8db-9cb2ab809082","pitcher_id":"87c96c1e-390d-4142-8969-78453a67baca","inning":6,"inning_half":"B","type":"pitch","hitter_outcome":"aHR","id":"3ba14a82-67e6-4146-ba15-8d34efcec2c7","runners":[{"starting_base":0,"first_name":"Matthew","last_name":"den Dekker","preferred_name":"Matt","jersey_number":"21","id":"c3031f0f-6101-4d7b-b8db-9cb2ab809082"}]},{"hitter_id":"9a35443a-4d10-4f57-83d3-350dba550653","pitcher_id":"bbc430c3-1c84-4387-928f-aff8b97c215c","inning":8,"inning_half":"B","type":"pitch","hitter_outcome":"oSF","id":"e70cd874-8a20-4016-b665-79c5e3decb06","runners":[{"starting_base":3,"first_name":"Matthew","last_name":"den Dekker","preferred_name":"Matt","jersey_number":"21","id":"c3031f0f-6101-4d7b-b8db-9cb2ab809082"}]}]},"away":{"name":"Reds","market":"Cincinnati","abbr":"CIN","id":"c874a065-c115-4e7d-b0f0-235584fb0e6f","runs":1,"hits":3,"errors":1,"win":63,"loss":92,"probable_pitcher":{"preferred_name":"Brandon","first_name":"Brandon","last_name":"Finnegan","jersey_number":"29","id":"d3bafaff-56a9-4998-8068-dade411976c6","win":4,"loss":1,"era":3.649},"starting_pitcher":{"preferred_name":"Brandon","first_name":"Brandon","last_name":"Finnegan","jersey_number":"29","id":"d3bafaff-56a9-4998-8068-dade411976c6","win":4,"loss":1,"era":3.649},"scoring":[{"number":1,"sequence":1,"runs":0,"hits":0,"errors":0,"type":"inning"},{"number":2,"sequence":2,"runs":0,"hits":0,"errors":0,"type":"inning"},{"number":3,"sequence":3,"runs":0,"hits":0,"errors":0,"type":"inning"},{"number":4,"sequence":4,"runs":0,"hits":0,"errors":0,"type":"inning"},{"number":5,"sequence":5,"runs":0,"hits":0,"errors":0,"type":"inning"},{"number":6,"sequence":6,"runs":0,"hits":0,"errors":0,"type":"inning"},{"number":7,"sequence":7,"runs":0,"hits":0,"errors":0,"type":"inning"},{"number":8,"sequence":8,"runs":1,"hits":2,"errors":0,"type":"inning"},{"number":9,"sequence":9,"runs":0,"hits":1,"errors":0,"type":"inning"}],"events":[{"hitter_id":"624ebcd4-afa3-4a2c-a606-0b083ff26567","pitcher_id":"2527770b-cf48-42b9-81fa-9323756fb311","inning":8,"inning_half":"T","type":"pitch","hitter_outcome":"aS","id":"958e35dc-de83-431a-94f4-8a3fe8508a89","runners":[{"starting_base":2,"first_name":"Tucker","last_name":"Barnhart","preferred_name":"Tucker","jersey_number":"16","id":"7922c705-97b9-494f-8565-89423d728aa5"}]}]},"pitching":{"win":{"preferred_name":"Max","first_name":"Maxwell","last_name":"Scherzer","jersey_number":"31","status":"A","position":"P","primary_position":"SP","id":"2527770b-cf48-42b9-81fa-9323756fb311","win":13,"loss":12,"save":0,"hold":0,"blown_save":0},"loss":{"preferred_name":"Brandon","first_name":"Brandon","last_name":"Finnegan","jersey_number":"29","status":"D10","position":"P","primary_position":"SP","id":"d3bafaff-56a9-4998-8068-dade411976c6","win":4,"loss":2,"save":0,"hold":0,"blown_save":1}}}},{"game":{"id":"0ed48be8-7852-4cb0-924b-194e6cae1eba","status":"closed","coverage":"full","game_number":1,"day_night":"N","scheduled":"2015-09-29T00:05:00+00:00","home_team":"55714da8-fcaf-4574-8443-59bfb511a524","away_team":"833a51a9-0d84-410f-bd77-da08c3e5e26e","attendance":40552,"double_header":false,"venue":{"name":"Wrigley Field","market":"Chicago","capacity":41649,"surface":"grass","address":"1060 West Addison Street","city":"Chicago","state":"IL","zip":"60613","country":"USA","id":"53f8eb0d-a361-4a7a-930b-2f8735ea0698","field_orientation":"NE","stadium_type":"outdoor","location":{"lat":"41.9474473","lng":"-87.6560538"}},"broadcast":{"network":"CSN"},"rescheduled":[{"from":"2015-05-30T23:15:00+00:00","reason":"postponed"}],"final":{"inning":11,"inning_half":"B"},"home":{"name":"Cubs","market":"Chicago","abbr":"CHC","id":"55714da8-fcaf-4574-8443-59bfb511a524","runs":1,"hits":4,"errors":0,"win":90,"loss":65,"probable_pitcher":{"preferred_name":"Kyle","first_name":"Kyle","last_name":"Hendricks","jersey_number":"28","id":"dec510da-0104-48f0-892f-37a9ab9d02ff","win":7,"loss":7,"era":4.232},"starting_pitcher":{"preferred_name":"Kyle","first_name":"Kyle","last_name":"Hendricks","jersey_number":"28","id":"dec510da-0104-48f0-892f-37a9ab9d02ff","win":7,"loss":7,"era":4.232},"scoring":[{"number":1,"sequence":1,"runs":0,"hits":0,"errors":0,"type":"inning"},{"number":2,"sequence":2,"runs":0,"hits":0,"errors":0,"type":"inning"},{"number":3,"sequence":3,"runs":0,"hits":0,"errors":0,"type":"inning"},{"number":4,"sequence":4,"runs":0,"hits":0,"errors":0,"type":"inning"},{"number":5,"sequence":5,"runs":0,"hits":0,"errors":0,"type":"inning"},{"number":6,"sequence":6,"runs":0,"hits":1,"errors":0,"type":"inning"},{"number":7,"sequence":7,"runs":0,"hits":1,"errors":0,"type":"inning"},{"number":8,"sequence":8,"runs":0,"hits":0,"errors":0,"type":"inning"},{"number":9,"sequence":9,"runs":0,"hits":0,"errors":0,"type":"inning"},{"number":10,"sequence":10,"runs":0,"hits":1,"errors":0,"type":"inning"},{"number":11,"sequence":11,"runs":1,"hits":1,"errors":0,"type":"inning"}],"events":[{"hitter_id":"ea2e908d-cf07-47c5-9e98-f0ce9c7ff813","pitcher_id":"33ee8bdb-a238-4756-9ba4-b830325bf669","inning":11,"inning_half":"B","type":"pitch","hitter_outcome":"aHR","id":"72d0f3df-bc78-4f17-af16-3aeceb19ec0a","runners":[{"starting_base":0,"first_name":"Christopher","last_name":"Denorfia","preferred_name":"Chris","jersey_number":"15","id":"ea2e908d-cf07-47c5-9e98-f0ce9c7ff813"}]}]},"away":{"name":"Royals","market":"Kansas City","abbr":"KC","id":"833a51a9-0d84-410f-bd77-da08c3e5e26e","runs":0,"hits":4,"errors":0,"win":90,"loss":65,"probable_pitcher":{"preferred_name":"Yordano","first_name":"Yordano","last_name":"Ventura","jersey_number":"30","id":"b030ef7f-7564-4df7-9b52-bcd77ce7f33c","win":12,"loss":8,"era":4.4},"starting_pitcher":{"preferred_name":"Yordano","first_name":"Yordano","last_name":"Ventura","jersey_number":"30","id":"b030ef7f-7564-4df7-9b52-bcd77ce7f33c","win":12,"loss":8,"era":4.4},"scoring":[{"number":1,"sequence":1,"runs":0,"hits":0,"errors":0,"type":"inning"},{"number":2,"sequence":2,"runs":0,"hits":1,"errors":0,"type":"inning"},{"number":3,"sequence":3,"runs":0,"hits":0,"errors":0,"type":"inning"},{"number":4,"sequence":4,"runs":0,"hits":1,"errors":0,"type":"inning"},{"number":5,"sequence":5,"runs":0,"hits":0,"errors":0,"type":"inning"},{"number":6,"sequence":6,"runs":0,"hits":0,"errors":0,"type":"inning"},{"number":7,"sequence":7,"runs":0,"hits":1,"errors":0,"type":"inning"},{"number":8,"sequence":8,"runs":0,"hits":0,"errors":0,"type":"inning"},{"number":9,"sequence":9,"runs":0,"hits":1,"errors":0,"type":"inning"},{"number":10,"sequence":10,"runs":0,"hits":0,"errors":0,"type":"inning"},{"number":11,"sequence":11,"runs":0,"hits":0,"errors":0,"type":"inning"}]},"pitching":{"win":{"preferred_name":"Fernando","first_name":"Fernando","last_name":"Rodney","jersey_number":"56","status":"A","position":"P","primary_position":"RP","id":"b99833a6-f9bf-48f2-b490-533aecef0a5d","win":7,"loss":5,"save":16,"hold":8,"blown_save":7},"loss":{"preferred_name":"Miguel","first_name":"Miguel","last_name":"Almonte","jersey_number":"50","status":"MIN","position":"P","primary_position":"RP","id":"33ee8bdb-a238-4756-9ba4-b830325bf669","win":0,"loss":2,"save":0,"hold":0,"blown_save":0}}}},{"game":{"id":"1dadf266-aa83-472f-b0ea-1dfbd6bf3a50","status":"closed","coverage":"full","game_number":1,"day_night":"N","scheduled":"2015-09-28T23:05:00+00:00","home_team":"481dfe7e-5dab-46ab-a49f-9dcc2b6e2cfd","away_team":"44671792-dc02-4fdd-a5ad-f5f17edaa9d7","attendance":30198,"double_header":false,"venue":{"name":"PNC Park","market":"Pittsburgh","capacity":38362,"surface":"grass","address":"115 Federal Street","city":"Pittsburgh","state":"PA","zip":"15212","country":"USA","id":"61314394-c8b8-411e-b891-ca41285d5362","field_orientation":"E","stadium_type":"outdoor","location":{"lat":"40.4471507","lng":"-80.0064087"}},"broadcast":{"network":"ROOT SPORTS"},"final":{"inning":9,"inning_half":"B"},"home":{"name":"Pirates","market":"Pittsburgh","abbr":"PIT","id":"481dfe7e-5dab-46ab-a49f-9dcc2b6e2cfd","runs":0,"hits":6,"errors":1,"win":95,"loss":61,"probable_pitcher":{"preferred_name":"J.A.","first_name":"James","last_name":"Happ","jersey_number":"33","id":"9760f1d6-9560-45ed-bc73-5ec2205905a2","win":10,"loss":8,"era":3.881},"starting_pitcher":{"preferred_name":"J.A.","first_name":"James","last_name":"Happ","jersey_number":"33","id":"9760f1d6-9560-45ed-bc73-5ec2205905a2","win":10,"loss":8,"era":3.881},"scoring":[{"number":1,"sequence":1,"runs":0,"hits":0,"errors":0,"type":"inning"},{"number":2,"sequence":2,"runs":0,"hits":1,"errors":0,"type":"inning"},{"number":3,"sequence":3,"runs":0,"hits":2,"errors":0,"type":"inning"},{"number":4,"sequence":4,"runs":0,"hits":0,"errors":0,"type":"inning"},{"number":5,"sequence":5,"runs":0,"hits":1,"errors":0,"type":"inning"},{"number":6,"sequence":6,"runs":0,"hits":0,"errors":0,"type":"inning"},{"number":7,"sequence":7,"runs":0,"hits":1,"errors":1,"type":"inning"},{"number":8,"sequence":8,"runs":0,"hits":0,"errors":0,"type":"inning"},{"number":9,"sequence":9,"runs":0,"hits":1,"errors":0,"type":"inning"}]},"away":{"name":"Cardinals","market":"St. Louis","abbr":"STL","id":"44671792-dc02-4fdd-a5ad-f5f17edaa9d7","runs":3,"hits":6,"errors":1,"win":98,"loss":58,"probable_pitcher":{"preferred_name":"Lance","first_name":"Michael","last_name":"Lynn","jersey_number":"31","id":"532d4a28-6fd6-4f5e-9054-69203c78de4b","win":12,"loss":10,"era":3.157},"starting_pitcher":{"preferred_name":"Lance","first_name":"Michael","last_name":"Lynn","jersey_number":"31","id":"532d4a28-6fd6-4f5e-9054-69203c78de4b","win":12,"loss":10,"era":3.157},"scoring":[{"number":1,"sequence":1,"runs":0,"hits":0,"errors":0,"type":"inning"},{"number":2,"sequence":2,"runs":0,"hits":0,"errors":0,"type":"inning"},{"number":3,"sequence":3,"runs":0,"hits":1,"errors":0,"type":"inning"},{"number":4,"sequence":4,"runs":0,"hits":0,"errors":0,"type":"inning"},{"number":5,"sequence":5,"runs":0,"hits":0,"errors":0,"type":"inning"},{"number":6,"sequence":6,"runs":0,"hits":0,"errors":0,"type":"inning"},{"number":7,"sequence":7,"runs":0,"hits":1,"errors":0,"type":"inning"},{"number":8,"sequence":8,"runs":0,"hits":1,"errors":0,"type":"inning"},{"number":9,"sequence":9,"runs":3,"hits":3,"errors":1,"type":"inning"}],"events":[{"hitter_id":"c9b5fef5-5353-486a-84b6-d791fbc79b73","pitcher_id":"01982903-301b-41eb-8a8d-b88a7b3070d0","inning":9,"inning_half":"T","type":"pitch","hitter_outcome":"aSAD2","id":"427ef282-33ed-4186-abbd-6ae06eb26da1","runners":[{"starting_base":1,"first_name":"Matthew","last_name":"Carpenter","preferred_name":"Matt","jersey_number":"13","id":"a8cd51db-4a15-454a-836d-79fe158f7b71"}]},{"hitter_id":"d0f4c8f6-1d2a-456d-b292-16e37231e738","pitcher_id":"01982903-301b-41eb-8a8d-b88a7b3070d0","inning":9,"inning_half":"T","type":"pitch","hitter_outcome":"aHR","id":"d7300540-22c8-4e7d-a122-35aa69d4e689","runners":[{"starting_base":0,"first_name":"Mark","last_name":"Reynolds","preferred_name":"Mark","jersey_number":"12","id":"d0f4c8f6-1d2a-456d-b292-16e37231e738"},{"starting_base":2,"first_name":"Jonathan","last_name":"Jay","preferred_name":"Jon","jersey_number":"19","id":"c9b5fef5-5353-486a-84b6-d791fbc79b73"}]}]},"pitching":{"win":{"preferred_name":"Jonathan","first_name":"Jonathan","last_name":"Broxton","status":"FA","position":"P","primary_position":"RP","id":"82ec0df3-3d6d-439e-9990-1fd5db783df3","win":4,"loss":5,"save":0,"hold":17,"blown_save":3},"loss":{"preferred_name":"Mark","first_name":"Mark","last_name":"Melancon","jersey_number":"41","status":"D10","position":"P","primary_position":"RP","id":"01982903-301b-41eb-8a8d-b88a7b3070d0","win":3,"loss":2,"save":51,"hold":1,"blown_save":2},"save":{"preferred_name":"Trevor","first_name":"Trevor","last_name":"Rosenthal","status":"FA","position":"P","primary_position":"RP","id":"af45388a-bb00-46e3-ac6f-632ddab7873b","win":2,"loss":4,"save":48,"hold":0,"blown_save":3}}}},{"game":{"id":"7a5d9cc0-21b4-48c5-94d0-1fef89735999","status":"closed","coverage":"full","game_number":1,"day_night":"N","scheduled":"2015-09-29T02:15:00+00:00","home_team":"a7723160-10b7-4277-a309-d8dd95a8ae65","away_team":"ef64da7f-cfaf-4300-87b0-9313386b977c","attendance":41341,"double_header":false,"venue":{"name":"AT\u0026T Park","market":"San Francisco","capacity":41915,"surface":"grass","address":"24 Willie Mays Plaza","city":"San Francisco","state":"CA","zip":"94107","country":"USA","id":"2d7542f5-7b80-49f7-9b24-c53ffdc75af6","field_orientation":"E","stadium_type":"outdoor","location":{"lat":"37.7784199","lng":"-122.3906212"}},"broadcast":{"network":"CSN-BA"},"final":{"inning":12,"inning_half":"B"},"home":{"name":"Giants","market":"San Francisco","abbr":"SF","id":"a7723160-10b7-4277-a309-d8dd95a8ae65","runs":3,"hits":9,"errors":0,"win":81,"loss":74,"probable_pitcher":{"preferred_name":"Jake","first_name":"Jacob","last_name":"Peavy","jersey_number":"22","id":"4972d0a8-eb5a-476b-b865-3e4b6375503e","win":7,"loss":6,"era":3.831},"starting_pitcher":{"preferred_name":"Jake","first_name":"Jacob","last_name":"Peavy","jersey_number":"22","id":"4972d0a8-eb5a-476b-b865-3e4b6375503e","win":7,"loss":6,"era":3.831},"scoring":[{"number":1,"sequence":1,"runs":0,"hits":0,"errors":0,"type":"inning"},{"number":2,"sequence":2,"runs":2,"hits":3,"errors":0,"type":"inning"},{"number":3,"sequence":3,"runs":0,"hits":1,"errors":0,"type":"inning"},{"number":4,"sequence":4,"runs":0,"hits":0,"errors":0,"type":"inning"},{"number":5,"sequence":5,"runs":0,"hits":0,"errors":0,"type":"inning"},{"number":6,"sequence":6,"runs":0,"hits":0,"errors":0,"type":"inning"},{"number":7,"sequence":7,"runs":0,"hits":0,"errors":0,"type":"inning"},{"number":8,"sequence":8,"runs":0,"hits":1,"errors":0,"type":"inning"},{"number":9,"sequence":9,"runs":0,"hits":1,"errors":0,"type":"inning"},{"number":10,"sequence":10,"runs":0,"hits":0,"errors":0,"type":"inning"},{"number":11,"sequence":11,"runs":0,"hits":1,"errors":0,"type":"inning"},{"number":12,"sequence":12,"runs":1,"hits":2,"errors":0,"type":"inning"}],"events":[{"hitter_id":"ef1b62d3-3915-48cf-93b5-2b98fbb7bb48","pitcher_id":"ba554801-7322-487c-a998-74fd132712e8","inning":2,"inning_half":"B","type":"pitch","hitter_outcome":"aD","id":"37826b67-ae73-409c-8d59-19537b87285f","runners":[{"starting_base":1,"first_name":"Kelby","last_name":"Tomlinson","preferred_name":"Kelby","jersey_number":"37","id":"7c78fb7a-3347-4d68-a6fe-ff6849f02a1c"},{"starting_base":2,"first_name":"Marlon","last_name":"Byrd","preferred_name":"Marlon","jersey_number":"6","id":"0aaf592f-e6d1-460f-8af4-e0aff911dc62"}]},{"hitter_id":"6925dab7-33d3-419c-91cf-b7fc60b1077a","pitcher_id":"79ad0ac3-8b77-4989-b50f-a7ca99c87db6","inning":12,"inning_half":"B","type":"pitch","hitter_outcome":"oSF","id":"7e24adc1-47f6-4e96-9a7f-76fbacdda28a","runners":[{"starting_base":3,"first_name":"Marlon","last_name":"Byrd","preferred_name":"Marlon","jersey_number":"6","id":"0aaf592f-e6d1-460f-8af4-e0aff911dc62"}]}]},"away":{"name":"Dodgers","market":"Los Angeles","abbr":"LAD","id":"ef64da7f-cfaf-4300-87b0-9313386b977c","runs":2,"hits":9,"errors":0,"win":87,"loss":68,"probable_pitcher":{"preferred_name":"Zack","first_name":"Donald","last_name":"Greinke","jersey_number":"21","id":"ba554801-7322-487c-a998-74fd132712e8","win":18,"loss":3,"era":1.647},"starting_pitcher":{"preferred_name":"Zack","first_name":"Donald","last_name":"Greinke","jersey_number":"21","id":"ba554801-7322-487c-a998-74fd132712e8","win":18,"loss":3,"era":1.647},"scoring":[{"number":1,"sequence":1,"runs":0,"hits":0,"errors":0,"type":"inning"},{"number":2,"sequence":2,"runs":0,"hits":1,"errors":0,"type":"inning"},{"number":3,"sequence":3,"runs":1,"hits":2,"errors":0,"type":"inning"},{"number":4,"sequence":4,"runs":0,"hits":0,"errors":0,"type":"inning"},{"number":5,"sequence":5,"runs":0,"hits":0,"errors":0,"type":"inning"},{"number":6,"sequence":6,"runs":0,"hits":0,"errors":0,"type":"inning"},{"number":7,"sequence":7,"runs":0,"hits":0,"errors":0,"type":"inning"},{"number":8,"sequence":8,"runs":0,"hits":0,"errors":0,"type":"inning"},{"number":9,"sequence":9,"runs":1,"hits":2,"errors":0,"type":"inning"},{"number":10,"sequence":10,"runs":0,"hits":1,"errors":0,"type":"inning"},{"number":11,"sequence":11,"runs":0,"hits":2,"errors":0,"type":"inning"},{"number":12,"sequence":12,"runs":0,"hits":1,"errors":0,"type":"inning"}],"events":[{"hitter_id":"ca159e78-05a9-410a-be7b-3ebad5496a88","pitcher_id":"4972d0a8-eb5a-476b-b865-3e4b6375503e","inning":3,"inning_half":"T","type":"pitch","hitter_outcome":"aS","id":"69d5b3b2-30d2-41f1-a06e-4622d69184e0","runners":[{"starting_base":2,"first_name":"Carl","last_name":"Crawford","preferred_name":"Carl","jersey_number":"3","id":"d424e4cd-3a15-4a00-a1fe-15c7823a654d"}]},{"hitter_id":"e1a0286d-3b82-4f1e-b98d-74c056c755ca","pitcher_id":"09316efa-a9d5-4485-ac54-54f7d4681dba","inning":9,"inning_half":"T","type":"pitch","hitter_outcome":"oGO","id":"6b5f8864-e216-4b22-b21d-63b733f05318","runners":[{"starting_base":3,"first_name":"Corey","last_name":"Seager","preferred_name":"Corey","jersey_number":"5","id":"ca159e78-05a9-410a-be7b-3ebad5496a88"}]}]},"pitching":{"win":{"preferred_name":"Hunter","first_name":"Hunter","last_name":"Strickland","jersey_number":"60","status":"A","position":"P","primary_position":"RP","id":"62d08991-cdca-41a8-ac74-dbc4be778c4f","win":3,"loss":3,"save":0,"hold":20,"blown_save":2},"loss":{"preferred_name":"Yimi","first_name":"Yimi","last_name":"Garcia","jersey_number":"63","status":"D10","position":"P","primary_position":"RP","id":"3731cc61-f348-4155-bccc-a46a2a7edbf3","win":3,"loss":5,"save":1,"hold":10,"blown_save":5},"hold":[{"preferred_name":"Josh","first_name":"Joshua","last_name":"Osich","jersey_number":"61","status":"A","position":"P","primary_position":"RP","id":"cd458a73-2036-412d-8323-2627b112a782","win":2,"loss":0,"save":0,"hold":9,"blown_save":2}],"blown_save":[{"preferred_name":"Santiago","first_name":"Santiago","last_name":"Casilla","jersey_number":"46","status":"A","position":"P","primary_position":"RP","id":"09316efa-a9d5-4485-ac54-54f7d4681dba","win":4,"loss":2,"save":37,"hold":0,"blown_save":6}]}}},{"game":{"id":"5e1088f1-3647-47e5-814b-581d940fbbfc","status":"closed","coverage":"full","game_number":1,"day_night":"N","scheduled":"2015-09-28T23:10:00+00:00","home_team":"80715d0d-0d2a-450f-a970-1b9a3b18c7e7","away_team":"aa34e0ed-f342-4ec6-b774-c79b47b60e2d","attendance":10007,"double_header":false,"venue":{"name":"Progressive Field","market":"Cleveland","capacity":35225,"surface":"grass","address":"2401 Ontario Street","city":"Cleveland","state":"OH","zip":"44115","country":"USA","id":"2b0ccd49-4d87-4996-ac4d-27ffc7ee4c16","field_orientation":"N","stadium_type":"outdoor","location":{"lat":"41.4957048","lng":"-81.6852732"}},"broadcast":{"network":"SportsTime Ohio"},"final":{"inning":9,"inning_half":"B"},"home":{"name":"Indians","market":"Cleveland","abbr":"CLE","id":"80715d0d-0d2a-450f-a970-1b9a3b18c7e7","runs":2,"hits":6,"errors":0,"win":77,"loss":77,"probable_pitcher":{"preferred_name":"Corey","first_name":"Corey","last_name":"Kluber","jersey_number":"28","id":"48982279-0e43-4d94-95fb-fd5e623b54b6","win":8,"loss":15,"era":3.548},"starting_pitcher":{"preferred_name":"Corey","first_name":"Corey","last_name":"Kluber","jersey_number":"28","id":"48982279-0e43-4d94-95fb-fd5e623b54b6","win":8,"loss":15,"era":3.548},"scoring":[{"number":1,"sequence":1,"runs":1,"hits":1,"errors":0,"type":"inning"},{"number":2,"sequence":2,"runs":0,"hits":2,"errors":0,"type":"inning"},{"number":3,"sequence":3,"runs":0,"hits":0,"errors":0,"type":"inning"},{"number":4,"sequence":4,"runs":0,"hits":0,"errors":0,"type":"inning"},{"number":5,"sequence":5,"runs":0,"hits":0,"errors":0,"type":"inning"},{"number":6,"sequence":6,"runs":1,"hits":1,"errors":0,"type":"inning"},{"number":7,"sequence":7,"runs":0,"hits":1,"errors":0,"type":"inning"},{"number":8,"sequence":8,"runs":0,"hits":1,"errors":0,"type":"inning"},{"number":9,"sequence":9,"runs":0,"hits":0,"errors":0,"type":"inning"}],"events":[{"hitter_id":"98d3d7c1-16bb-490c-8e03-73567efdbabf","pitcher_id":"6e86edc9-b40a-4ab2-b8ec-8b751041bc62","inning":1,"inning_half":"B","type":"pitch","hitter_outcome":"aHR","id":"5e943887-2319-429a-bffc-e59e22c1d1f8","runners":[{"starting_base":0,"first_name":"Francisco","last_name":"Lindor","preferred_name":"Francisco","jersey_number":"12","id":"98d3d7c1-16bb-490c-8e03-73567efdbabf"}]},{"hitter_id":"98d3d7c1-16bb-490c-8e03-73567efdbabf","pitcher_id":"6e86edc9-b40a-4ab2-b8ec-8b751041bc62","inning":6,"inning_half":"B","type":"pitch","hitter_outcome":"oGO","id":"31791c25-1c27-4c8b-98a3-bc570d80fa43","runners":[{"starting_base":3,"first_name":"Jason","last_name":"Kipnis","preferred_name":"Jason","jersey_number":"22","id":"07aa2ada-6d34-4eca-8396-eca25d733e74"}]}]},"away":{"name":"Twins","market":"Minnesota","abbr":"MIN","id":"aa34e0ed-f342-4ec6-b774-c79b47b60e2d","runs":4,"hits":8,"errors":0,"win":80,"loss":75,"probable_pitcher":{"preferred_name":"Tommy","first_name":"Tomaso","last_name":"Milone","id":"6e86edc9-b40a-4ab2-b8ec-8b751041bc62","win":8,"loss":5,"era":4.077},"starting_pitcher":{"preferred_name":"Tommy","first_name":"Tomaso","last_name":"Milone","id":"6e86edc9-b40a-4ab2-b8ec-8b751041bc62","win":8,"loss":5,"era":4.077},"scoring":[{"number":1,"sequence":1,"runs":3,"hits":3,"errors":0,"type":"inning"},{"number":2,"sequence":2,"runs":0,"hits":1,"errors":0,"type":"inning"},{"number":3,"sequence":3,"runs":0,"hits":0,"errors":0,"type":"inning"},{"number":4,"sequence":4,"runs":1,"hits":1,"errors":0,"type":"inning"},{"number":5,"sequence":5,"runs":0,"hits":2,"errors":0,"type":"inning"},{"number":6,"sequence":6,"runs":0,"hits":0,"errors":0,"type":"inning"},{"number":7,"sequence":7,"runs":0,"hits":0,"errors":0,"type":"inning"},{"number":8,"sequence":8,"runs":0,"hits":1,"errors":0,"type":"inning"},{"number":9,"sequence":9,"runs":0,"hits":0,"errors":0,"type":"inning"}],"events":[{"hitter_id":"aecc630f-57da-4b23-842b-fd65394e81be","pitcher_id":"48982279-0e43-4d94-95fb-fd5e623b54b6","inning":1,"inning_half":"T","type":"pitch","hitter_outcome":"aD","id":"577a0b95-cb82-47ad-ad19-4df8dad65691","runners":[{"starting_base":2,"first_name":"Joseph","last_name":"Mauer","preferred_name":"Joe","jersey_number":"7","id":"31d992e8-1016-484a-b7c3-2b5851442cc5"}]},{"hitter_id":"b6871f2a-5dba-4760-874c-e3e323cfed70","pitcher_id":"48982279-0e43-4d94-95fb-fd5e623b54b6","inning":1,"inning_half":"T","type":"pitch","hitter_outcome":"aHR","id":"722f43c9-653d-440c-9456-66ee3906e718","runners":[{"starting_base":0,"first_name":"Trevor","last_name":"Plouffe","preferred_name":"Trevor","jersey_number":"24","id":"b6871f2a-5dba-4760-874c-e3e323cfed70"},{"starting_base":2,"first_name":"Miguel","last_name":"Sano","preferred_name":"Miguel","jersey_number":"22","id":"aecc630f-57da-4b23-842b-fd65394e81be"}]},{"hitter_id":"29a80d91-946d-4701-af7d-034850bdef00","pitcher_id":"48982279-0e43-4d94-95fb-fd5e623b54b6","inning":4,"inning_half":"T","type":"pitch","hitter_outcome":"oSF","id":"57f0dd37-1d09-4d48-a73b-a33ef18068af","runners":[{"starting_base":3,"first_name":"Eddie","last_name":"Rosario","preferred_name":"Eddie","jersey_number":"20","id":"4be357dd-add5-4613-937d-6b9a0831d9ee"}]}]},"pitching":{"win":{"preferred_name":"Tommy","first_name":"Tomaso","last_name":"Milone","status":"MIN","position":"P","primary_position":"RP","id":"6e86edc9-b40a-4ab2-b8ec-8b751041bc62","win":9,"loss":5,"save":1,"hold":0,"blown_save":0},"loss":{"preferred_name":"Corey","first_name":"Corey","last_name":"Kluber","jersey_number":"28","status":"A","position":"P","primary_position":"SP","id":"48982279-0e43-4d94-95fb-fd5e623b54b6","win":8,"loss":16,"save":0,"hold":0,"blown_save":0},"save":{"preferred_name":"Kevin","first_name":"Kevin","last_name":"Jepsen","jersey_number":"32","status":"A","position":"P","primary_position":"RP","id":"14a7138b-b12b-4dbf-a561-e715cd0491db","win":3,"loss":6,"save":14,"hold":24,"blown_save":5},"hold":[{"preferred_name":"Blaine","first_name":"Blaine","last_name":"Boyer","jersey_number":"51","status":"A","position":"P","primary_position":"RP","id":"3b3f273e-7eb0-426d-bd8f-86fa2d4c11f3","win":3,"loss":5,"save":1,"hold":19,"blown_save":2},{"preferred_name":"Casey","first_name":"Casey","last_name":"Fien","jersey_number":"54","status":"FA","position":"P","primary_position":"RP","id":"913a1c1a-2a80-4a9b-87ed-b623567aa640","win":4,"loss":6,"save":0,"hold":18,"blown_save":4},{"preferred_name":"Glen","first_name":"Glen","last_name":"Perkins","status":"RET","position":"P","primary_position":"RP","id":"c182d4ce-7604-47b4-8477-a6392ec357ec","win":2,"loss":5,"save":32,"hold":3,"blown_save":3}]}}},{"game":{"id":"5dc3a13a-647c-48d8-b4cb-2fc2507a78dc","status":"closed","coverage":"full","game_number":1,"day_night":"N","scheduled":"2015-09-29T02:10:00+00:00","home_team":"43a39081-52b4-4f93-ad29-da7f329ea960","away_team":"eb21dadd-8f10-4095-8bf3-dfb3b779f107","attendance":13935,"double_header":false,"venue":{"name":"Safeco Field","market":"Seattle","capacity":47943,"surface":"grass","address":"1516 First Avenue South","city":"Seattle","state":"WA","zip":"98134","country":"USA","id":"f1c03dac-3c0f-437c-a325-8d5702cd321a","field_orientation":"NE","stadium_type":"retractable","location":{"lat":"47.5899037","lng":"-122.3337561"}},"broadcast":{"network":"ROOT SPORTS"},"final":{"inning":9,"inning_half":"B"},"home":{"name":"Mariners","market":"Seattle","abbr":"SEA","id":"43a39081-52b4-4f93-ad29-da7f329ea960","runs":2,"hits":4,"errors":0,"win":74,"loss":82,"probable_pitcher":{"preferred_name":"Roenis","first_name":"Roenis","last_name":"Elías","jersey_number":"29","id":"86877e81-53d7-417d-bb51-308a948ef6a3","win":5,"loss":8,"era":3.941},"starting_pitcher":{"preferred_name":"Roenis","first_name":"Roenis","last_name":"Elías","jersey_number":"29","id":"86877e81-53d7-417d-bb51-308a948ef6a3","win":5,"loss":8,"era":3.941},"scoring":[{"number":1,"sequence":1,"runs":1,"hits":2,"errors":0,"type":"inning"},{"number":2,"sequence":2,"runs":0,"hits":0,"errors":0,"type":"inning"},{"number":3,"sequence":3,"runs":0,"hits":0,"errors":0,"type":"inning"},{"number":4,"sequence":4,"runs":0,"hits":1,"errors":0,"type":"inning"},{"number":5,"sequence":5,"runs":0,"hits":0,"errors":0,"type":"inning"},{"number":6,"sequence":6,"runs":1,"hits":1,"errors":0,"type":"inning"},{"number":7,"sequence":7,"runs":0,"hits":0,"errors":0,"type":"inning"},{"number":8,"sequence":8,"runs":0,"hits":0,"errors":0,"type":"inning"},{"number":9,"sequence":9,"runs":0,"hits":0,"errors":0,"type":"inning"}],"events":[{"hitter_id":"aff8ce97-4a84-43db-bdaf-3517b6b5fa88","pitcher_id":"fc552e8f-e5e0-4060-b018-6babc108507b","inning":1,"inning_half":"B","type":"pitch","hitter_outcome":"aS","id":"a14ba176-4d82-4c15-acac-f1d896d47179","runners":[{"starting_base":3,"first_name":"Kyle","last_name":"Seager","preferred_name":"Kyle","jersey_number":"15","id":"483d3c01-a089-407d-baaf-c7bfabd56587"}]},{"hitter_id":"04b68b54-6217-4436-b3e8-bed6d3bd4942","pitcher_id":"fc552e8f-e5e0-4060-b018-6babc108507b","inning":6,"inning_half":"B","type":"pitch","hitter_outcome":"aHR","id":"ac167bed-fca2-45da-8b66-4b19afdbbf94","runners":[{"starting_base":0,"first_name":"Ketel","last_name":"Marte","preferred_name":"Ketel","jersey_number":"4","id":"04b68b54-6217-4436-b3e8-bed6d3bd4942"}]}]},"away":{"name":"Astros","market":"Houston","abbr":"HOU","id":"eb21dadd-8f10-4095-8bf3-dfb3b779f107","runs":3,"hits":7,"errors":0,"win":82,"loss":74,"probable_pitcher":{"preferred_name":"Lance","first_name":"Lance","last_name":"McCullers","jersey_number":"43","id":"fc552e8f-e5e0-4060-b018-6babc108507b","win":5,"loss":7,"era":3.218},"starting_pitcher":{"preferred_name":"Lance","first_name":"Lance","last_name":"McCullers","jersey_number":"43","id":"fc552e8f-e5e0-4060-b018-6babc108507b","win":5,"loss":7,"era":3.218},"scoring":[{"number":1,"sequence":1,"runs":2,"hits":2,"errors":0,"type":"inning"},{"number":2,"sequence":2,"runs":0,"hits":0,"errors":0,"type":"inning"},{"number":3,"sequence":3,"runs":0,"hits":0,"errors":0,"type":"inning"},{"number":4,"sequence":4,"runs":0,"hits":1,"errors":0,"type":"inning"},{"number":5,"sequence":5,"runs":0,"hits":0,"errors":0,"type":"inning"},{"number":6,"sequence":6,"runs":0,"hits":0,"errors":0,"type":"inning"},{"number":7,"sequence":7,"runs":1,"hits":1,"errors":0,"type":"inning"},{"number":8,"sequence":8,"runs":0,"hits":2,"errors":0,"type":"inning"},{"number":9,"sequence":9,"runs":0,"hits":1,"errors":0,"type":"inning"}],"events":[{"hitter_id":"7f92278a-91c4-4c25-9e75-eaff3aed89b3","pitcher_id":"86877e81-53d7-417d-bb51-308a948ef6a3","inning":1,"inning_half":"T","type":"pitch","hitter_outcome":"aHR","id":"c7b27708-86d6-4ef0-b63e-d1a10d5dae13","runners":[{"starting_base":0,"first_name":"George","last_name":"Springer","preferred_name":"George","jersey_number":"4","id":"7f92278a-91c4-4c25-9e75-eaff3aed89b3"}]},{"hitter_id":"ab823ce4-655b-4d1d-ba3e-23316d8053dc","pitcher_id":"86877e81-53d7-417d-bb51-308a948ef6a3","inning":1,"inning_half":"T","type":"pitch","hitter_outcome":"aHR","id":"1cc523b6-d44e-4f3f-9f54-41822d757698","runners":[{"starting_base":0,"first_name":"James","last_name":"Gattis","preferred_name":"Evan","jersey_number":"11","id":"ab823ce4-655b-4d1d-ba3e-23316d8053dc"}]},{"hitter_id":"bfd7b881-1ed2-4886-9e23-df61a1e3373b","pitcher_id":"8e841e8a-ed03-45e9-b002-9189c005596b","inning":7,"inning_half":"T","type":"pitch","hitter_outcome":"aHR","id":"caab04bf-8a0a-46da-b0f8-504d2c80744b","runners":[{"starting_base":0,"first_name":"Vernon","last_name":"Carter","preferred_name":"Chris","jersey_number":"23","id":"bfd7b881-1ed2-4886-9e23-df61a1e3373b"}]}]},"pitching":{"win":{"preferred_name":"Lance","first_name":"Lance","last_name":"McCullers","jersey_number":"43","status":"A","position":"P","primary_position":"SP","id":"fc552e8f-e5e0-4060-b018-6babc108507b","win":6,"loss":7,"save":0,"hold":0,"blown_save":0},"loss":{"preferred_name":"Danny","first_name":"Daniel","last_name":"Farquhar","jersey_number":"43","status":"A","position":"P","primary_position":"RP","id":"8e841e8a-ed03-45e9-b002-9189c005596b","win":1,"loss":6,"save":1,"hold":8,"blown_save":2},"save":{"preferred_name":"Luke","first_name":"Lucas","last_name":"Gregerson","jersey_number":"44","status":"D10","position":"P","primary_position":"RP","id":"c5bfc085-8258-45a7-865f-e8019c844015","win":7,"loss":3,"save":30,"hold":0,"blown_save":5},"hold":[{"preferred_name":"Oliver","first_name":"Oliver","last_name":"Pérez","status":"MIN","position":"P","primary_position":"RP","id":"1b5eecd0-90af-451f-a04a-b36b20f0363f","win":2,"loss":3,"save":0,"hold":9,"blown_save":3},{"preferred_name":"Tony","first_name":"Tony","last_name":"Sipp","jersey_number":"29","status":"A","position":"P","primary_position":"RP","id":"76ad7cd2-86ca-4fa6-918b-519321ba62f1","win":2,"loss":4,"save":0,"hold":13,"blown_save":3}]}}},{"game":{"id":"6f7c8c49-a508-4072-a7c7-5b4e7767b159","status":"closed","coverage":"full","game_number":1,"day_night":"N","scheduled":"2015-09-28T23:05:00+00:00","home_team":"a09ec676-f887-43dc-bbb3-cf4bbaee9a18","away_team":"93941372-eb4c-4c40-aced-fe3267174393","attendance":39476,"double_header":false,"venue":{"name":"Yankee Stadium","market":"New York","capacity":54251,"surface":"grass","address":"One East 161st Street","city":"Bronx","state":"NY","zip":"10451","country":"USA","id":"706e9828-6687-4ac8-a409-3fb972e8bae9","field_orientation":"E","stadium_type":"outdoor","location":{"lat":"40.8288189","lng":"-73.9265691"}},"broadcast":{"network":"YES"},"final":{"inning":9,"inning_half":"B"},"home":{"name":"Yankees","market":"New York","abbr":"NYY","id":"a09ec676-f887-43dc-bbb3-cf4bbaee9a18","runs":1,"hits":9,"errors":0,"win":86,"loss":69,"probable_pitcher":{"preferred_name":"Iván","first_name":"Iván","last_name":"Nova","jersey_number":"46","id":"af2db144-f849-4c6e-96ed-8c1c9ce12979","win":6,"loss":9,"era":4.869},"starting_pitcher":{"preferred_name":"Iván","first_name":"Iván","last_name":"Nova","jersey_number":"46","id":"af2db144-f849-4c6e-96ed-8c1c9ce12979","win":6,"loss":9,"era":4.869},"scoring":[{"number":1,"sequence":1,"runs":1,"hits":3,"errors":0,"type":"inning"},{"number":2,"sequence":2,"runs":0,"hits":1,"errors":1,"type":"inning"},{"number":3,"sequence":3,"runs":0,"hits":1,"errors":0,"type":"inning"},{"number":4,"sequence":4,"runs":0,"hits":1,"errors":0,"type":"inning"},{"number":5,"sequence":5,"runs":0,"hits":1,"errors":0,"type":"inning"},{"number":6,"sequence":6,"runs":0,"hits":0,"errors":0,"type":"inning"},{"number":7,"sequence":7,"runs":0,"hits":1,"errors":0,"type":"inning"},{"number":8,"sequence":8,"runs":0,"hits":0,"errors":0,"type":"inning"},{"number":9,"sequence":9,"runs":0,"hits":1,"errors":0,"type":"inning"}],"events":[{"hitter_id":"9253ce81-0d6f-451e-b503-7b0435eb6cce","pitcher_id":"93413a68-2c05-405a-a38c-9ee983b36913","inning":1,"inning_half":"B","type":"pitch","hitter_outcome":"oSF","id":"8e01fe86-2fc4-423e-8027-a3bc780917f2","runners":[{"starting_base":3,"first_name":"Jacoby","last_name":"Ellsbury","preferred_name":"Jacoby","jersey_number":"22","id":"28e6daa5-fb40-49d9-9e58-04d113cd63b9"}]}]},"away":{"name":"Red Sox","market":"Boston","abbr":"BOS","id":"93941372-eb4c-4c40-aced-fe3267174393","runs":5,"hits":10,"errors":1,"win":75,"loss":80,"probable_pitcher":{"preferred_name":"Eduardo","first_name":"Eduardo","last_name":"Rodríguez","jersey_number":"57","id":"93413a68-2c05-405a-a38c-9ee983b36913","win":9,"loss":6,"era":3.968},"starting_pitcher":{"preferred_name":"Eduardo","first_name":"Eduardo","last_name":"Rodríguez","jersey_number":"57","id":"93413a68-2c05-405a-a38c-9ee983b36913","win":9,"loss":6,"era":3.968},"scoring":[{"number":1,"sequence":1,"runs":0,"hits":1,"errors":0,"type":"inning"},{"number":2,"sequence":2,"runs":0,"hits":1,"errors":0,"type":"inning"},{"number":3,"sequence":3,"runs":0,"hits":0,"errors":0,"type":"inning"},{"number":4,"sequence":4,"runs":0,"hits":1,"errors":0,"type":"inning"},{"number":5,"sequence":5,"runs":0,"hits":0,"errors":0,"type":"inning"},{"number":6,"sequence":6,"runs":2,"hits":2,"errors":0,"type":"inning"},{"number":7,"sequence":7,"runs":2,"hits":2,"errors":0,"type":"inning"},{"number":8,"sequence":8,"runs":0,"hits":1,"errors":0,"type":"inning"},{"number":9,"sequence":9,"runs":1,"hits":2,"errors":0,"type":"inning"}],"events":[{"hitter_id":"a9ad5859-6769-4349-bd41-3ea2dcae4c78","pitcher_id":"af2db144-f849-4c6e-96ed-8c1c9ce12979","inning":6,"inning_half":"T","type":"pitch","hitter_outcome":"aHR","id":"da082246-dabe-4d95-93b5-c531c2c57daf","runners":[{"starting_base":0,"first_name":"Travis","last_name":"Shaw","preferred_name":"Travis","jersey_number":"47","id":"a9ad5859-6769-4349-bd41-3ea2dcae4c78"},{"starting_base":2,"first_name":"Xander","last_name":"Bogaerts","preferred_name":"Xander","jersey_number":"2","id":"272abdba-ae99-4137-a6dd-5615f234adfc"}]},{"hitter_id":"3f38dbee-db39-48c9-8b30-d7347deccd19","pitcher_id":"af2db144-f849-4c6e-96ed-8c1c9ce12979","inning":7,"inning_half":"T","type":"pitch","hitter_outcome":"aHR","id":"45917a76-1bcf-4ff7-a150-cbb11b558f33","runners":[{"starting_base":0,"first_name":"Jackie","last_name":"Bradley Jr.","preferred_name":"Jackie","jersey_number":"25","id":"3f38dbee-db39-48c9-8b30-d7347deccd19"},{"starting_base":1,"first_name":"Blake","last_name":"Swihart","preferred_name":"Blake","jersey_number":"23","id":"f808029c-587b-476b-aa49-4d287f23fca6"}]},{"hitter_id":"3150ff7e-bac3-44b3-b919-06ced5fb6565","pitcher_id":"847f1574-9006-4e77-93f3-1506edfb5837","inning":9,"inning_half":"T","type":"pitch","hitter_outcome":"aHR","id":"ccc2abf6-2b35-4531-8d41-39d3ad584485","runners":[{"starting_base":0,"first_name":"Deven","last_name":"Marrero","preferred_name":"Deven","jersey_number":"16","id":"3150ff7e-bac3-44b3-b919-06ced5fb6565"}]}]},"pitching":{"win":{"preferred_name":"Eduardo","first_name":"Eduardo","last_name":"Rodríguez","jersey_number":"57","status":"D10","position":"P","primary_position":"SP","id":"93413a68-2c05-405a-a38c-9ee983b36913","win":10,"loss":6,"save":0,"hold":0,"blown_save":0},"loss":{"preferred_name":"Iván","first_name":"Iván","last_name":"Nova","jersey_number":"46","status":"A","position":"P","primary_position":"SP","id":"af2db144-f849-4c6e-96ed-8c1c9ce12979","win":6,"loss":10,"save":0,"hold":0,"blown_save":0},"hold":[{"preferred_name":"Heath","first_name":"Richard","last_name":"Hembree","jersey_number":"37","status":"A","position":"P","primary_position":"RP","id":"5a80eb4f-85be-4581-95cd-0062e22ecc46","win":2,"loss":0,"save":0,"hold":1,"blown_save":0},{"preferred_name":"Noe","first_name":"Noe","last_name":"Ramirez","jersey_number":"25","status":"A","position":"P","primary_position":"RP","id":"9451617b-a18e-4963-bbca-9d1f3c49f3aa","win":0,"loss":1,"save":0,"hold":4,"blown_save":0},{"preferred_name":"Matt","first_name":"Matthew","last_name":"Barnes","jersey_number":"32","status":"A","position":"P","primary_position":"RP","id":"db6334d5-f34a-4db9-8e6b-5cb843617550","win":3,"loss":4,"save":0,"hold":3,"blown_save":0}]}}},{"game":{"id":"c491cb36-6675-4d58-b086-71152f089a7e","status":"closed","coverage":"full","game_number":1,"day_night":"N","scheduled":"2015-09-29T00:05:00+00:00","home_team":"d99f919b-1534-4516-8e8a-9cd106c6d8cd","away_team":"575c19b7-4052-41c2-9f0a-1c5813d02f99","attendance":27847,"double_header":false,"venue":{"name":"Globe Life Park in Arlington","market":"Texas","capacity":49115,"surface":"grass","address":"1000 Ballpark Way","city":"Arlington","state":"TX","zip":"76011","country":"USA","id":"3f47c1c6-b059-4fa2-9d85-5d37b7000992","field_orientation":"SE","stadium_type":"outdoor","location":{"lat":"32.7512152","lng":"-97.083209"}},"broadcast":{"network":"FSSW"},"final":{"inning":9,"inning_half":"B"},"home":{"name":"Rangers","market":"Texas","abbr":"TEX","id":"d99f919b-1534-4516-8e8a-9cd106c6d8cd","runs":4,"hits":10,"errors":1,"win":84,"loss":71,"probable_pitcher":{"preferred_name":"Colby","first_name":"Colby","last_name":"Lewis","id":"2e7c2c36-3b23-44e2-9e85-6db6261e4e15","win":17,"loss":8,"era":4.362},"starting_pitcher":{"preferred_name":"Colby","first_name":"Colby","last_name":"Lewis","id":"2e7c2c36-3b23-44e2-9e85-6db6261e4e15","win":17,"loss":8,"era":4.362},"scoring":[{"number":1,"sequence":1,"runs":0,"hits":0,"errors":0,"type":"inning"},{"number":2,"sequence":2,"runs":0,"hits":1,"errors":0,"type":"inning"},{"number":3,"sequence":3,"runs":0,"hits":0,"errors":0,"type":"inning"},{"number":4,"sequence":4,"runs":1,"hits":3,"errors":0,"type":"inning"},{"number":5,"sequence":5,"runs":0,"hits":1,"errors":0,"type":"inning"},{"number":6,"sequence":6,"runs":0,"hits":1,"errors":0,"type":"inning"},{"number":7,"sequence":7,"runs":1,"hits":2,"errors":0,"type":"inning"},{"number":8,"sequence":8,"runs":0,"hits":0,"errors":0,"type":"inning"},{"number":9,"sequence":9,"runs":2,"hits":2,"errors":0,"type":"inning"}],"events":[{"hitter_id":"85d0ebf6-ef39-4fa6-acc9-d8c4a863a6c9","pitcher_id":"2fe6cb9b-c41e-4ee2-9b22-f8b27bf6c5be","inning":4,"inning_half":"B","type":"pitch","hitter_outcome":"aHR","id":"956e6100-59da-4897-a7ca-dc7dfb66e58b","runners":[{"starting_base":0,"first_name":"Prince","last_name":"Fielder","preferred_name":"Prince","jersey_number":"84","id":"85d0ebf6-ef39-4fa6-acc9-d8c4a863a6c9"}]},{"hitter_id":"85d0ebf6-ef39-4fa6-acc9-d8c4a863a6c9","pitcher_id":"05d50bcf-3afc-4149-8e78-9c8cb8a4a547","inning":7,"inning_half":"B","type":"pitch","hitter_outcome":"oGO","id":"24226e75-787d-480f-8252-e8005d9869c7","runners":[{"starting_base":3,"first_name":"Christopher","last_name":"Gimenez","preferred_name":"Chris","jersey_number":"38","id":"879db845-963e-4169-ae9c-4cd80406a322"}]},{"hitter_id":"85d0ebf6-ef39-4fa6-acc9-d8c4a863a6c9","pitcher_id":"6eb8c698-6dc2-4f70-a0c4-c71957adbf36","inning":9,"inning_half":"B","type":"pitch","hitter_outcome":"aS","id":"11416749-689f-41fd-a4e7-4f9ab6367185","runners":[{"starting_base":2,"first_name":"Robert","last_name":"Stubbs","preferred_name":"Drew","jersey_number":"15","id":"01f489cd-ded9-475f-90ae-702dcde24845"},{"starting_base":3,"first_name":"Robinson","last_name":"Chirinos","preferred_name":"Robinson","jersey_number":"61","id":"2ec3abd0-bbdd-441d-8400-d539d96e7fbf"}]}]},"away":{"name":"Tigers","market":"Detroit","abbr":"DET","id":"575c19b7-4052-41c2-9f0a-1c5813d02f99","runs":7,"hits":12,"errors":0,"win":72,"loss":83,"probable_pitcher":{"preferred_name":"Justin","first_name":"Justin","last_name":"Verlander","jersey_number":"35","id":"2fe6cb9b-c41e-4ee2-9b22-f8b27bf6c5be","win":4,"loss":8,"era":3.486},"starting_pitcher":{"preferred_name":"Justin","first_name":"Justin","last_name":"Verlander","jersey_number":"35","id":"2fe6cb9b-c41e-4ee2-9b22-f8b27bf6c5be","win":4,"loss":8,"era":3.486},"scoring":[{"number":1,"sequence":1,"runs":0,"hits":0,"errors":0,"type":"inning"},{"number":2,"sequence":2,"runs":0,"hits":1,"errors":0,"type":"inning"},{"number":3,"sequence":3,"runs":1,"hits":2,"errors":0,"type":"inning"},{"number":4,"sequence":4,"runs":0,"hits":1,"errors":0,"type":"inning"},{"number":5,"sequence":5,"runs":5,"hits":6,"errors":0,"type":"inning"},{"number":6,"sequence":6,"runs":1,"hits":1,"errors":1,"type":"inning"},{"number":7,"sequence":7,"runs":0,"hits":1,"errors":0,"type":"inning"},{"number":8,"sequence":8,"runs":0,"hits":0,"errors":0,"type":"inning"},{"number":9,"sequence":9,"runs":0,"hits":0,"errors":0,"type":"inning"}],"events":[{"hitter_id":"0fad748a-3ed8-4787-97db-845155c8e7ce","pitcher_id":"2e7c2c36-3b23-44e2-9e85-6db6261e4e15","inning":3,"inning_half":"T","type":"pitch","hitter_outcome":"bB","id":"7e02a0d0-534d-4136-8540-14cea89095ee","runners":[{"starting_base":3,"first_name":"Andrew","last_name":"Romine","preferred_name":"Andrew","jersey_number":"27","id":"7217e4e7-8fd1-4ed8-8bee-0a5cbb2add1a"}]},{"hitter_id":"743b5687-1d70-4777-a55a-f82e4324d703","pitcher_id":"2e7c2c36-3b23-44e2-9e85-6db6261e4e15","inning":5,"inning_half":"T","type":"pitch","hitter_outcome":"aHR","id":"7a0b2db0-30bf-4163-858b-0bfadb89fd83","runners":[{"starting_base":0,"first_name":"Tyler","last_name":"Collins","preferred_name":"Tyler","jersey_number":"18","id":"743b5687-1d70-4777-a55a-f82e4324d703"},{"starting_base":2,"first_name":"Anthony","last_name":"Gose","preferred_name":"Anthony","jersey_number":"12","id":"103d8964-626b-4de6-a526-4c2fb1e94642"},{"starting_base":3,"first_name":"Dixon","last_name":"Machado","preferred_name":"Dixon","jersey_number":"49","id":"f0c5e891-884d-4d37-8ca6-0a3bcb90c08d"}]},{"hitter_id":"71580b08-acfc-4d33-9670-6e5a82f389ea","pitcher_id":"2e7c2c36-3b23-44e2-9e85-6db6261e4e15","inning":5,"inning_half":"T","type":"pitch","hitter_outcome":"aS","id":"bfea45d8-a576-4ab5-b854-03e9ca05c06f","runners":[{"starting_base":2,"first_name":"Nicholas","last_name":"Castellanos","preferred_name":"Nick","jersey_number":"9","id":"169ed0b1-e34b-4f4b-925b-f3288f24a5e7"},{"starting_base":3,"first_name":"Victor","last_name":"Martínez","preferred_name":"Victor","jersey_number":"41","id":"f27a7574-57db-4eeb-8f88-377048806de2"}]},{"hitter_id":"f423faea-d0e3-49b6-b347-52ec5cfac66a","pitcher_id":"273a0544-e47d-4129-b976-834985bb5f4e","inning":6,"inning_half":"T","type":"pitch","hitter_outcome":"oFC","id":"a920365e-9102-406e-bdd8-16b95fd30964","runners":[{"starting_base":3,"first_name":"Anthony","last_name":"Gose","preferred_name":"Anthony","jersey_number":"12","id":"103d8964-626b-4de6-a526-4c2fb1e94642"}]}]},"pitching":{"win":{"preferred_name":"Justin","first_name":"Justin","last_name":"Verlander","jersey_number":"35","status":"A","position":"P","primary_position":"SP","id":"2fe6cb9b-c41e-4ee2-9b22-f8b27bf6c5be","win":5,"loss":8,"save":0,"hold":0,"blown_save":0},"loss":{"preferred_name":"Colby","first_name":"Colby","last_name":"Lewis","status":"FA","position":"P","primary_position":"SP","id":"2e7c2c36-3b23-44e2-9e85-6db6261e4e15","win":17,"loss":9,"save":0,"hold":0,"blown_save":0},"save":{"preferred_name":"Neftali","first_name":"Neftali","last_name":"Feliz","status":"MIN","position":"P","primary_position":"RP","id":"6eb8c698-6dc2-4f70-a0c4-c71957adbf36","win":3,"loss":3,"save":10,"hold":2,"blown_save":6}}}},{"game":{"id":"9fe15350-fd8b-4dbc-b944-a9198236d799","status":"closed","coverage":"full","game_number":1,"day_night":"N","scheduled":"2015-09-28T23:05:00+00:00","home_team":"75729d34-bca7-4a0f-b3df-6f26c6ad3719","away_team":"1d678440-b4b1-4954-9b39-70afb3ebbcfa","attendance":19093,"double_header":false,"venue":{"name":"Oriole Park at Camden Yards","market":"Baltimore","capacity":45971,"surface":"grass","address":"333 West Camden Street","city":"Baltimore","state":"MD","zip":"21201","country":"USA","id":"434aa63c-1049-4a54-a6bc-3790c7772ee1","field_orientation":"NE","stadium_type":"outdoor","location":{"lat":"39.2840361","lng":"-76.619919"}},"broadcast":{"network":"MASN 2"},"final":{"inning":9,"inning_half":"B"},"home":{"name":"Orioles","market":"Baltimore","abbr":"BAL","id":"75729d34-bca7-4a0f-b3df-6f26c6ad3719","runs":3,"hits":4,"errors":0,"win":76,"loss":79,"probable_pitcher":{"preferred_name":"Chris","first_name":"Christopher","last_name":"Tillman","jersey_number":"30","id":"cb4d530e-a63e-4328-b3a5-7307e168086e","win":10,"loss":11,"era":5.164},"starting_pitcher":{"preferred_name":"Chris","first_name":"Christopher","last_name":"Tillman","jersey_number":"30","id":"cb4d530e-a63e-4328-b3a5-7307e168086e","win":10,"loss":11,"era":5.164},"scoring":[{"number":1,"sequence":1,"runs":0,"hits":0,"errors":0,"type":"inning"},{"number":2,"sequence":2,"runs":3,"hits":3,"errors":0,"type":"inning"},{"number":3,"sequence":3,"runs":0,"hits":0,"errors":0,"type":"inning"},{"number":4,"sequence":4,"runs":0,"hits":1,"errors":0,"type":"inning"},{"number":5,"sequence":5,"runs":0,"hits":0,"errors":0,"type":"inning"},{"number":6,"sequence":6,"runs":0,"hits":0,"errors":0,"type":"inning"},{"number":7,"sequence":7,"runs":0,"hits":0,"errors":0,"type":"inning"},{"number":8,"sequence":8,"runs":0,"hits":0,"errors":0,"type":"inning"},{"number":9,"sequence":9,"runs":0,"hits":0,"errors":0,"type":"inning"}],"events":[{"hitter_id":"e5227d77-89fe-4512-86ff-f9d13ff43afa","pitcher_id":"c06ac3e5-bb24-415e-a4b6-7b5ae2377948","inning":2,"inning_half":"B","type":"pitch","hitter_outcome":"aHR","id":"177dddaf-b5f2-438e-a70f-9b7a7b55e8e7","runners":[{"starting_base":0,"first_name":"Ryan","last_name":"Flaherty","preferred_name":"Ryan","jersey_number":"3","id":"e5227d77-89fe-4512-86ff-f9d13ff43afa"},{"starting_base":1,"first_name":"Jonathan","last_name":"Schoop","preferred_name":"Jonathan","jersey_number":"6","id":"df2cff0c-0869-4352-a7fc-3706475c873e"},{"starting_base":2,"first_name":"Matthew","last_name":"Wieters","preferred_name":"Matt","jersey_number":"32","id":"3af422a1-b7bd-4edb-8b78-a61e3f4483a3"}]}]},"away":{"name":"Blue Jays","market":"Toronto","abbr":"TOR","id":"1d678440-b4b1-4954-9b39-70afb3ebbcfa","runs":4,"hits":10,"errors":0,"win":90,"loss":65,"probable_pitcher":{"preferred_name":"Marco","first_name":"Marco","last_name":"Estrada","jersey_number":"25","id":"c06ac3e5-bb24-415e-a4b6-7b5ae2377948","win":13,"loss":8,"era":3.126},"starting_pitcher":{"preferred_name":"Marco","first_name":"Marco","last_name":"Estrada","jersey_number":"25","id":"c06ac3e5-bb24-415e-a4b6-7b5ae2377948","win":13,"loss":8,"era":3.126},"scoring":[{"number":1,"sequence":1,"runs":0,"hits":0,"errors":0,"type":"inning"},{"number":2,"sequence":2,"runs":1,"hits":2,"errors":0,"type":"inning"},{"number":3,"sequence":3,"runs":0,"hits":0,"errors":0,"type":"inning"},{"number":4,"sequence":4,"runs":0,"hits":2,"errors":0,"type":"inning"},{"number":5,"sequence":5,"runs":0,"hits":0,"errors":0,"type":"inning"},{"number":6,"sequence":6,"runs":0,"hits":0,"errors":0,"type":"inning"},{"number":7,"sequence":7,"runs":0,"hits":0,"errors":0,"type":"inning"},{"number":8,"sequence":8,"runs":2,"hits":4,"errors":0,"type":"inning"},{"number":9,"sequence":9,"runs":1,"hits":2,"errors":0,"type":"inning"}],"events":[{"hitter_id":"8ec56596-5b8b-41f8-88a7-384f20b8b6a7","pitcher_id":"cb4d530e-a63e-4328-b3a5-7307e168086e","inning":2,"inning_half":"T","type":"pitch","hitter_outcome":"aHR","id":"81be05d5-4a24-40c2-8929-92fa6d7f4964","runners":[{"starting_base":0,"first_name":"Edwin","last_name":"Encarnación","preferred_name":"Edwin","jersey_number":"10","id":"8ec56596-5b8b-41f8-88a7-384f20b8b6a7"}]},{"hitter_id":"f4b89e5f-baae-4dd4-87b2-1cd75889b48b","pitcher_id":"dca5c161-527c-4ea8-98c3-a71d924db39c","inning":8,"inning_half":"T","type":"pitch","hitter_outcome":"aS","id":"7ab54f70-a073-4399-9b26-1d449b94dc53","runners":[{"starting_base":2,"first_name":"Ryan","last_name":"Goins","preferred_name":"Ryan","jersey_number":"17","id":"029ba09e-9965-4497-b141-5bd8dedbad6a"}]},{"hitter_id":"78bbb2e3-487a-4f14-ad95-22dfae998a98","pitcher_id":"dca5c161-527c-4ea8-98c3-a71d924db39c","inning":8,"inning_half":"T","type":"pitch","hitter_outcome":"oST2","id":"5e74ad34-84fe-49c3-8379-6c72a32dba21","runners":[{"starting_base":2,"first_name":"Ben","last_name":"Revere","preferred_name":"Ben","jersey_number":"7","id":"f4b89e5f-baae-4dd4-87b2-1cd75889b48b"}]},{"hitter_id":"44c2a812-101d-4955-a3e5-3085afa9296b","pitcher_id":"b667e70a-4380-4459-b33b-df62653d41fd","inning":9,"inning_half":"T","type":"pitch","hitter_outcome":"aFCAD2","id":"25cd8e70-3f8e-4980-a934-1a80393b2ad7","runners":[{"starting_base":3,"first_name":"Dalton","last_name":"Pompey","preferred_name":"Dalton","jersey_number":"45","id":"6b8f8b32-4b62-4a90-8749-d9ece15d3a1e"}]}]},"pitching":{"win":{"preferred_name":"Brett","first_name":"Brett","last_name":"Cecil","jersey_number":"27","status":"D10","position":"P","primary_position":"RP","id":"e3d27135-822c-4969-ad06-b74aca0e1fbd","win":5,"loss":5,"save":5,"hold":8,"blown_save":3},"loss":{"preferred_name":"Brad","first_name":"Brad","last_name":"Brach","jersey_number":"35","status":"A","position":"P","primary_position":"RP","id":"b667e70a-4380-4459-b33b-df62653d41fd","win":5,"loss":3,"save":1,"hold":13,"blown_save":1},"save":{"preferred_name":"Roberto","first_name":"Roberto","last_name":"Osuna","jersey_number":"54","status":"A","position":"P","primary_position":"RP","id":"f160ac03-8f68-4b9f-8773-6d21f312abdf","win":1,"loss":5,"save":20,"hold":7,"blown_save":2},"blown_save":[{"preferred_name":"Darren","first_name":"Darren","last_name":"O'Day","jersey_number":"56","status":"A","position":"P","primary_position":"RP","id":"dca5c161-527c-4ea8-98c3-a71d924db39c","win":6,"loss":2,"save":6,"hold":16,"blown_save":5}]}}}]},"_comment":"Generation started @ 2019-12-01 20:08:00 UTC ended @ 2019-12-01 20:08:00 UTC"}