{"league":{"alias":"MLB","name":"Major League Baseball","id":"2fa448bc-fc17-4d3d-be03-e60e080fdc26","date":"2016-06-19","games":[{"game":{"id":"87487873-0f5f-4f90-9415-1f16f0b5ba4f","status":"closed","coverage":"full","game_number":1,"day_night":"D","scheduled":"2016-06-19T17:10:00+00:00","home_team":"03556285-bdbb-4576-a06d-42f71f46ddc5","away_team":"29dd9a87-5bcc-4774-80c3-7f50d985068b","attendance":24993,"duration":"2:51","double_header":false,"venue":{"name":"Marlins Park","market":"Miami","capacity":36742,"surface":"grass","address":"501 Marlins Way","city":"Miami","state":"FL","zip":"33125","country":"USA","id":"d5a66fb3-ff26-4f36-910c-3df5cedb36b3","field_orientation":"SE","stadium_type":"retractable","location":{"lat":"25.7780567","lng":"-80.2194087"}},"broadcast":{"network":"FS-F"},"final":{"inning":9,"inning_half":"T"},"home":{"name":"Marlins","market":"Miami","abbr":"MIA","id":"03556285-bdbb-4576-a06d-42f71f46ddc5","runs":3,"hits":8,"errors":0,"win":36,"loss":32,"probable_pitcher":{"preferred_name":"Tom","first_name":"Thomas","last_name":"Koehler","jersey_number":"55","id":"8b9897db-9c08-4b3d-a6d3-3c22c1bd9979","win":5,"loss":6,"era":4.25},"starting_pitcher":{"preferred_name":"Tom","first_name":"Thomas","last_name":"Koehler","jersey_number":"55","id":"8b9897db-9c08-4b3d-a6d3-3c22c1bd9979","win":5,"loss":6,"era":4.25},"scoring":[{"number":1,"sequence":1,"runs":0,"hits":0,"errors":0,"type":"inning"},{"number":2,"sequence":2,"runs":0,"hits":2,"errors":0,"type":"inning"},{"number":3,"sequence":3,"runs":0,"hits":0,"errors":0,"type":"inning"},{"number":4,"sequence":4,"runs":0,"hits":1,"errors":0,"type":"inning"},{"number":5,"sequence":5,"runs":0,"hits":0,"errors":0,"type":"inning"},{"number":6,"sequence":6,"runs":3,"hits":3,"errors":1,"type":"inning"},{"number":7,"sequence":7,"runs":0,"hits":1,"errors":0,"type":"inning"},{"number":8,"sequence":8,"runs":0,"hits":1,"errors":0,"type":"inning"}],"events":[{"hitter_id":"57f0a40f-e0f5-4e76-bd59-b8c4de7a680c","pitcher_id":"a8b37789-7620-414c-a5a4-c0eac1bb76a0","inning":6,"inning_half":"B","type":"pitch","hitter_outcome":"aHR","id":"258e8bc5-cf8f-4c7a-a721-4eefe55ea903","runners":[{"starting_base":0,"first_name":"Marcell","last_name":"Ozuna","preferred_name":"Marcell","jersey_number":"13","id":"57f0a40f-e0f5-4e76-bd59-b8c4de7a680c"},{"starting_base":1,"first_name":"Martín","last_name":"Prado","preferred_name":"Martín","jersey_number":"14","id":"933a0bc9-26c0-478e-982c-01fd8ffe0614"},{"starting_base":2,"first_name":"Derek","last_name":"Dietrich","preferred_name":"Derek","jersey_number":"32","id":"04931bc2-76ee-4427-8da8-b5b3696f9ba6"}]}]},"away":{"name":"Rockies","market":"Colorado","abbr":"COL","id":"29dd9a87-5bcc-4774-80c3-7f50d985068b","runs":0,"hits":2,"errors":1,"win":32,"loss":35,"probable_pitcher":{"preferred_name":"Tyler","first_name":"Tyler","last_name":"Anderson","jersey_number":"44","id":"a920073f-154b-4173-a8ff-aed0b2c22711","win":0,"loss":0,"era":1.421},"starting_pitcher":{"preferred_name":"Tyler","first_name":"Tyler","last_name":"Anderson","jersey_number":"44","id":"a920073f-154b-4173-a8ff-aed0b2c22711","win":0,"loss":0,"era":1.421},"scoring":[{"number":1,"sequence":1,"runs":0,"hits":0,"errors":0,"type":"inning"},{"number":2,"sequence":2,"runs":0,"hits":0,"errors":0,"type":"inning"},{"number":3,"sequence":3,"runs":0,"hits":1,"errors":0,"type":"inning"},{"number":4,"sequence":4,"runs":0,"hits":0,"errors":0,"type":"inning"},{"number":5,"sequence":5,"runs":0,"hits":0,"errors":0,"type":"inning"},{"number":6,"sequence":6,"runs":0,"hits":1,"errors":0,"type":"inning"},{"number":7,"sequence":7,"runs":0,"hits":0,"errors":0,"type":"inning"},{"number":8,"sequence":8,"runs":0,"hits":0,"errors":0,"type":"inning"},{"number":9,"sequence":9,"runs":0,"hits":0,"errors":0,"type":"inning"}]},"pitching":{"win":{"preferred_name":"Tom","first_name":"Thomas","last_name":"Koehler","jersey_number":"55","status":"D10","position":"P","primary_position":"SP","id":"8b9897db-9c08-4b3d-a6d3-3c22c1bd9979","win":6,"loss":6,"save":0,"hold":0,"blown_save":0},"loss":{"preferred_name":"Tyler","first_name":"Tyler","last_name":"Anderson","jersey_number":"44","status":"A","position":"P","primary_position":"SP","id":"a920073f-154b-4173-a8ff-aed0b2c22711","win":0,"loss":1,"save":0,"hold":0,"blown_save":0},"save":{"preferred_name":"A.J.","first_name":"Alejandro","last_name":"Ramos","jersey_number":"44","status":"A","position":"P","primary_position":"RP","id":"509ee425-cae4-4ca2-92c6-23c621e9ce2a","win":0,"loss":0,"save":22,"hold":0,"blown_save":0},"hold":[{"preferred_name":"Kyle","first_name":"Kyle","last_name":"Barraclough","jersey_number":"46","status":"A","position":"P","primary_position":"RP","id":"eb3d13ba-4372-4b52-8bc8-9e5566c67149","win":3,"loss":1,"save":0,"hold":16,"blown_save":1},{"preferred_name":"David","first_name":"David","last_name":"Phelps","jersey_number":"35","status":"D10","position":"P","primary_position":"RP","id":"fc6848bc-5f1a-491d-89a8-1270c6b9b5b7","win":4,"loss":4,"save":2,"hold":17,"blown_save":3}]}}},{"game":{"id":"569e994b-3556-4e57-9aeb-a09236c885f5","status":"closed","coverage":"full","game_number":1,"day_night":"D","scheduled":"2016-06-19T17:35:00+00:00","home_team":"75729d34-bca7-4a0f-b3df-6f26c6ad3719","away_team":"1d678440-b4b1-4954-9b39-70afb3ebbcfa","attendance":39024,"duration":"3:31","double_header":false,"venue":{"name":"Oriole Park at Camden Yards","market":"Baltimore","capacity":45971,"surface":"grass","address":"333 West Camden Street","city":"Baltimore","state":"MD","zip":"21201","country":"USA","id":"434aa63c-1049-4a54-a6bc-3790c7772ee1","field_orientation":"NE","stadium_type":"outdoor","location":{"lat":"39.2840361","lng":"-76.619919"}},"broadcast":{"network":"WJZ"},"final":{"inning":9,"inning_half":"T"},"home":{"name":"Orioles","market":"Baltimore","abbr":"BAL","id":"75729d34-bca7-4a0f-b3df-6f26c6ad3719","runs":11,"hits":19,"errors":1,"win":39,"loss":28,"probable_pitcher":{"preferred_name":"Chris","first_name":"Christopher","last_name":"Tillman","jersey_number":"30","id":"cb4d530e-a63e-4328-b3a5-7307e168086e","win":9,"loss":1,"era":2.87},"starting_pitcher":{"preferred_name":"Chris","first_name":"Christopher","last_name":"Tillman","jersey_number":"30","id":"cb4d530e-a63e-4328-b3a5-7307e168086e","win":9,"loss":1,"era":2.87},"scoring":[{"number":1,"sequence":1,"runs":3,"hits":4,"errors":0,"type":"inning"},{"number":2,"sequence":2,"runs":1,"hits":2,"errors":0,"type":"inning"},{"number":3,"sequence":3,"runs":0,"hits":0,"errors":0,"type":"inning"},{"number":4,"sequence":4,"runs":3,"hits":5,"errors":0,"type":"inning"},{"number":5,"sequence":5,"runs":1,"hits":3,"errors":0,"type":"inning"},{"number":6,"sequence":6,"runs":0,"hits":0,"errors":0,"type":"inning"},{"number":7,"sequence":7,"runs":3,"hits":3,"errors":0,"type":"inning"},{"number":8,"sequence":8,"runs":0,"hits":2,"errors":0,"type":"inning"}],"events":[{"hitter_id":"ddfbc667-95d8-49fc-8e77-a8e4e452d820","pitcher_id":"cc86d4d3-1618-415e-b7fc-a303f3b8dd6f","inning":1,"inning_half":"B","type":"pitch","hitter_outcome":"aS","id":"700debe5-95b1-433f-874a-1d83465bfaed","runners":[{"starting_base":3,"first_name":"Adam","last_name":"Jones","preferred_name":"Adam","jersey_number":"10","id":"41b87c77-fe20-4217-aed1-8c2cda8794c1"}]},{"hitter_id":"3af422a1-b7bd-4edb-8b78-a61e3f4483a3","pitcher_id":"cc86d4d3-1618-415e-b7fc-a303f3b8dd6f","inning":1,"inning_half":"B","type":"pitch","hitter_outcome":"aHR","id":"b0be6384-141b-4623-bbbe-0818cc0c3f07","runners":[{"starting_base":0,"first_name":"Matthew","last_name":"Wieters","preferred_name":"Matt","jersey_number":"32","id":"3af422a1-b7bd-4edb-8b78-a61e3f4483a3"},{"starting_base":1,"first_name":"Christopher","last_name":"Davis","preferred_name":"Chris","jersey_number":"19","id":"ddfbc667-95d8-49fc-8e77-a8e4e452d820"}]},{"hitter_id":"e5227d77-89fe-4512-86ff-f9d13ff43afa","pitcher_id":"cc86d4d3-1618-415e-b7fc-a303f3b8dd6f","inning":2,"inning_half":"B","type":"pitch","hitter_outcome":"oST2","id":"dd6fbc03-28a8-4b69-b7d8-5fcbc5749b01","runners":[{"starting_base":2,"first_name":"Pedro","last_name":"Alvarez","preferred_name":"Pedro","jersey_number":"24","id":"da2f167c-1f5f-470d-aa7c-eafdc4b7bd94"}]},{"hitter_id":"df2cff0c-0869-4352-a7fc-3706475c873e","pitcher_id":"cc86d4d3-1618-415e-b7fc-a303f3b8dd6f","inning":4,"inning_half":"B","type":"pitch","hitter_outcome":"aS","id":"64bcf004-a254-41a0-bc16-5b2336903d21","runners":[{"starting_base":2,"first_name":"Matthew","last_name":"Wieters","preferred_name":"Matt","jersey_number":"32","id":"3af422a1-b7bd-4edb-8b78-a61e3f4483a3"}]},{"hitter_id":"e5227d77-89fe-4512-86ff-f9d13ff43afa","pitcher_id":"cc86d4d3-1618-415e-b7fc-a303f3b8dd6f","inning":4,"inning_half":"B","type":"pitch","hitter_outcome":"aD","id":"548ba11e-9f83-4275-95b8-14e16582ea2d","runners":[{"starting_base":2,"first_name":"Jonathan","last_name":"Schoop","preferred_name":"Jonathan","jersey_number":"6","id":"df2cff0c-0869-4352-a7fc-3706475c873e"}]},{"hitter_id":"41b87c77-fe20-4217-aed1-8c2cda8794c1","pitcher_id":"cc86d4d3-1618-415e-b7fc-a303f3b8dd6f","inning":4,"inning_half":"B","type":"pitch","hitter_outcome":"aS","id":"fab7db2b-5983-4a56-9796-6bb78574ad6c","runners":[{"starting_base":2,"first_name":"Ryan","last_name":"Flaherty","preferred_name":"Ryan","jersey_number":"3","id":"e5227d77-89fe-4512-86ff-f9d13ff43afa"}]},{"hitter_id":"3af422a1-b7bd-4edb-8b78-a61e3f4483a3","pitcher_id":"e92c426b-a1fd-4253-8c9d-45fa5c1da100","inning":5,"inning_half":"B","type":"pitch","hitter_outcome":"aS","id":"819a12e6-37a6-43da-b134-e1217cd73a47","runners":[{"starting_base":2,"first_name":"Christopher","last_name":"Davis","preferred_name":"Chris","jersey_number":"19","id":"ddfbc667-95d8-49fc-8e77-a8e4e452d820"}]},{"hitter_id":"3af422a1-b7bd-4edb-8b78-a61e3f4483a3","pitcher_id":"f6e5344f-c816-460f-87ab-9322cfdc08b3","inning":7,"inning_half":"B","type":"pitch","hitter_outcome":"aS","id":"19d66c95-456f-4221-82da-89ae90f84501","runners":[{"starting_base":2,"first_name":"Christopher","last_name":"Davis","preferred_name":"Chris","jersey_number":"19","id":"ddfbc667-95d8-49fc-8e77-a8e4e452d820"}]},{"hitter_id":"df2cff0c-0869-4352-a7fc-3706475c873e","pitcher_id":"f6e5344f-c816-460f-87ab-9322cfdc08b3","inning":7,"inning_half":"B","type":"pitch","hitter_outcome":"aHR","id":"28de2c7a-e5c3-4ce6-b2eb-a3674c1eac96","runners":[{"starting_base":0,"first_name":"Jonathan","last_name":"Schoop","preferred_name":"Jonathan","jersey_number":"6","id":"df2cff0c-0869-4352-a7fc-3706475c873e"},{"starting_base":1,"first_name":"Matthew","last_name":"Wieters","preferred_name":"Matt","jersey_number":"32","id":"3af422a1-b7bd-4edb-8b78-a61e3f4483a3"}]}]},"away":{"name":"Blue Jays","market":"Toronto","abbr":"TOR","id":"1d678440-b4b1-4954-9b39-70afb3ebbcfa","runs":6,"hits":7,"errors":0,"win":39,"loss":32,"probable_pitcher":{"preferred_name":"Marcus","first_name":"Marcus","last_name":"Stroman","jersey_number":"6","id":"cc86d4d3-1618-415e-b7fc-a303f3b8dd6f","win":6,"loss":2,"era":4.759},"starting_pitcher":{"preferred_name":"Marcus","first_name":"Marcus","last_name":"Stroman","jersey_number":"6","id":"cc86d4d3-1618-415e-b7fc-a303f3b8dd6f","win":6,"loss":2,"era":4.759},"scoring":[{"number":1,"sequence":1,"runs":0,"hits":0,"errors":0,"type":"inning"},{"number":2,"sequence":2,"runs":4,"hits":4,"errors":0,"type":"inning"},{"number":3,"sequence":3,"runs":0,"hits":0,"errors":0,"type":"inning"},{"number":4,"sequence":4,"runs":0,"hits":0,"errors":0,"type":"inning"},{"number":5,"sequence":5,"runs":0,"hits":1,"errors":0,"type":"inning"},{"number":6,"sequence":6,"runs":0,"hits":0,"errors":0,"type":"inning"},{"number":7,"sequence":7,"runs":2,"hits":2,"errors":1,"type":"inning"},{"number":8,"sequence":8,"runs":0,"hits":0,"errors":0,"type":"inning"},{"number":9,"sequence":9,"runs":0,"hits":0,"errors":0,"type":"inning"}],"events":[{"hitter_id":"9cc5e32a-1dad-4b18-80c8-919ec0dac676","pitcher_id":"cb4d530e-a63e-4328-b3a5-7307e168086e","inning":2,"inning_half":"T","type":"pitch","hitter_outcome":"aHR","id":"81b90ea6-da9d-4ef4-9451-428d19bc30bf","runners":[{"starting_base":0,"first_name":"Troy","last_name":"Tulowitzki","preferred_name":"Troy","jersey_number":"2","id":"9cc5e32a-1dad-4b18-80c8-919ec0dac676"},{"starting_base":2,"first_name":"Russell","last_name":"Martin","preferred_name":"Russell","jersey_number":"55","id":"3da24e28-741c-4978-bdba-52de51975820"}]},{"hitter_id":"e6b6b905-a355-4e85-84ca-db655cc3dce4","pitcher_id":"cb4d530e-a63e-4328-b3a5-7307e168086e","inning":2,"inning_half":"T","type":"pitch","hitter_outcome":"aHR","id":"14ff948a-50ef-4155-855f-5a540a5930f4","runners":[{"starting_base":0,"first_name":"Devon","last_name":"Travis","preferred_name":"Devon","jersey_number":"29","id":"e6b6b905-a355-4e85-84ca-db655cc3dce4"},{"starting_base":1,"first_name":"Kevin","last_name":"Pillar","preferred_name":"Kevin","jersey_number":"11","id":"7335e54f-cc2f-422c-808e-c19a267827a5"}]},{"hitter_id":"e6b6b905-a355-4e85-84ca-db655cc3dce4","pitcher_id":"05359fd7-6f1a-4c4b-8093-d63134f21b93","inning":7,"inning_half":"T","type":"pitch","hitter_outcome":"aD","id":"b817f4d8-6928-4840-a288-4a72e3aa9274","runners":[{"starting_base":2,"first_name":"Troy","last_name":"Tulowitzki","preferred_name":"Troy","jersey_number":"2","id":"9cc5e32a-1dad-4b18-80c8-919ec0dac676"}]},{"hitter_id":"44c2a812-101d-4955-a3e5-3085afa9296b","pitcher_id":"05359fd7-6f1a-4c4b-8093-d63134f21b93","inning":7,"inning_half":"T","type":"pitch","hitter_outcome":"aROE","id":"c99ba25c-80b2-4a86-917f-149df41742c0","runners":[{"starting_base":2,"first_name":"Devon","last_name":"Travis","preferred_name":"Devon","jersey_number":"29","id":"e6b6b905-a355-4e85-84ca-db655cc3dce4"}]}]},"pitching":{"win":{"preferred_name":"Chris","first_name":"Christopher","last_name":"Tillman","jersey_number":"30","status":"A","position":"P","primary_position":"SP","id":"cb4d530e-a63e-4328-b3a5-7307e168086e","win":10,"loss":1,"save":0,"hold":0,"blown_save":0},"loss":{"preferred_name":"Marcus","first_name":"Marcus","last_name":"Stroman","jersey_number":"6","status":"A","position":"P","primary_position":"SP","id":"cc86d4d3-1618-415e-b7fc-a303f3b8dd6f","win":6,"loss":3,"save":0,"hold":0,"blown_save":0},"hold":[{"preferred_name":"Brad","first_name":"Brad","last_name":"Brach","jersey_number":"35","status":"A","position":"P","primary_position":"RP","id":"b667e70a-4380-4459-b33b-df62653d41fd","win":5,"loss":1,"save":2,"hold":10,"blown_save":3}]}}},{"game":{"id":"f2747230-7df5-4535-a475-a1c823d0d654","status":"closed","coverage":"full","game_number":1,"day_night":"D","scheduled":"2016-06-19T18:10:00+00:00","home_team":"aa34e0ed-f342-4ec6-b774-c79b47b60e2d","away_team":"a09ec676-f887-43dc-bbb3-cf4bbaee9a18","attendance":29553,"duration":"3:00","double_header":false,"venue":{"name":"Target Field","market":"Minnesota","capacity":39504,"surface":"grass","address":"353 N 5th Street","city":"Minneapolis","state":"MN","zip":"55403","country":"USA","id":"302f8dcd-eed6-4b83-8609-81548d51e955","field_orientation":"E","stadium_type":"outdoor","location":{"lat":"44.98142199999999","lng":"-93.27847"}},"broadcast":{"network":"FS-N"},"final":{"inning":9,"inning_half":"T"},"home":{"name":"Twins","market":"Minnesota","abbr":"MIN","id":"aa34e0ed-f342-4ec6-b774-c79b47b60e2d","runs":7,"hits":11,"errors":2,"win":20,"loss":48,"probable_pitcher":{"preferred_name":"Ervin","first_name":"Ervin","last_name":"Santana","jersey_number":"54","id":"f6cac526-d361-4d8b-b74f-f035e0e15fd9","win":1,"loss":7,"era":5.097},"starting_pitcher":{"preferred_name":"Ervin","first_name":"Ervin","last_name":"Santana","jersey_number":"54","id":"f6cac526-d361-4d8b-b74f-f035e0e15fd9","win":1,"loss":7,"era":5.097},"scoring":[{"number":1,"sequence":1,"runs":0,"hits":0,"errors":0,"type":"inning"},{"number":2,"sequence":2,"runs":0,"hits":0,"errors":0,"type":"inning"},{"number":3,"sequence":3,"runs":0,"hits":1,"errors":0,"type":"inning"},{"number":4,"sequence":4,"runs":0,"hits":0,"errors":0,"type":"inning"},{"number":5,"sequence":5,"runs":1,"hits":2,"errors":0,"type":"inning"},{"number":6,"sequence":6,"runs":4,"hits":5,"errors":0,"type":"inning"},{"number":7,"sequence":7,"runs":1,"hits":1,"errors":0,"type":"inning"},{"number":8,"sequence":8,"runs":1,"hits":2,"errors":0,"type":"inning"}],"events":[{"hitter_id":"a16f6afb-dbff-42ad-9621-52b769d2f224","pitcher_id":"6dd571bc-b26c-4efc-87da-7b501c96faf1","inning":5,"inning_half":"B","type":"pitch","hitter_outcome":"aHR","id":"f3b7445e-e870-4d84-bb91-a9763e8d526d","runners":[{"starting_base":0,"first_name":"Maximilian","last_name":"Kepler","preferred_name":"Max","jersey_number":"26","id":"a16f6afb-dbff-42ad-9621-52b769d2f224"}]},{"hitter_id":"178af28f-f5bb-49e1-9770-71d6e39edb63","pitcher_id":"6dd571bc-b26c-4efc-87da-7b501c96faf1","inning":6,"inning_half":"B","type":"pitch","hitter_outcome":"aT","id":"d9066165-3059-4f07-b296-774f7e4a26e8","runners":[{"starting_base":1,"first_name":"Trevor","last_name":"Plouffe","preferred_name":"Trevor","jersey_number":"24","id":"b6871f2a-5dba-4760-874c-e3e323cfed70"},{"starting_base":3,"first_name":"James","last_name":"Dozier","preferred_name":"Brian","jersey_number":"2","id":"29a80d91-946d-4701-af7d-034850bdef00"}]},{"hitter_id":"a16f6afb-dbff-42ad-9621-52b769d2f224","pitcher_id":"41d695be-d912-4a4f-a75f-6e1078c3362a","inning":6,"inning_half":"B","type":"pitch","hitter_outcome":"aS","id":"4a6e2b11-1ab6-4f8d-b43b-6e9da0c0f181","runners":[{"starting_base":3,"first_name":"Eduardo","last_name":"Escobar","preferred_name":"Eduardo","jersey_number":"5","id":"178af28f-f5bb-49e1-9770-71d6e39edb63"}]},{"hitter_id":"6e455e9c-d760-4661-8258-90d1ee46bb9e","pitcher_id":"41d695be-d912-4a4f-a75f-6e1078c3362a","inning":6,"inning_half":"B","type":"pitch","hitter_outcome":"aD","id":"c461f80c-fdff-40c5-82f8-7c5ddcba4ba3","runners":[{"starting_base":2,"first_name":"Maximilian","last_name":"Kepler","preferred_name":"Max","jersey_number":"26","id":"a16f6afb-dbff-42ad-9621-52b769d2f224"}]},{"hitter_id":"29a80d91-946d-4701-af7d-034850bdef00","pitcher_id":"fe45e33b-f554-4856-af56-1f4f578eaa82","inning":7,"inning_half":"B","type":"pitch","hitter_outcome":"aHR","id":"7c933609-3a4d-40d4-b197-fe2b961924ff","runners":[{"starting_base":0,"first_name":"James","last_name":"Dozier","preferred_name":"Brian","jersey_number":"2","id":"29a80d91-946d-4701-af7d-034850bdef00"}]},{"hitter_id":"e33992e1-be5a-4107-a2ea-e9f372357ca6","pitcher_id":"1b5d6ad7-e1fa-46fe-a547-4926f17072ac","inning":8,"inning_half":"B","type":"pitch","hitter_outcome":"aS","id":"11b4104d-68cf-4f38-9f32-2aef6eb2a3ba","runners":[{"starting_base":3,"first_name":"Maximilian","last_name":"Kepler","preferred_name":"Max","jersey_number":"26","id":"a16f6afb-dbff-42ad-9621-52b769d2f224"}]}]},"away":{"name":"Yankees","market":"New York","abbr":"NYY","id":"a09ec676-f887-43dc-bbb3-cf4bbaee9a18","runs":4,"hits":7,"errors":0,"win":34,"loss":34,"probable_pitcher":{"preferred_name":"Nathan","first_name":"Nathan","last_name":"Eovaldi","jersey_number":"24","id":"6dd571bc-b26c-4efc-87da-7b501c96faf1","win":6,"loss":3,"era":4.898},"starting_pitcher":{"preferred_name":"Nathan","first_name":"Nathan","last_name":"Eovaldi","jersey_number":"24","id":"6dd571bc-b26c-4efc-87da-7b501c96faf1","win":6,"loss":3,"era":4.898},"scoring":[{"number":1,"sequence":1,"runs":0,"hits":0,"errors":0,"type":"inning"},{"number":2,"sequence":2,"runs":1,"hits":1,"errors":0,"type":"inning"},{"number":3,"sequence":3,"runs":0,"hits":0,"errors":0,"type":"inning"},{"number":4,"sequence":4,"runs":1,"hits":2,"errors":0,"type":"inning"},{"number":5,"sequence":5,"runs":0,"hits":0,"errors":0,"type":"inning"},{"number":6,"sequence":6,"runs":0,"hits":1,"errors":0,"type":"inning"},{"number":7,"sequence":7,"runs":0,"hits":1,"errors":0,"type":"inning"},{"number":8,"sequence":8,"runs":1,"hits":1,"errors":2,"type":"inning"},{"number":9,"sequence":9,"runs":1,"hits":1,"errors":0,"type":"inning"}],"events":[{"hitter_id":"eb4fe55f-14ba-4da5-ba4c-5e8df005fa0a","pitcher_id":"f6cac526-d361-4d8b-b74f-f035e0e15fd9","inning":2,"inning_half":"T","type":"pitch","hitter_outcome":"aHR","id":"13ac41ed-b7aa-48ea-8ea4-5512aa9cd580","runners":[{"starting_base":0,"first_name":"Brian","last_name":"McCann","preferred_name":"Brian","jersey_number":"34","id":"eb4fe55f-14ba-4da5-ba4c-5e8df005fa0a"}]},{"hitter_id":"9253ce81-0d6f-451e-b503-7b0435eb6cce","pitcher_id":"f6cac526-d361-4d8b-b74f-f035e0e15fd9","inning":4,"inning_half":"T","type":"pitch","hitter_outcome":"aS","id":"393042b5-19c1-4c9e-8532-e71b9dc62104","runners":[{"starting_base":2,"first_name":"Brett","last_name":"Gardner","preferred_name":"Brett","jersey_number":"11","id":"32362986-6bba-443c-927d-8b87153caf0d"}]},{"hitter_id":"32362986-6bba-443c-927d-8b87153caf0d","pitcher_id":"cf42953d-893f-4191-aab5-c1a94636efc8","inning":8,"inning_half":"T","type":"pitch","hitter_outcome":"aROE","id":"87e4fed2-fd2b-4feb-a84a-65bbc21c690e","runners":[{"starting_base":2,"first_name":"Isaac","last_name":"Davis","preferred_name":"Ike","jersey_number":"24","id":"e3641588-3ac8-4b44-8067-d7b92d2520cf"}]},{"hitter_id":"eb4fe55f-14ba-4da5-ba4c-5e8df005fa0a","pitcher_id":"e0d89956-1427-4b2f-9025-10330561e464","inning":9,"inning_half":"T","type":"pitch","hitter_outcome":"aHR","id":"8cea8496-f146-49bd-b5da-956925b8c5e6","runners":[{"starting_base":0,"first_name":"Brian","last_name":"McCann","preferred_name":"Brian","jersey_number":"34","id":"eb4fe55f-14ba-4da5-ba4c-5e8df005fa0a"}]}]},"pitching":{"win":{"preferred_name":"Ervin","first_name":"Ervin","last_name":"Santana","jersey_number":"54","status":"D10","position":"P","primary_position":"SP","id":"f6cac526-d361-4d8b-b74f-f035e0e15fd9","win":2,"loss":7,"save":0,"hold":0,"blown_save":0},"loss":{"preferred_name":"Nathan","first_name":"Nathan","last_name":"Eovaldi","jersey_number":"24","status":"D10","position":"P","primary_position":"SP","id":"6dd571bc-b26c-4efc-87da-7b501c96faf1","win":6,"loss":4,"save":0,"hold":0,"blown_save":0},"save":{"preferred_name":"Brandon","first_name":"Brandon","last_name":"Kintzler","jersey_number":"21","status":"A","position":"P","primary_position":"RP","id":"e0d89956-1427-4b2f-9025-10330561e464","win":0,"loss":0,"save":2,"hold":1,"blown_save":0}}}},{"game":{"id":"261e9162-6bc5-455c-bcb9-063347734e7b","status":"closed","coverage":"full","game_number":1,"day_night":"D","scheduled":"2016-06-19T20:05:00+00:00","home_team":"27a59d3b-ff7c-48ea-b016-4798f560f5e1","away_team":"4f735188-37c8-473d-ae32-1f7e34ccf892","attendance":22846,"duration":"2:19","double_header":false,"venue":{"name":"Oakland-Alameda County Coliseum","market":"Oakland","capacity":46765,"surface":"grass","address":"7000 Coliseum Way","city":"Oakland","state":"CA","zip":"94621","country":"USA","id":"48cbd35a-d932-4a75-beab-067bfbacfc26","field_orientation":"NE","stadium_type":"outdoor","location":{"lat":"37.7503423","lng":"-122.2028058"}},"broadcast":{"network":"CSNCA"},"final":{"inning":9,"inning_half":"B"},"home":{"name":"Athletics","market":"Oakland","abbr":"OAK","id":"27a59d3b-ff7c-48ea-b016-4798f560f5e1","runs":0,"hits":3,"errors":0,"win":28,"loss":40,"probable_pitcher":{"preferred_name":"Eric","first_name":"Eric","last_name":"Surkamp","id":"9bc3a4f7-58fe-4003-b8be-348b8a3d44fc","win":0,"loss":4,"era":8.069},"starting_pitcher":{"preferred_name":"Eric","first_name":"Eric","last_name":"Surkamp","id":"9bc3a4f7-58fe-4003-b8be-348b8a3d44fc","win":0,"loss":4,"era":8.069},"scoring":[{"number":1,"sequence":1,"runs":0,"hits":0,"errors":0,"type":"inning"},{"number":2,"sequence":2,"runs":0,"hits":1,"errors":0,"type":"inning"},{"number":3,"sequence":3,"runs":0,"hits":0,"errors":0,"type":"inning"},{"number":4,"sequence":4,"runs":0,"hits":0,"errors":0,"type":"inning"},{"number":5,"sequence":5,"runs":0,"hits":1,"errors":0,"type":"inning"},{"number":6,"sequence":6,"runs":0,"hits":0,"errors":0,"type":"inning"},{"number":7,"sequence":7,"runs":0,"hits":0,"errors":0,"type":"inning"},{"number":8,"sequence":8,"runs":0,"hits":1,"errors":0,"type":"inning"},{"number":9,"sequence":9,"runs":0,"hits":0,"errors":0,"type":"inning"}]},"away":{"name":"Angels","market":"Los Angeles","abbr":"LAA","id":"4f735188-37c8-473d-ae32-1f7e34ccf892","runs":2,"hits":7,"errors":0,"win":30,"loss":38,"probable_pitcher":{"preferred_name":"Jered","first_name":"Jered","last_name":"Weaver","id":"e27b8c66-79c6-4291-bf9a-effce3049ed6","win":5,"loss":6,"era":5.709},"starting_pitcher":{"preferred_name":"Jered","first_name":"Jered","last_name":"Weaver","id":"e27b8c66-79c6-4291-bf9a-effce3049ed6","win":5,"loss":6,"era":5.709},"scoring":[{"number":1,"sequence":1,"runs":1,"hits":1,"errors":0,"type":"inning"},{"number":2,"sequence":2,"runs":0,"hits":1,"errors":0,"type":"inning"},{"number":3,"sequence":3,"runs":0,"hits":1,"errors":0,"type":"inning"},{"number":4,"sequence":4,"runs":0,"hits":0,"errors":0,"type":"inning"},{"number":5,"sequence":5,"runs":1,"hits":2,"errors":0,"type":"inning"},{"number":6,"sequence":6,"runs":0,"hits":1,"errors":0,"type":"inning"},{"number":7,"sequence":7,"runs":0,"hits":0,"errors":0,"type":"inning"},{"number":8,"sequence":8,"runs":0,"hits":0,"errors":0,"type":"inning"},{"number":9,"sequence":9,"runs":0,"hits":1,"errors":0,"type":"inning"}],"events":[{"hitter_id":"fb061c77-5253-4181-ad7b-c68ef18aa511","pitcher_id":"9bc3a4f7-58fe-4003-b8be-348b8a3d44fc","inning":1,"inning_half":"T","type":"pitch","hitter_outcome":"oFC","id":"537e5382-8e8a-4e10-8fdd-6cd4ca01b1fc","runners":[{"starting_base":3,"first_name":"Yunel","last_name":"Escobar","preferred_name":"Yunel","jersey_number":"6","id":"9ca64cb3-b29b-4cb4-a048-a5919dcb44a3"}]},{"hitter_id":"6049097c-f59f-48d4-ae57-38f6027235a3","pitcher_id":"9bc3a4f7-58fe-4003-b8be-348b8a3d44fc","inning":5,"inning_half":"T","type":"pitch","hitter_outcome":"aHR","id":"9e5c1a7e-4535-4fe7-9b91-f81848aa2740","runners":[{"starting_base":0,"first_name":"Carlos","last_name":"Pérez","preferred_name":"Carlos","jersey_number":"58","id":"6049097c-f59f-48d4-ae57-38f6027235a3"}]}]},"pitching":{"win":{"preferred_name":"Jered","first_name":"Jered","last_name":"Weaver","status":"RET","position":"P","primary_position":"SP","id":"e27b8c66-79c6-4291-bf9a-effce3049ed6","win":6,"loss":6,"save":0,"hold":0,"blown_save":0},"loss":{"preferred_name":"Eric","first_name":"Eric","last_name":"Surkamp","status":"FA","position":"P","primary_position":"SP","id":"9bc3a4f7-58fe-4003-b8be-348b8a3d44fc","win":0,"loss":5,"save":0,"hold":0,"blown_save":0}}}},{"game":{"id":"96c8f7a1-db6c-42a4-9928-a4cdef8e3f60","status":"closed","coverage":"full","game_number":1,"day_night":"D","scheduled":"2016-06-19T18:10:00+00:00","home_team":"eb21dadd-8f10-4095-8bf3-dfb3b779f107","away_team":"c874a065-c115-4e7d-b0f0-235584fb0e6f","attendance":36369,"duration":"2:48","double_header":false,"venue":{"name":"Minute Maid Park","market":"Houston","capacity":41168,"surface":"grass","address":"501 Crawford Street","city":"Houston","state":"TX","zip":"77002","country":"USA","id":"f0600f04-1386-4c61-a412-804960c46cb1","field_orientation":"N","stadium_type":"retractable","location":{"lat":"29.7577058","lng":"-95.35453989999999"}},"broadcast":{"network":"ROOT SPORTS SW"},"final":{"inning":9,"inning_half":"T"},"home":{"name":"Astros","market":"Houston","abbr":"HOU","id":"eb21dadd-8f10-4095-8bf3-dfb3b779f107","runs":6,"hits":8,"errors":0,"win":33,"loss":36,"probable_pitcher":{"preferred_name":"Mike","first_name":"Michael","last_name":"Fiers","jersey_number":"50","id":"e0b021ce-33aa-46fc-b673-6bd35f220eb6","win":4,"loss":3,"era":4.765},"starting_pitcher":{"preferred_name":"Mike","first_name":"Michael","last_name":"Fiers","jersey_number":"50","id":"e0b021ce-33aa-46fc-b673-6bd35f220eb6","win":4,"loss":3,"era":4.765},"scoring":[{"number":1,"sequence":1,"runs":0,"hits":0,"errors":0,"type":"inning"},{"number":2,"sequence":2,"runs":2,"hits":3,"errors":0,"type":"inning"},{"number":3,"sequence":3,"runs":0,"hits":1,"errors":0,"type":"inning"},{"number":4,"sequence":4,"runs":0,"hits":0,"errors":0,"type":"inning"},{"number":5,"sequence":5,"runs":2,"hits":1,"errors":0,"type":"inning"},{"number":6,"sequence":6,"runs":0,"hits":0,"errors":0,"type":"inning"},{"number":7,"sequence":7,"runs":1,"hits":1,"errors":0,"type":"inning"},{"number":8,"sequence":8,"runs":1,"hits":2,"errors":0,"type":"inning"}],"events":[{"hitter_id":"ab823ce4-655b-4d1d-ba3e-23316d8053dc","pitcher_id":"d3bafaff-56a9-4998-8068-dade411976c6","inning":2,"inning_half":"B","type":"pitch","hitter_outcome":"aD","id":"51fe0647-797f-40a9-9096-2edfaafd6111","runners":[{"starting_base":1,"first_name":"Daniel","last_name":"Worth","preferred_name":"Danny","jersey_number":"26","id":"723092e2-fef9-42c6-87dc-763405451c43"}]},{"hitter_id":"988be7d6-536b-4aec-81af-710c6b3537b3","pitcher_id":"d3bafaff-56a9-4998-8068-dade411976c6","inning":2,"inning_half":"B","type":"pitch","hitter_outcome":"aS","id":"4132e19b-1f1b-4094-97b5-32d9e9968403","runners":[{"starting_base":2,"first_name":"James","last_name":"Gattis","preferred_name":"Evan","jersey_number":"11","id":"ab823ce4-655b-4d1d-ba3e-23316d8053dc"}]},{"hitter_id":"988be7d6-536b-4aec-81af-710c6b3537b3","pitcher_id":"d3bafaff-56a9-4998-8068-dade411976c6","inning":5,"inning_half":"B","type":"pitch","hitter_outcome":"aHR","id":"d74bf3f6-e598-4b01-ba4d-83198be88788","runners":[{"starting_base":0,"first_name":"Luis","last_name":"Valbuena","preferred_name":"Luis","jersey_number":"18","id":"988be7d6-536b-4aec-81af-710c6b3537b3"}]},{"hitter_id":"1616381c-d6ac-40b1-8c3f-c70d51bda098","pitcher_id":"d3bafaff-56a9-4998-8068-dade411976c6","inning":5,"inning_half":"B","type":"pitch","hitter_outcome":"oSF","id":"1d217aa9-85a5-4b97-a6c0-64114fbb05c4","runners":[{"starting_base":3,"first_name":"George","last_name":"Springer","preferred_name":"George","jersey_number":"4","id":"7f92278a-91c4-4c25-9e75-eaff3aed89b3"}]},{"hitter_id":"ab823ce4-655b-4d1d-ba3e-23316d8053dc","pitcher_id":"cef45d58-1030-4ae0-8a37-3a10ade752be","inning":7,"inning_half":"B","type":"pitch","hitter_outcome":"aHR","id":"b3c519bc-d6ba-49ff-b484-d979ab8aa5a0","runners":[{"starting_base":0,"first_name":"James","last_name":"Gattis","preferred_name":"Evan","jersey_number":"11","id":"ab823ce4-655b-4d1d-ba3e-23316d8053dc"}]},{"hitter_id":"d77fc18d-e11d-4ce8-b12c-9d08b913cb61","pitcher_id":"e7f69d9c-f311-466b-8f28-591255b49489","inning":8,"inning_half":"B","type":"pitch","hitter_outcome":"aD","id":"5e62437f-8007-4963-a577-0351deefc93a","runners":[{"starting_base":2,"first_name":"José","last_name":"Altuve","preferred_name":"José","jersey_number":"27","id":"1616381c-d6ac-40b1-8c3f-c70d51bda098"}]}]},"away":{"name":"Reds","market":"Cincinnati","abbr":"CIN","id":"c874a065-c115-4e7d-b0f0-235584fb0e6f","runs":0,"hits":5,"errors":0,"win":27,"loss":42,"probable_pitcher":{"preferred_name":"Brandon","first_name":"Brandon","last_name":"Finnegan","jersey_number":"29","id":"d3bafaff-56a9-4998-8068-dade411976c6","win":3,"loss":4,"era":3.607},"starting_pitcher":{"preferred_name":"Brandon","first_name":"Brandon","last_name":"Finnegan","jersey_number":"29","id":"d3bafaff-56a9-4998-8068-dade411976c6","win":3,"loss":4,"era":3.607},"scoring":[{"number":1,"sequence":1,"runs":0,"hits":1,"errors":0,"type":"inning"},{"number":2,"sequence":2,"runs":0,"hits":0,"errors":0,"type":"inning"},{"number":3,"sequence":3,"runs":0,"hits":1,"errors":0,"type":"inning"},{"number":4,"sequence":4,"runs":0,"hits":0,"errors":0,"type":"inning"},{"number":5,"sequence":5,"runs":0,"hits":1,"errors":0,"type":"inning"},{"number":6,"sequence":6,"runs":0,"hits":1,"errors":0,"type":"inning"},{"number":7,"sequence":7,"runs":0,"hits":0,"errors":0,"type":"inning"},{"number":8,"sequence":8,"runs":0,"hits":0,"errors":0,"type":"inning"},{"number":9,"sequence":9,"runs":0,"hits":1,"errors":0,"type":"inning"}]},"pitching":{"win":{"preferred_name":"Mike","first_name":"Michael","last_name":"Fiers","jersey_number":"50","status":"D10","position":"P","primary_position":"RP","id":"e0b021ce-33aa-46fc-b673-6bd35f220eb6","win":5,"loss":3,"save":0,"hold":0,"blown_save":0},"loss":{"preferred_name":"Brandon","first_name":"Brandon","last_name":"Finnegan","jersey_number":"29","status":"D10","position":"P","primary_position":"SP","id":"d3bafaff-56a9-4998-8068-dade411976c6","win":3,"loss":5,"save":0,"hold":0,"blown_save":0},"save":{"preferred_name":"Chris","first_name":"Christopher","last_name":"Devenski","jersey_number":"47","status":"A","position":"P","primary_position":"RP","id":"a9d45a51-418a-4539-8352-4817409eb481","win":0,"loss":2,"save":1,"hold":0,"blown_save":0}}}},{"game":{"id":"895c2851-22ee-41de-bc53-7bf4bdf010a0","status":"closed","coverage":"full","game_number":1,"day_night":"D","scheduled":"2016-06-19T20:40:00+00:00","home_team":"d52d5339-cbdd-43f3-9dfa-a42fd588b9a3","away_team":"d89bed32-3aee-4407-99e3-4103641b999a","attendance":32285,"duration":"2:59","double_header":false,"venue":{"name":"PETCO Park","market":"San Diego","capacity":42445,"surface":"grass","address":"100 Park Blvd.","city":"San Diego","state":"CA","zip":"92101","country":"USA","id":"0ab45d79-5475-4308-9f94-74b0c185ee6f","field_orientation":"N","stadium_type":"outdoor","location":{"lat":"32.70752890000001","lng":"-117.1568083"}},"broadcast":{"network":"FSSD"},"final":{"inning":9,"inning_half":"T"},"home":{"name":"Padres","market":"San Diego","abbr":"SD","id":"d52d5339-cbdd-43f3-9dfa-a42fd588b9a3","runs":6,"hits":10,"errors":0,"win":28,"loss":42,"probable_pitcher":{"preferred_name":"Drew","first_name":"Thomas","last_name":"Pomeranz","jersey_number":"31","id":"b2e4ccc4-0f7c-4ad6-a0bf-3186a6b57f8d","win":5,"loss":7,"era":2.88},"starting_pitcher":{"preferred_name":"Drew","first_name":"Thomas","last_name":"Pomeranz","jersey_number":"31","id":"b2e4ccc4-0f7c-4ad6-a0bf-3186a6b57f8d","win":5,"loss":7,"era":2.88},"scoring":[{"number":1,"sequence":1,"runs":1,"hits":2,"errors":0,"type":"inning"},{"number":2,"sequence":2,"runs":0,"hits":0,"errors":0,"type":"inning"},{"number":3,"sequence":3,"runs":0,"hits":0,"errors":0,"type":"inning"},{"number":4,"sequence":4,"runs":2,"hits":3,"errors":0,"type":"inning"},{"number":5,"sequence":5,"runs":2,"hits":2,"errors":1,"type":"inning"},{"number":6,"sequence":6,"runs":1,"hits":2,"errors":0,"type":"inning"},{"number":7,"sequence":7,"runs":0,"hits":0,"errors":0,"type":"inning"},{"number":8,"sequence":8,"runs":0,"hits":1,"errors":0,"type":"inning"}],"events":[{"hitter_id":"8b5827ef-6325-4183-8b40-fe30e50e20cd","pitcher_id":"0d674411-7f4d-4bc0-ba7a-853458580bab","inning":1,"inning_half":"B","type":"pitch","hitter_outcome":"aS","id":"ba1c49a1-0221-4f57-a08e-fbe6d20f2cee","runners":[{"starting_base":2,"first_name":"William","last_name":"Myers","preferred_name":"Wil","jersey_number":"4","id":"8f6f5bdf-9712-472e-8af5-12d5fb1e52e8"}]},{"hitter_id":"3b8b0765-15e5-4017-9121-98da070cb541","pitcher_id":"0d674411-7f4d-4bc0-ba7a-853458580bab","inning":4,"inning_half":"B","type":"pitch","hitter_outcome":"aD","id":"9ab84eb2-a38d-4c38-96b4-39d321c2bed8","runners":[{"starting_base":1,"first_name":"Derek","last_name":"Norris","preferred_name":"Derek","jersey_number":"3","id":"f71b4761-775b-47f2-a675-c1ee7114aa43"},{"starting_base":2,"first_name":"Melvin","last_name":"Upton","preferred_name":"Melvin","jersey_number":"2","id":"577a95ca-9043-4deb-963d-3b9aa6752d71"}]},{"hitter_id":"f71b4761-775b-47f2-a675-c1ee7114aa43","pitcher_id":"0d674411-7f4d-4bc0-ba7a-853458580bab","inning":5,"inning_half":"B","type":"pitch","hitter_outcome":"oSF","id":"e245bc94-0db8-45f4-baba-a29a6989d8db","runners":[{"starting_base":3,"first_name":"Yangervis","last_name":"Solarte","preferred_name":"Yangervis","jersey_number":"26","id":"8b5827ef-6325-4183-8b40-fe30e50e20cd"}]},{"hitter_id":"e3a93809-7a2d-4729-a1a6-7f3808fbdce7","pitcher_id":"0d674411-7f4d-4bc0-ba7a-853458580bab","inning":5,"inning_half":"B","type":"pitch","hitter_outcome":"aS","id":"bbaad58f-0da5-4151-9254-5bdd0b6f88e6","runners":[{"starting_base":2,"first_name":"Melvin","last_name":"Upton","preferred_name":"Melvin","jersey_number":"2","id":"577a95ca-9043-4deb-963d-3b9aa6752d71"}]},{"hitter_id":"f4c666e5-2a05-4258-8ddc-da6e0cffdb57","pitcher_id":"894fea8a-5b90-487c-9a95-8ff25be48b30","inning":6,"inning_half":"B","type":"pitch","hitter_outcome":"aS","id":"281fad40-5da6-476e-a072-821d3b232e2c","runners":[{"starting_base":2,"first_name":"Ryan","last_name":"Schimpf","preferred_name":"Ryan","jersey_number":"11","id":"ddfa098d-5e3b-4551-8cb8-bb762feaa37f"}]}]},"away":{"name":"Nationals","market":"Washington","abbr":"WSH","id":"d89bed32-3aee-4407-99e3-4103641b999a","runs":3,"hits":7,"errors":1,"win":43,"loss":26,"probable_pitcher":{"preferred_name":"Gio","first_name":"Giovany","last_name":"González","jersey_number":"47","id":"0d674411-7f4d-4bc0-ba7a-853458580bab","win":3,"loss":5,"era":3.957},"starting_pitcher":{"preferred_name":"Gio","first_name":"Giovany","last_name":"González","jersey_number":"47","id":"0d674411-7f4d-4bc0-ba7a-853458580bab","win":3,"loss":5,"era":3.957},"scoring":[{"number":1,"sequence":1,"runs":1,"hits":3,"errors":0,"type":"inning"},{"number":2,"sequence":2,"runs":0,"hits":0,"errors":0,"type":"inning"},{"number":3,"sequence":3,"runs":0,"hits":1,"errors":0,"type":"inning"},{"number":4,"sequence":4,"runs":0,"hits":0,"errors":0,"type":"inning"},{"number":5,"sequence":5,"runs":2,"hits":2,"errors":0,"type":"inning"},{"number":6,"sequence":6,"runs":0,"hits":0,"errors":0,"type":"inning"},{"number":7,"sequence":7,"runs":0,"hits":0,"errors":0,"type":"inning"},{"number":8,"sequence":8,"runs":0,"hits":1,"errors":0,"type":"inning"},{"number":9,"sequence":9,"runs":0,"hits":0,"errors":0,"type":"inning"}],"events":[{"hitter_id":"9fd5e31f-8188-48bf-a93b-c9d9dbd29265","pitcher_id":"b2e4ccc4-0f7c-4ad6-a0bf-3186a6b57f8d","inning":1,"inning_half":"T","type":"pitch","hitter_outcome":"aHR","id":"d72ce778-e564-43e4-82a2-62fdac538e67","runners":[{"starting_base":0,"first_name":"Michael","last_name":"Taylor","preferred_name":"Michael","jersey_number":"3","id":"9fd5e31f-8188-48bf-a93b-c9d9dbd29265"}]},{"hitter_id":"f9e77907-22a6-44dd-81f3-21c1dbdc06c9","pitcher_id":"b2e4ccc4-0f7c-4ad6-a0bf-3186a6b57f8d","inning":5,"inning_half":"T","type":"pitch","hitter_outcome":"aHR","id":"88378dc4-1118-4201-892e-25469ed2d1bc","runners":[{"starting_base":0,"first_name":"Daniel","last_name":"Espinosa","preferred_name":"Danny","jersey_number":"8","id":"f9e77907-22a6-44dd-81f3-21c1dbdc06c9"}]},{"hitter_id":"9fd5e31f-8188-48bf-a93b-c9d9dbd29265","pitcher_id":"b2e4ccc4-0f7c-4ad6-a0bf-3186a6b57f8d","inning":5,"inning_half":"T","type":"pitch","hitter_outcome":"aHR","id":"45862aaf-f212-4ad2-9d87-07b89cc213d6","runners":[{"starting_base":0,"first_name":"Michael","last_name":"Taylor","preferred_name":"Michael","jersey_number":"3","id":"9fd5e31f-8188-48bf-a93b-c9d9dbd29265"}]}]},"pitching":{"win":{"preferred_name":"Drew","first_name":"Thomas","last_name":"Pomeranz","jersey_number":"31","status":"D10","position":"P","primary_position":"SP","id":"b2e4ccc4-0f7c-4ad6-a0bf-3186a6b57f8d","win":6,"loss":7,"save":0,"hold":0,"blown_save":0},"loss":{"preferred_name":"Gio","first_name":"Giovany","last_name":"González","jersey_number":"47","status":"A","position":"P","primary_position":"SP","id":"0d674411-7f4d-4bc0-ba7a-853458580bab","win":3,"loss":6,"save":0,"hold":0,"blown_save":0},"save":{"preferred_name":"Fernando","first_name":"Fernando","last_name":"Rodney","jersey_number":"56","status":"A","position":"P","primary_position":"RP","id":"b99833a6-f9bf-48f2-b490-533aecef0a5d","win":0,"loss":1,"save":14,"hold":0,"blown_save":0},"hold":[{"preferred_name":"Ryan","first_name":"Ryan","last_name":"Buchter","jersey_number":"52","status":"A","position":"P","primary_position":"RP","id":"1dcf7717-ab4a-424f-9f37-5509ec1d8b2a","win":1,"loss":0,"save":1,"hold":10,"blown_save":1},{"preferred_name":"Carlos","first_name":"Carlos","last_name":"Villanueva","jersey_number":"23","status":"FA","position":"P","primary_position":"RP","id":"4e179243-e437-4fc6-8a2a-822f1248054a","win":1,"loss":0,"save":1,"hold":3,"blown_save":0}]}}},{"game":{"id":"cba55170-7b0f-4441-8c77-bfa9ef6584ef","status":"closed","coverage":"full","game_number":1,"day_night":"D","scheduled":"2016-06-19T17:10:00+00:00","home_team":"bdc11650-6f74-49c4-875e-778aeb7632d9","away_team":"a7723160-10b7-4277-a309-d8dd95a8ae65","attendance":17361,"duration":"3:30","double_header":false,"venue":{"name":"Tropicana Field","market":"Tampa Bay","capacity":42735,"surface":"turf","address":"One Tropicana Drive","city":"St. Petersburg","state":"FL","zip":"33705","country":"USA","id":"3aaaf4af-0f8c-49c1-8bf1-1780bb5a5f5c","field_orientation":"NE","stadium_type":"indoor","location":{"lat":"27.768188","lng":"-82.653408"}},"broadcast":{"network":"Sun Sports"},"final":{"inning":9,"inning_half":"B"},"home":{"name":"Rays","market":"Tampa Bay","abbr":"TB","id":"bdc11650-6f74-49c4-875e-778aeb7632d9","runs":1,"hits":7,"errors":0,"win":31,"loss":35,"probable_pitcher":{"preferred_name":"Jake","first_name":"Jacob","last_name":"Odorizzi","jersey_number":"12","id":"2acb215d-2d2a-4b75-89b0-1f9d51093b07","win":3,"loss":3,"era":3.791},"starting_pitcher":{"preferred_name":"Jake","first_name":"Jacob","last_name":"Odorizzi","jersey_number":"12","id":"2acb215d-2d2a-4b75-89b0-1f9d51093b07","win":3,"loss":3,"era":3.791},"scoring":[{"number":1,"sequence":1,"runs":1,"hits":2,"errors":2,"type":"inning"},{"number":2,"sequence":2,"runs":0,"hits":1,"errors":1,"type":"inning"},{"number":3,"sequence":3,"runs":0,"hits":1,"errors":0,"type":"inning"},{"number":4,"sequence":4,"runs":0,"hits":0,"errors":0,"type":"inning"},{"number":5,"sequence":5,"runs":0,"hits":0,"errors":0,"type":"inning"},{"number":6,"sequence":6,"runs":0,"hits":0,"errors":0,"type":"inning"},{"number":7,"sequence":7,"runs":0,"hits":1,"errors":0,"type":"inning"},{"number":8,"sequence":8,"runs":0,"hits":0,"errors":0,"type":"inning"},{"number":9,"sequence":9,"runs":0,"hits":2,"errors":0,"type":"inning"}],"events":[{"hitter_id":"8d6f801e-7f89-4a81-81ec-072f72604c8e","pitcher_id":"4972d0a8-eb5a-476b-b865-3e4b6375503e","inning":1,"inning_half":"B","type":"steal","id":"3fe7261e-22f3-4e1e-a6f4-7bfbaea77e6f","runners":[{"starting_base":3,"first_name":"John","last_name":"Forsythe","preferred_name":"Logan","jersey_number":"11","id":"d1c9fb51-c10d-4e06-923d-cd9b5dab07ed"}]}]},"away":{"name":"Giants","market":"San Francisco","abbr":"SF","id":"a7723160-10b7-4277-a309-d8dd95a8ae65","runs":5,"hits":9,"errors":3,"win":43,"loss":26,"probable_pitcher":{"preferred_name":"Jake","first_name":"Jacob","last_name":"Peavy","jersey_number":"22","id":"4972d0a8-eb5a-476b-b865-3e4b6375503e","win":3,"loss":6,"era":5.834},"starting_pitcher":{"preferred_name":"Jake","first_name":"Jacob","last_name":"Peavy","jersey_number":"22","id":"4972d0a8-eb5a-476b-b865-3e4b6375503e","win":3,"loss":6,"era":5.834},"scoring":[{"number":1,"sequence":1,"runs":0,"hits":1,"errors":0,"type":"inning"},{"number":2,"sequence":2,"runs":0,"hits":0,"errors":0,"type":"inning"},{"number":3,"sequence":3,"runs":0,"hits":0,"errors":0,"type":"inning"},{"number":4,"sequence":4,"runs":1,"hits":1,"errors":0,"type":"inning"},{"number":5,"sequence":5,"runs":0,"hits":2,"errors":0,"type":"inning"},{"number":6,"sequence":6,"runs":0,"hits":0,"errors":0,"type":"inning"},{"number":7,"sequence":7,"runs":0,"hits":1,"errors":0,"type":"inning"},{"number":8,"sequence":8,"runs":4,"hits":4,"errors":0,"type":"inning"},{"number":9,"sequence":9,"runs":0,"hits":0,"errors":0,"type":"inning"}],"events":[{"hitter_id":"36ee970b-0cff-4d50-b8ac-9bd16fae2dd1","pitcher_id":"2acb215d-2d2a-4b75-89b0-1f9d51093b07","inning":4,"inning_half":"T","type":"pitch","hitter_outcome":"aHR","id":"7d9d97fb-2815-481a-a20a-dbd2b533f9d0","runners":[{"starting_base":0,"first_name":"Brandon","last_name":"Belt","preferred_name":"Brandon","jersey_number":"9","id":"36ee970b-0cff-4d50-b8ac-9bd16fae2dd1"}]},{"hitter_id":"e47bf865-f612-47f6-8a21-3110bb455e31","pitcher_id":"3f6d6a49-1361-441c-9145-e49f690587b7","inning":8,"inning_half":"T","type":"pitch","hitter_outcome":"aS","id":"78ea0bde-dfdd-427d-90e8-51ffa1ab551e","runners":[{"starting_base":2,"first_name":"Gregor","last_name":"Blanco","preferred_name":"Gregor","jersey_number":"7","id":"cbb197fc-6321-4a20-b931-b7260496a8b7"}]},{"hitter_id":"898c62b6-95bf-4973-a435-c6cb42a52158","pitcher_id":"67e06cae-58d0-4abf-9ef0-f1cf5c176538","inning":8,"inning_half":"T","type":"pitch","hitter_outcome":"aS","id":"b893e185-9a1d-49b3-bc8d-6cc8adeadf56","runners":[{"starting_base":2,"first_name":"Joseph","last_name":"Panik","preferred_name":"Joe","jersey_number":"12","id":"e47bf865-f612-47f6-8a21-3110bb455e31"}]},{"hitter_id":"f6aad1bd-fb2f-4c2e-92a5-8fe15f6ca36f","pitcher_id":"67e06cae-58d0-4abf-9ef0-f1cf5c176538","inning":8,"inning_half":"T","type":"pitch","hitter_outcome":"aD","id":"27b7f17d-31c5-4b88-9432-1e6f7b7a1d60","runners":[{"starting_base":1,"first_name":"Gerald","last_name":"Posey","preferred_name":"Buster","jersey_number":"28","id":"898c62b6-95bf-4973-a435-c6cb42a52158"},{"starting_base":3,"first_name":"Brandon","last_name":"Belt","preferred_name":"Brandon","jersey_number":"9","id":"36ee970b-0cff-4d50-b8ac-9bd16fae2dd1"}]}]},"pitching":{"win":{"preferred_name":"Derek","first_name":"Derek","last_name":"Law","jersey_number":"64","status":"MIN","position":"P","primary_position":"RP","id":"4b3f17a9-80c5-4a06-87b6-c515f3c34c42","win":2,"loss":1,"save":1,"hold":2,"blown_save":0},"loss":{"preferred_name":"Xavier","first_name":"Xavier","last_name":"Cedeño","status":"MIN","position":"P","primary_position":"RP","id":"3f6d6a49-1361-441c-9145-e49f690587b7","win":3,"loss":2,"save":0,"hold":14,"blown_save":3}}}},{"game":{"id":"a8e5300f-9c50-47c8-815b-842ae568bd16","status":"closed","coverage":"full","game_number":1,"day_night":"D","scheduled":"2016-06-19T18:15:00+00:00","home_team":"44671792-dc02-4fdd-a5ad-f5f17edaa9d7","away_team":"d99f919b-1534-4516-8e8a-9cd106c6d8cd","attendance":44897,"duration":"2:58","double_header":false,"venue":{"name":"Busch Stadium","market":"St. Louis","capacity":45538,"surface":"grass","address":"700 Clark Street","city":"St. Louis","state":"MO","zip":"63102","country":"USA","id":"83cc591a-1096-4383-a6ca-e2bd6f8db629","field_orientation":"NE","stadium_type":"outdoor","location":{"lat":"38.6226441","lng":"-90.1928125"}},"broadcast":{"network":"FS-M"},"final":{"inning":9,"inning_half":"B"},"home":{"name":"Cardinals","market":"St. Louis","abbr":"STL","id":"44671792-dc02-4fdd-a5ad-f5f17edaa9d7","runs":4,"hits":10,"errors":1,"win":35,"loss":32,"probable_pitcher":{"preferred_name":"Mike","first_name":"Michael","last_name":"Leake","jersey_number":"8","id":"7b54341a-7d39-4ea6-8b94-19ef145c8fba","win":5,"loss":4,"era":4.078},"starting_pitcher":{"preferred_name":"Mike","first_name":"Michael","last_name":"Leake","jersey_number":"8","id":"7b54341a-7d39-4ea6-8b94-19ef145c8fba","win":5,"loss":4,"era":4.078},"scoring":[{"number":1,"sequence":1,"runs":0,"hits":0,"errors":0,"type":"inning"},{"number":2,"sequence":2,"runs":1,"hits":1,"errors":0,"type":"inning"},{"number":3,"sequence":3,"runs":1,"hits":3,"errors":0,"type":"inning"},{"number":4,"sequence":4,"runs":0,"hits":1,"errors":1,"type":"inning"},{"number":5,"sequence":5,"runs":0,"hits":1,"errors":0,"type":"inning"},{"number":6,"sequence":6,"runs":2,"hits":2,"errors":0,"type":"inning"},{"number":7,"sequence":7,"runs":0,"hits":1,"errors":0,"type":"inning"},{"number":8,"sequence":8,"runs":0,"hits":0,"errors":0,"type":"inning"},{"number":9,"sequence":9,"runs":0,"hits":1,"errors":0,"type":"inning"}],"events":[{"hitter_id":"5a319b37-0c79-4859-8071-847c3ad7d9a0","pitcher_id":"9012e198-9f53-4885-8b24-402e51524e82","inning":2,"inning_half":"B","type":"pitch","hitter_outcome":"aHR","id":"01a684d5-808b-4fb8-82b4-d6bb04c54144","runners":[{"starting_base":0,"first_name":"Stephen","last_name":"Piscotty","preferred_name":"Stephen","jersey_number":"55","id":"5a319b37-0c79-4859-8071-847c3ad7d9a0"}]},{"hitter_id":"4083c6af-3416-4fb4-9b7e-d93e95640c86","pitcher_id":"9012e198-9f53-4885-8b24-402e51524e82","inning":3,"inning_half":"B","type":"pitch","hitter_outcome":"oSF","id":"edfdc2a6-dd7e-4e88-a5d6-c37d9dc51328","runners":[{"starting_base":3,"first_name":"Michael","last_name":"Leake","preferred_name":"Mike","jersey_number":"8","id":"7b54341a-7d39-4ea6-8b94-19ef145c8fba"}]},{"hitter_id":"4083c6af-3416-4fb4-9b7e-d93e95640c86","pitcher_id":"9012e198-9f53-4885-8b24-402e51524e82","inning":6,"inning_half":"B","type":"pitch","hitter_outcome":"aHR","id":"93cba20d-7dd4-422f-b74f-1d32976c11eb","runners":[{"starting_base":0,"first_name":"Matthew","last_name":"Holliday","preferred_name":"Matt","jersey_number":"7","id":"4083c6af-3416-4fb4-9b7e-d93e95640c86"}]},{"hitter_id":"8299081e-0173-46c5-be15-c4391eb58cbb","pitcher_id":"06b32645-a453-44b3-ac8a-db41c7ebead3","inning":6,"inning_half":"B","type":"pitch","hitter_outcome":"bB","id":"e551b0cd-0552-4786-98cd-c7fc23df476b","runners":[{"starting_base":3,"first_name":"Stephen","last_name":"Piscotty","preferred_name":"Stephen","jersey_number":"55","id":"5a319b37-0c79-4859-8071-847c3ad7d9a0"}]}]},"away":{"name":"Rangers","market":"Texas","abbr":"TEX","id":"d99f919b-1534-4516-8e8a-9cd106c6d8cd","runs":5,"hits":10,"errors":1,"win":44,"loss":25,"probable_pitcher":{"preferred_name":"Martín","first_name":"Martín","last_name":"Pérez","jersey_number":"33","id":"9012e198-9f53-4885-8b24-402e51524e82","win":6,"loss":4,"era":3.375},"starting_pitcher":{"preferred_name":"Martín","first_name":"Martín","last_name":"Pérez","jersey_number":"33","id":"9012e198-9f53-4885-8b24-402e51524e82","win":6,"loss":4,"era":3.375},"scoring":[{"number":1,"sequence":1,"runs":1,"hits":1,"errors":1,"type":"inning"},{"number":2,"sequence":2,"runs":0,"hits":0,"errors":0,"type":"inning"},{"number":3,"sequence":3,"runs":0,"hits":2,"errors":0,"type":"inning"},{"number":4,"sequence":4,"runs":1,"hits":2,"errors":0,"type":"inning"},{"number":5,"sequence":5,"runs":0,"hits":0,"errors":0,"type":"inning"},{"number":6,"sequence":6,"runs":1,"hits":3,"errors":0,"type":"inning"},{"number":7,"sequence":7,"runs":0,"hits":0,"errors":0,"type":"inning"},{"number":8,"sequence":8,"runs":2,"hits":2,"errors":0,"type":"inning"},{"number":9,"sequence":9,"runs":0,"hits":0,"errors":0,"type":"inning"}],"events":[{"hitter_id":"141d06a7-bef6-4d75-8bcb-7ed64be0d16e","pitcher_id":"7b54341a-7d39-4ea6-8b94-19ef145c8fba","inning":1,"inning_half":"T","type":"pitch","hitter_outcome":"oSF","id":"0abaf610-18ee-4642-904b-3080b3bd4837","runners":[{"starting_base":3,"first_name":"Ian","last_name":"Desmond","preferred_name":"Ian","jersey_number":"20","id":"fac92698-ed41-4615-8e1e-cd552612c5cf"}]},{"hitter_id":"a4f08027-ddc7-4e2d-ac69-9fc4f1c67bfd","pitcher_id":"7b54341a-7d39-4ea6-8b94-19ef145c8fba","inning":4,"inning_half":"T","type":"pitch","hitter_outcome":"aHR","id":"a6f5da75-bf5c-4065-ada0-00b917146ea0","runners":[{"starting_base":0,"first_name":"Mitchell","last_name":"Moreland","preferred_name":"Mitch","jersey_number":"18","id":"a4f08027-ddc7-4e2d-ac69-9fc4f1c67bfd"}]},{"hitter_id":"141d06a7-bef6-4d75-8bcb-7ed64be0d16e","pitcher_id":"7b54341a-7d39-4ea6-8b94-19ef145c8fba","inning":6,"inning_half":"T","type":"pitch","hitter_outcome":"aHR","id":"e61fb9bc-89a2-47f5-a105-e2b73c5c17eb","runners":[{"starting_base":0,"first_name":"Nomar","last_name":"Mazara","preferred_name":"Nomar","jersey_number":"30","id":"141d06a7-bef6-4d75-8bcb-7ed64be0d16e"}]},{"hitter_id":"75ba17fd-160d-4695-86af-7c614cb8f264","pitcher_id":"c565a293-6c2e-4976-bb1c-c8921ecf4c6e","inning":8,"inning_half":"T","type":"pitch","hitter_outcome":"aS","id":"56dbf267-e5e0-4ee0-9483-fe04c09abae8","runners":[{"starting_base":2,"first_name":"Mitchell","last_name":"Moreland","preferred_name":"Mitch","jersey_number":"18","id":"a4f08027-ddc7-4e2d-ac69-9fc4f1c67bfd"},{"starting_base":3,"first_name":"Rougned","last_name":"Odor","preferred_name":"Rougned","jersey_number":"12","id":"f2954280-cd18-4cba-bf61-321e37f730c5"}]}]},"pitching":{"win":{"preferred_name":"Tony","first_name":"Anthony","last_name":"Barnette","jersey_number":"43","status":"D10","position":"P","primary_position":"RP","id":"06b32645-a453-44b3-ac8a-db41c7ebead3","win":4,"loss":2,"save":0,"hold":9,"blown_save":0},"loss":{"preferred_name":"Matt","first_name":"Matthew","last_name":"Bowman","jersey_number":"67","status":"A","position":"P","primary_position":"RP","id":"c565a293-6c2e-4976-bb1c-c8921ecf4c6e","win":1,"loss":2,"save":0,"hold":1,"blown_save":1},"save":{"preferred_name":"Sam","first_name":"Samuel","last_name":"Dyson","jersey_number":"49","status":"A","position":"P","primary_position":"RP","id":"ee01fdc0-ef9d-4352-9ad9-b1331ce88f09","win":1,"loss":1,"save":13,"hold":10,"blown_save":1},"hold":[{"preferred_name":"Matt","first_name":"Matthew","last_name":"Bush","jersey_number":"51","status":"A","position":"P","primary_position":"RP","id":"d7eed2b7-584e-42d8-9e45-a27944434ebb","win":2,"loss":0,"save":0,"hold":8,"blown_save":0}],"blown_save":[{"preferred_name":"Matt","first_name":"Matthew","last_name":"Bowman","jersey_number":"67","status":"A","position":"P","primary_position":"RP","id":"c565a293-6c2e-4976-bb1c-c8921ecf4c6e","win":1,"loss":2,"save":0,"hold":1,"blown_save":1}]}}},{"game":{"id":"723be4ad-f6fa-4f11-8cce-37d3b943f9cb","status":"closed","coverage":"full","game_number":1,"day_night":"D","scheduled":"2016-06-19T17:35:00+00:00","home_team":"93941372-eb4c-4c40-aced-fe3267174393","away_team":"43a39081-52b4-4f93-ad29-da7f329ea960","attendance":37211,"duration":"3:05","double_header":false,"venue":{"name":"Fenway Park","market":"Boston","capacity":37731,"surface":"grass","address":"4 Yawkey Way","city":"Boston","state":"MA","zip":"02215","country":"USA","id":"b27b0dc5-c2c5-401d-b8b9-a6a2dbc225e5","field_orientation":"NE","stadium_type":"outdoor","location":{"lat":"42.34584359999999","lng":"-71.09878189999999"}},"broadcast":{"network":"NESN"},"final":{"inning":9,"inning_half":"T"},"home":{"name":"Red Sox","market":"Boston","abbr":"BOS","id":"93941372-eb4c-4c40-aced-fe3267174393","runs":2,"hits":11,"errors":0,"win":38,"loss":29,"probable_pitcher":{"preferred_name":"David","first_name":"David","last_name":"Price","jersey_number":"24","id":"875b903a-aabd-424e-b70e-1aa46a7334bc","win":7,"loss":4,"era":4.516},"starting_pitcher":{"preferred_name":"David","first_name":"David","last_name":"Price","jersey_number":"24","id":"875b903a-aabd-424e-b70e-1aa46a7334bc","win":7,"loss":4,"era":4.516},"scoring":[{"number":1,"sequence":1,"runs":0,"hits":1,"errors":0,"type":"inning"},{"number":2,"sequence":2,"runs":0,"hits":2,"errors":0,"type":"inning"},{"number":3,"sequence":3,"runs":0,"hits":2,"errors":0,"type":"inning"},{"number":4,"sequence":4,"runs":0,"hits":1,"errors":0,"type":"inning"},{"number":5,"sequence":5,"runs":0,"hits":0,"errors":0,"type":"inning"},{"number":6,"sequence":6,"runs":1,"hits":3,"errors":0,"type":"inning"},{"number":7,"sequence":7,"runs":1,"hits":1,"errors":0,"type":"inning"},{"number":8,"sequence":8,"runs":0,"hits":1,"errors":0,"type":"inning"}],"events":[{"hitter_id":"e9d2b083-2e0b-45aa-bbd4-4e62435d2a9e","pitcher_id":"811dd9ee-65cc-454a-8977-9e043b49bc9d","inning":6,"inning_half":"B","type":"pitch","hitter_outcome":"oFC","id":"e3ff482f-8786-4931-8d45-f7ffc24511ad","runners":[{"starting_base":3,"first_name":"Xander","last_name":"Bogaerts","preferred_name":"Xander","jersey_number":"2","id":"272abdba-ae99-4137-a6dd-5615f234adfc"}]},{"hitter_id":"084d2514-9ffb-414e-ae16-3bc690aaad51","pitcher_id":"26db575b-359f-40b1-92c8-dfc549b72a25","inning":7,"inning_half":"B","type":"pitch","hitter_outcome":"aHR","id":"988ccf2e-58b9-4ce0-b5d2-3f2f23a2aa06","runners":[{"starting_base":0,"first_name":"Markus","last_name":"Betts","preferred_name":"Mookie","jersey_number":"50","id":"084d2514-9ffb-414e-ae16-3bc690aaad51"}]}]},"away":{"name":"Mariners","market":"Seattle","abbr":"SEA","id":"43a39081-52b4-4f93-ad29-da7f329ea960","runs":1,"hits":8,"errors":0,"win":36,"loss":32,"probable_pitcher":{"preferred_name":"Taijuan","first_name":"Taijuan","last_name":"Walker","jersey_number":"99","id":"515af486-d938-4cb6-90e4-943323a5737c","win":3,"loss":6,"era":3.693},"starting_pitcher":{"preferred_name":"Taijuan","first_name":"Taijuan","last_name":"Walker","jersey_number":"99","id":"515af486-d938-4cb6-90e4-943323a5737c","win":3,"loss":6,"era":3.693},"scoring":[{"number":1,"sequence":1,"runs":0,"hits":1,"errors":0,"type":"inning"},{"number":2,"sequence":2,"runs":0,"hits":1,"errors":0,"type":"inning"},{"number":3,"sequence":3,"runs":0,"hits":0,"errors":0,"type":"inning"},{"number":4,"sequence":4,"runs":1,"hits":2,"errors":0,"type":"inning"},{"number":5,"sequence":5,"runs":0,"hits":1,"errors":0,"type":"inning"},{"number":6,"sequence":6,"runs":0,"hits":2,"errors":0,"type":"inning"},{"number":7,"sequence":7,"runs":0,"hits":1,"errors":0,"type":"inning"},{"number":8,"sequence":8,"runs":0,"hits":0,"errors":0,"type":"inning"},{"number":9,"sequence":9,"runs":0,"hits":0,"errors":0,"type":"inning"}],"events":[{"hitter_id":"46d96513-fa0b-4788-8f24-ac9b415ab6d6","pitcher_id":"875b903a-aabd-424e-b70e-1aa46a7334bc","inning":4,"inning_half":"T","type":"pitch","hitter_outcome":"aHR","id":"df1dcc9c-2233-4708-a02e-2b52bc332196","runners":[{"starting_base":0,"first_name":"Franklin","last_name":"Gutiérrez","preferred_name":"Franklin","jersey_number":"21","id":"46d96513-fa0b-4788-8f24-ac9b415ab6d6"}]}]},"pitching":{"win":{"preferred_name":"David","first_name":"David","last_name":"Price","jersey_number":"24","status":"A","position":"P","primary_position":"SP","id":"875b903a-aabd-424e-b70e-1aa46a7334bc","win":8,"loss":4,"save":0,"hold":0,"blown_save":0},"loss":{"preferred_name":"Edwin","first_name":"Edwin","last_name":"Díaz","jersey_number":"39","status":"A","position":"P","primary_position":"RP","id":"26db575b-359f-40b1-92c8-dfc549b72a25","win":0,"loss":1,"save":0,"hold":2,"blown_save":0},"save":{"preferred_name":"Craig","first_name":"Craig","last_name":"Kimbrel","jersey_number":"46","status":"A","position":"P","primary_position":"RP","id":"c4a8a308-1517-4c0e-a8af-f8cd824525cc","win":0,"loss":2,"save":16,"hold":0,"blown_save":2},"blown_save":[{"preferred_name":"Vidal","first_name":"Vidal","last_name":"Nuño","status":"MIN","position":"P","primary_position":"RP","id":"811dd9ee-65cc-454a-8977-9e043b49bc9d","win":0,"loss":0,"save":0,"hold":7,"blown_save":2}]}}},{"game":{"id":"9a4b8096-698d-4f14-9b31-81b6e044da6f","status":"closed","coverage":"full","game_number":1,"day_night":"N","scheduled":"2016-06-20T00:08:00+00:00","home_team":"55714da8-fcaf-4574-8443-59bfb511a524","away_team":"481dfe7e-5dab-46ab-a49f-9dcc2b6e2cfd","attendance":41024,"duration":"3:23","double_header":false,"venue":{"name":"Wrigley Field","market":"Chicago","capacity":41649,"surface":"grass","address":"1060 West Addison Street","city":"Chicago","state":"IL","zip":"60613","country":"USA","id":"53f8eb0d-a361-4a7a-930b-2f8735ea0698","field_orientation":"NE","stadium_type":"outdoor","location":{"lat":"41.9474473","lng":"-87.6560538"}},"broadcast":{"network":"ESPN"},"final":{"inning":9,"inning_half":"T"},"home":{"name":"Cubs","market":"Chicago","abbr":"CHC","id":"55714da8-fcaf-4574-8443-59bfb511a524","runs":10,"hits":14,"errors":1,"win":46,"loss":20,"probable_pitcher":{"preferred_name":"Kyle","first_name":"Kyle","last_name":"Hendricks","jersey_number":"28","id":"dec510da-0104-48f0-892f-37a9ab9d02ff","win":4,"loss":6,"era":3.054},"starting_pitcher":{"preferred_name":"Kyle","first_name":"Kyle","last_name":"Hendricks","jersey_number":"28","id":"dec510da-0104-48f0-892f-37a9ab9d02ff","win":4,"loss":6,"era":3.054},"scoring":[{"number":1,"sequence":1,"runs":1,"hits":2,"errors":0,"type":"inning"},{"number":2,"sequence":2,"runs":1,"hits":2,"errors":0,"type":"inning"},{"number":3,"sequence":3,"runs":2,"hits":4,"errors":0,"type":"inning"},{"number":4,"sequence":4,"runs":0,"hits":0,"errors":0,"type":"inning"},{"number":5,"sequence":5,"runs":0,"hits":0,"errors":0,"type":"inning"},{"number":6,"sequence":6,"runs":2,"hits":2,"errors":0,"type":"inning"},{"number":7,"sequence":7,"runs":4,"hits":3,"errors":0,"type":"inning"},{"number":8,"sequence":8,"runs":0,"hits":1,"errors":0,"type":"inning"}],"events":[{"hitter_id":"75cb4b6c-a087-4b77-90e3-7473284fa8ad","pitcher_id":"0b4c4345-7609-4ab1-9aaa-41d56d7f1fda","inning":1,"inning_half":"B","type":"pitch","hitter_outcome":"aS","id":"26b2cc46-5422-4b3e-8026-39303a428926","runners":[{"starting_base":3,"first_name":"Christopher","last_name":"Coghlan","preferred_name":"Chris","jersey_number":"3","id":"8dcb75a4-2928-4cd2-bcbd-cd5f79601e41"}]},{"hitter_id":"497c4595-bd0f-4a9e-b9cf-cb2eacb735bb","pitcher_id":"0b4c4345-7609-4ab1-9aaa-41d56d7f1fda","inning":2,"inning_half":"B","type":"pitch","hitter_outcome":"aHR","id":"f3533cb5-426b-4b61-baed-2f4f40c6bbaf","runners":[{"starting_base":0,"first_name":"Ednel","last_name":"Báez","preferred_name":"Javier","jersey_number":"9","id":"497c4595-bd0f-4a9e-b9cf-cb2eacb735bb"}]},{"hitter_id":"e1633ff9-8c46-4698-9bea-3eecd478fa94","pitcher_id":"0b4c4345-7609-4ab1-9aaa-41d56d7f1fda","inning":3,"inning_half":"B","type":"pitch","hitter_outcome":"aHR","id":"a6fe4fac-9aad-4eeb-86d8-6eff32882e25","runners":[{"starting_base":0,"first_name":"Kristopher","last_name":"Bryant","preferred_name":"Kris","jersey_number":"17","id":"e1633ff9-8c46-4698-9bea-3eecd478fa94"}]},{"hitter_id":"75cb4b6c-a087-4b77-90e3-7473284fa8ad","pitcher_id":"0b4c4345-7609-4ab1-9aaa-41d56d7f1fda","inning":3,"inning_half":"B","type":"pitch","hitter_outcome":"aHR","id":"dd0be125-3415-4016-bc92-122603433cd5","runners":[{"starting_base":0,"first_name":"Anthony","last_name":"Rizzo","preferred_name":"Anthony","jersey_number":"44","id":"75cb4b6c-a087-4b77-90e3-7473284fa8ad"}]},{"hitter_id":"9d93f121-f032-407d-bb30-ad3593641db9","pitcher_id":"8bc7b56e-d983-47be-acba-8c68248967d5","inning":6,"inning_half":"B","type":"pitch","hitter_outcome":"aHR","id":"65e7821d-df8f-4e1a-bb54-87d6769c0116","runners":[{"starting_base":0,"first_name":"Willson","last_name":"Contreras","preferred_name":"Willson","jersey_number":"40","id":"9d93f121-f032-407d-bb30-ad3593641db9"},{"starting_base":1,"first_name":"Ednel","last_name":"Báez","preferred_name":"Javier","jersey_number":"9","id":"497c4595-bd0f-4a9e-b9cf-cb2eacb735bb"}]},{"hitter_id":"75cb4b6c-a087-4b77-90e3-7473284fa8ad","pitcher_id":"f04ffea0-ed40-45d8-abf4-f7f3cabebec5","inning":7,"inning_half":"B","type":"pitch","hitter_outcome":"aS","id":"e1e6d138-2e07-4927-9400-c6bf7a516aa2","runners":[{"starting_base":2,"first_name":"Jason","last_name":"Heyward","preferred_name":"Jason","jersey_number":"22","id":"8e42fd09-b9d0-4566-b960-e107f580de46"}]},{"hitter_id":"13987736-aaaa-4d5b-a126-5158e2202fe2","pitcher_id":"5a7b41ae-d46c-4430-8e42-63d448935789","inning":7,"inning_half":"B","type":"pitch","hitter_outcome":"oFC","id":"23ff39cd-a92a-4834-8858-254af8bfd86b","runners":[{"starting_base":3,"first_name":"Kristopher","last_name":"Bryant","preferred_name":"Kris","jersey_number":"17","id":"e1633ff9-8c46-4698-9bea-3eecd478fa94"}]},{"hitter_id":"408b2324-83a9-4366-a3b4-9883f2c46260","pitcher_id":"5a7b41ae-d46c-4430-8e42-63d448935789","inning":7,"inning_half":"B","type":"pitch","hitter_outcome":"aHR","id":"b5d4ea5b-59bb-45ae-adc7-6ff09c7254fb","runners":[{"starting_base":0,"first_name":"Addison","last_name":"Russell","preferred_name":"Addison","jersey_number":"27","id":"408b2324-83a9-4366-a3b4-9883f2c46260"},{"starting_base":3,"first_name":"Anthony","last_name":"Rizzo","preferred_name":"Anthony","jersey_number":"44","id":"75cb4b6c-a087-4b77-90e3-7473284fa8ad"}]}]},"away":{"name":"Pirates","market":"Pittsburgh","abbr":"PIT","id":"481dfe7e-5dab-46ab-a49f-9dcc2b6e2cfd","runs":5,"hits":13,"errors":0,"win":33,"loss":35,"probable_pitcher":{"preferred_name":"Jameson","first_name":"Jameson","last_name":"Taillon","jersey_number":"50","id":"0b4c4345-7609-4ab1-9aaa-41d56d7f1fda","win":1,"loss":0,"era":1.929},"starting_pitcher":{"preferred_name":"Jameson","first_name":"Jameson","last_name":"Taillon","jersey_number":"50","id":"0b4c4345-7609-4ab1-9aaa-41d56d7f1fda","win":1,"loss":0,"era":1.929},"scoring":[{"number":1,"sequence":1,"runs":0,"hits":0,"errors":0,"type":"inning"},{"number":2,"sequence":2,"runs":0,"hits":2,"errors":0,"type":"inning"},{"number":3,"sequence":3,"runs":0,"hits":1,"errors":0,"type":"inning"},{"number":4,"sequence":4,"runs":1,"hits":2,"errors":0,"type":"inning"},{"number":5,"sequence":5,"runs":0,"hits":1,"errors":0,"type":"inning"},{"number":6,"sequence":6,"runs":0,"hits":1,"errors":1,"type":"inning"},{"number":7,"sequence":7,"runs":3,"hits":3,"errors":0,"type":"inning"},{"number":8,"sequence":8,"runs":0,"hits":0,"errors":0,"type":"inning"},{"number":9,"sequence":9,"runs":1,"hits":3,"errors":0,"type":"inning"}],"events":[{"hitter_id":"0e762dec-639f-497f-a65b-af0eaa8be39f","pitcher_id":"dec510da-0104-48f0-892f-37a9ab9d02ff","inning":4,"inning_half":"T","type":"pitch","hitter_outcome":"aHR","id":"1b695d7c-1cad-471b-8713-ff2bab086cd2","runners":[{"starting_base":0,"first_name":"Joshua","last_name":"Harrison","preferred_name":"Josh","jersey_number":"5","id":"0e762dec-639f-497f-a65b-af0eaa8be39f"}]},{"hitter_id":"1c58cf18-0d61-479d-9438-0a4057f552ef","pitcher_id":"6ea9ca2c-55ff-407d-99ef-8f3e741af0a7","inning":7,"inning_half":"T","type":"pitch","hitter_outcome":"aT","id":"0a0502a9-28c4-432a-99c2-68b737e6be36","runners":[{"starting_base":1,"first_name":"Andrew","last_name":"McCutchen","preferred_name":"Andrew","jersey_number":"22","id":"53a80099-966e-451c-a1e2-dccbb16f8dd8"},{"starting_base":3,"first_name":"Matthew","last_name":"Joyce","preferred_name":"Matt","jersey_number":"17","id":"51cfeba6-6ea2-420b-8512-92584890a8a1"}]},{"hitter_id":"55955b56-8197-4c82-9653-e0348917739d","pitcher_id":"6ea9ca2c-55ff-407d-99ef-8f3e741af0a7","inning":7,"inning_half":"T","type":"pitch","hitter_outcome":"aS","id":"30502190-d105-4551-a9da-eaef89ca006b","runners":[{"starting_base":3,"first_name":"Starling","last_name":"Marte","preferred_name":"Starling","jersey_number":"6","id":"1c58cf18-0d61-479d-9438-0a4057f552ef"}]},{"hitter_id":"53a80099-966e-451c-a1e2-dccbb16f8dd8","pitcher_id":"6ea9ca2c-55ff-407d-99ef-8f3e741af0a7","inning":9,"inning_half":"T","type":"pitch","hitter_outcome":"aS","id":"33381e09-b8d2-45e8-94d7-554a772c5392","runners":[{"starting_base":3,"first_name":"David","last_name":"Freese","preferred_name":"David","jersey_number":"23","id":"6b511f87-fd17-4dfd-b227-8e96fc8951c2"}]}]},"pitching":{"win":{"preferred_name":"Kyle","first_name":"Kyle","last_name":"Hendricks","jersey_number":"28","status":"A","position":"P","primary_position":"SP","id":"dec510da-0104-48f0-892f-37a9ab9d02ff","win":5,"loss":6,"save":0,"hold":0,"blown_save":0},"loss":{"preferred_name":"Jameson","first_name":"Jameson","last_name":"Taillon","jersey_number":"50","status":"A","position":"P","primary_position":"SP","id":"0b4c4345-7609-4ab1-9aaa-41d56d7f1fda","win":1,"loss":1,"save":0,"hold":0,"blown_save":0}}}},{"game":{"id":"132e3b2b-dd4e-407a-bd0a-4f934f652640","status":"closed","coverage":"full","game_number":1,"day_night":"D","scheduled":"2016-06-19T17:35:00+00:00","home_team":"2142e1ba-3b40-445c-b8bb-f1f8b1054220","away_team":"25507be1-6a68-4267-bd82-e097d94b359b","attendance":40214,"duration":"2:59","double_header":false,"venue":{"name":"Citizens Bank Park","market":"Philadelphia","capacity":43647,"surface":"grass","address":"One Citizens Bank Way","city":"Philadelphia","state":"PA","zip":"19148","country":"USA","id":"b4186004-b6d0-42e7-8dc1-82ef0d946ecc","field_orientation":"NE","stadium_type":"outdoor","location":{"lat":"39.9059929","lng":"-75.1666401"}},"broadcast":{"network":"CSN"},"final":{"inning":9,"inning_half":"B"},"home":{"name":"Phillies","market":"Philadelphia","abbr":"PHI","id":"2142e1ba-3b40-445c-b8bb-f1f8b1054220","runs":1,"hits":3,"errors":1,"win":30,"loss":39,"probable_pitcher":{"preferred_name":"Zach","first_name":"Zachary","last_name":"Eflin","jersey_number":"56","id":"dc22b8c1-fc07-4f68-ae4c-254e9dcc74c1","win":0,"loss":1,"era":27.0},"starting_pitcher":{"preferred_name":"Zach","first_name":"Zachary","last_name":"Eflin","jersey_number":"56","id":"dc22b8c1-fc07-4f68-ae4c-254e9dcc74c1","win":0,"loss":1,"era":27.0},"scoring":[{"number":1,"sequence":1,"runs":0,"hits":1,"errors":0,"type":"inning"},{"number":2,"sequence":2,"runs":0,"hits":0,"errors":0,"type":"inning"},{"number":3,"sequence":3,"runs":0,"hits":0,"errors":0,"type":"inning"},{"number":4,"sequence":4,"runs":0,"hits":0,"errors":0,"type":"inning"},{"number":5,"sequence":5,"runs":0,"hits":1,"errors":0,"type":"inning"},{"number":6,"sequence":6,"runs":1,"hits":1,"errors":1,"type":"inning"},{"number":7,"sequence":7,"runs":0,"hits":0,"errors":0,"type":"inning"},{"number":8,"sequence":8,"runs":0,"hits":0,"errors":0,"type":"inning"},{"number":9,"sequence":9,"runs":0,"hits":0,"errors":0,"type":"inning"}],"events":[{"hitter_id":"36d8674c-0ff2-468a-b284-6dc338c6a13a","pitcher_id":"4a745f36-bec0-47d9-bdf6-6bac2ea84aeb","inning":6,"inning_half":"B","type":"pitch","hitter_outcome":"oGO","id":"f31f5566-2a6e-49b4-ab53-d2a3cd750987","runners":[{"starting_base":3,"first_name":"Andrés","last_name":"Blanco","preferred_name":"Andrés","jersey_number":"4","id":"9681d8f1-db23-41f6-8054-d0182e3b6f46"}]}]},"away":{"name":"Diamondbacks","market":"Arizona","abbr":"ARI","id":"25507be1-6a68-4267-bd82-e097d94b359b","runs":5,"hits":10,"errors":1,"win":31,"loss":39,"probable_pitcher":{"preferred_name":"Archie","first_name":"Archie","last_name":"Bradley","jersey_number":"25","id":"4a745f36-bec0-47d9-bdf6-6bac2ea84aeb","win":2,"loss":3,"era":5.657},"starting_pitcher":{"preferred_name":"Archie","first_name":"Archie","last_name":"Bradley","jersey_number":"25","id":"4a745f36-bec0-47d9-bdf6-6bac2ea84aeb","win":2,"loss":3,"era":5.657},"scoring":[{"number":1,"sequence":1,"runs":0,"hits":0,"errors":0,"type":"inning"},{"number":2,"sequence":2,"runs":0,"hits":0,"errors":0,"type":"inning"},{"number":3,"sequence":3,"runs":1,"hits":2,"errors":0,"type":"inning"},{"number":4,"sequence":4,"runs":0,"hits":0,"errors":1,"type":"inning"},{"number":5,"sequence":5,"runs":0,"hits":0,"errors":0,"type":"inning"},{"number":6,"sequence":6,"runs":1,"hits":2,"errors":0,"type":"inning"},{"number":7,"sequence":7,"runs":1,"hits":2,"errors":0,"type":"inning"},{"number":8,"sequence":8,"runs":0,"hits":2,"errors":0,"type":"inning"},{"number":9,"sequence":9,"runs":2,"hits":2,"errors":0,"type":"inning"}],"events":[{"hitter_id":"4a745f36-bec0-47d9-bdf6-6bac2ea84aeb","pitcher_id":"dc22b8c1-fc07-4f68-ae4c-254e9dcc74c1","inning":3,"inning_half":"T","type":"pitch","hitter_outcome":"oSF","id":"11f2bd94-6d3a-4e36-aafc-bd8b27aab6e7","runners":[{"starting_base":3,"first_name":"Brandon","last_name":"Drury","preferred_name":"Brandon","jersey_number":"27","id":"37de17c5-5ff0-449e-b6a9-a936d1c9a78b"}]},{"hitter_id":"35a3e757-618f-4f85-a80f-9f717bec806d","pitcher_id":"dc22b8c1-fc07-4f68-ae4c-254e9dcc74c1","inning":6,"inning_half":"T","type":"pitch","hitter_outcome":"aD","id":"2784d812-a9de-43e4-bc36-00d4be8e9818","runners":[{"starting_base":1,"first_name":"Paul","last_name":"Goldschmidt","preferred_name":"Paul","jersey_number":"44","id":"7c9c97fd-7a89-49e1-830b-0274a5c2209a"}]},{"hitter_id":"468c82b9-425a-4986-a862-e1ae9de32a7c","pitcher_id":"ab6801a2-e5ce-4773-aed0-0cc0a0363871","inning":7,"inning_half":"T","type":"pitch","hitter_outcome":"aSAD2","id":"3d110442-4837-4948-9886-3bb0a238a51f","runners":[{"starting_base":2,"first_name":"Brandon","last_name":"Drury","preferred_name":"Brandon","jersey_number":"27","id":"37de17c5-5ff0-449e-b6a9-a936d1c9a78b"}]},{"hitter_id":"468c82b9-425a-4986-a862-e1ae9de32a7c","pitcher_id":"970d1ba0-93be-4a15-bb0d-70389f8d3d3f","inning":9,"inning_half":"T","type":"pitch","hitter_outcome":"bB","id":"40a802fe-6adf-41c6-aa63-b857e7d364b5","runners":[{"starting_base":3,"first_name":"Philip","last_name":"Gosselin","preferred_name":"Phil","jersey_number":"15","id":"d598fe0d-8402-4707-b05d-4663a1c3cbe7"}]},{"hitter_id":"35a3e757-618f-4f85-a80f-9f717bec806d","pitcher_id":"afb67744-95ec-4494-b660-15e471cd2c88","inning":9,"inning_half":"T","type":"pitch","hitter_outcome":"aT","id":"b3fd8492-4d93-4324-b34f-df3343c461a9","runners":[{"starting_base":1,"first_name":"Paul","last_name":"Goldschmidt","preferred_name":"Paul","jersey_number":"44","id":"7c9c97fd-7a89-49e1-830b-0274a5c2209a"}]}]},"pitching":{"win":{"preferred_name":"Archie","first_name":"Archie","last_name":"Bradley","jersey_number":"25","status":"A","position":"P","primary_position":"RP","id":"4a745f36-bec0-47d9-bdf6-6bac2ea84aeb","win":3,"loss":3,"save":0,"hold":0,"blown_save":0},"loss":{"preferred_name":"Zach","first_name":"Zachary","last_name":"Eflin","jersey_number":"56","status":"MIN","position":"P","primary_position":"SP","id":"dc22b8c1-fc07-4f68-ae4c-254e9dcc74c1","win":0,"loss":2,"save":0,"hold":0,"blown_save":0},"hold":[{"preferred_name":"Daniel","first_name":"Daniel","last_name":"Hudson","status":"FA","position":"P","primary_position":"RP","id":"3d6aef45-a71b-43dc-87ed-85483cd241a3","win":1,"loss":1,"save":0,"hold":11,"blown_save":0},{"preferred_name":"Tyler","first_name":"Tyler","last_name":"Clippard","jersey_number":"36","status":"A","position":"P","primary_position":"RP","id":"e057c52e-d17b-4774-8e0a-5ea4f19c0a3a","win":2,"loss":3,"save":1,"hold":8,"blown_save":1}]}}},{"game":{"id":"f46189bf-7b64-4854-b167-c041bb647793","status":"closed","coverage":"full","game_number":1,"day_night":"D","scheduled":"2016-06-19T17:10:00+00:00","home_team":"f246a5e5-afdb-479c-9aaa-c68beeda7af6","away_team":"12079497-e414-450a-8bf2-29f91de646bf","attendance":41576,"duration":"2:51","double_header":false,"venue":{"name":"Citi Field","market":"New York","capacity":41922,"surface":"grass","address":"123-01 Roosevelt Avenue","city":"Flushing, Queens","state":"NY","zip":"11368","country":"USA","id":"265c7d6c-427a-4b8a-8def-392c41954bec","field_orientation":"NE","stadium_type":"outdoor","location":{"lat":"40.7564124","lng":"-73.84589369999999"}},"broadcast":{"network":"WPIX"},"final":{"inning":9,"inning_half":"B"},"home":{"name":"Mets","market":"New York","abbr":"NYM","id":"f246a5e5-afdb-479c-9aaa-c68beeda7af6","runs":0,"hits":1,"errors":0,"win":36,"loss":31,"probable_pitcher":{"preferred_name":"Jacob","first_name":"Jacob","last_name":"deGrom","jersey_number":"48","id":"e5cfe3b2-6596-4f08-bba7-f107ecae63c2","win":3,"loss":3,"era":2.821},"starting_pitcher":{"preferred_name":"Jacob","first_name":"Jacob","last_name":"deGrom","jersey_number":"48","id":"e5cfe3b2-6596-4f08-bba7-f107ecae63c2","win":3,"loss":3,"era":2.821},"scoring":[{"number":1,"sequence":1,"runs":0,"hits":0,"errors":0,"type":"inning"},{"number":2,"sequence":2,"runs":0,"hits":0,"errors":0,"type":"inning"},{"number":3,"sequence":3,"runs":0,"hits":1,"errors":0,"type":"inning"},{"number":4,"sequence":4,"runs":0,"hits":0,"errors":0,"type":"inning"},{"number":5,"sequence":5,"runs":0,"hits":0,"errors":0,"type":"inning"},{"number":6,"sequence":6,"runs":0,"hits":0,"errors":0,"type":"inning"},{"number":7,"sequence":7,"runs":0,"hits":0,"errors":0,"type":"inning"},{"number":8,"sequence":8,"runs":0,"hits":0,"errors":0,"type":"inning"},{"number":9,"sequence":9,"runs":0,"hits":0,"errors":0,"type":"inning"}]},"away":{"name":"Braves","market":"Atlanta","abbr":"ATL","id":"12079497-e414-450a-8bf2-29f91de646bf","runs":6,"hits":11,"errors":0,"win":22,"loss":46,"probable_pitcher":{"preferred_name":"Julio","first_name":"Julio","last_name":"Teherán","jersey_number":"49","id":"57943e75-0e1c-4b96-8ded-479db4a6351c","win":2,"loss":7,"era":2.933},"starting_pitcher":{"preferred_name":"Julio","first_name":"Julio","last_name":"Teherán","jersey_number":"49","id":"57943e75-0e1c-4b96-8ded-479db4a6351c","win":2,"loss":7,"era":2.933},"scoring":[{"number":1,"sequence":1,"runs":0,"hits":1,"errors":0,"type":"inning"},{"number":2,"sequence":2,"runs":0,"hits":0,"errors":0,"type":"inning"},{"number":3,"sequence":3,"runs":2,"hits":3,"errors":0,"type":"inning"},{"number":4,"sequence":4,"runs":0,"hits":0,"errors":0,"type":"inning"},{"number":5,"sequence":5,"runs":0,"hits":0,"errors":0,"type":"inning"},{"number":6,"sequence":6,"runs":1,"hits":1,"errors":0,"type":"inning"},{"number":7,"sequence":7,"runs":2,"hits":2,"errors":0,"type":"inning"},{"number":8,"sequence":8,"runs":1,"hits":3,"errors":0,"type":"inning"},{"number":9,"sequence":9,"runs":0,"hits":1,"errors":0,"type":"inning"}],"events":[{"hitter_id":"91406228-8d10-4a6d-877a-c5ae235ccc00","pitcher_id":"e5cfe3b2-6596-4f08-bba7-f107ecae63c2","inning":3,"inning_half":"T","type":"pitch","hitter_outcome":"aS","id":"6e1d25d2-687f-46a4-9cef-6ab8a439bc2f","runners":[{"starting_base":3,"first_name":"Erick","last_name":"Aybar","preferred_name":"Erick","jersey_number":"1","id":"9ebd933f-8400-4f1f-93fd-61d4055237f2"}]},{"hitter_id":"9880d4de-4cd4-47a5-8996-61d52a35ea2a","pitcher_id":"e5cfe3b2-6596-4f08-bba7-f107ecae63c2","inning":3,"inning_half":"T","type":"pitch","hitter_outcome":"aS","id":"924bd1a0-eb60-4e3e-8313-e8e6981ac433","runners":[{"starting_base":2,"first_name":"Ender","last_name":"Inciarte","preferred_name":"Ender","jersey_number":"11","id":"91406228-8d10-4a6d-877a-c5ae235ccc00"}]},{"hitter_id":"9880d4de-4cd4-47a5-8996-61d52a35ea2a","pitcher_id":"e5cfe3b2-6596-4f08-bba7-f107ecae63c2","inning":6,"inning_half":"T","type":"pitch","hitter_outcome":"aHR","id":"31cb4c69-ac9d-47ad-a0ad-4620102e83ce","runners":[{"starting_base":0,"first_name":"Nicholas","last_name":"Markakis","preferred_name":"Nick","jersey_number":"22","id":"9880d4de-4cd4-47a5-8996-61d52a35ea2a"}]},{"hitter_id":"91406228-8d10-4a6d-877a-c5ae235ccc00","pitcher_id":"8341c20b-5412-4c76-89c4-2f36fac8e5ff","inning":7,"inning_half":"T","type":"pitch","hitter_outcome":"aBK","id":"a062b553-a68b-4a56-9d19-7a1c367915d0","runners":[{"starting_base":3,"first_name":"Erick","last_name":"Aybar","preferred_name":"Erick","jersey_number":"1","id":"9ebd933f-8400-4f1f-93fd-61d4055237f2"}]},{"hitter_id":"ea1a2111-44cc-4996-babb-9439465e6760","pitcher_id":"8341c20b-5412-4c76-89c4-2f36fac8e5ff","inning":7,"inning_half":"T","type":"pitch","hitter_outcome":"aD","id":"6ebfd9d4-4851-4c0e-aa12-be2cad11e35d","runners":[{"starting_base":2,"first_name":"Mallex","last_name":"Smith","preferred_name":"Mallex","jersey_number":"17","id":"d89e0030-393c-4433-9779-25aed817abb5"}]},{"hitter_id":"8fbf7c62-485e-457e-b69f-7bb27984559e","pitcher_id":"aacf4eee-3371-4ec4-870a-9012fd69e629","inning":8,"inning_half":"T","type":"pitch","hitter_outcome":"bB","id":"8e9c14e1-3880-43bc-b377-2c0fcf1cb7a4","runners":[{"starting_base":3,"first_name":"Jace","last_name":"Peterson","preferred_name":"Jace","jersey_number":"8","id":"e43136cd-762f-4b3f-8595-4f07e83be3b2"}]}]},"pitching":{"win":{"preferred_name":"Julio","first_name":"Julio","last_name":"Teherán","jersey_number":"49","status":"A","position":"P","primary_position":"SP","id":"57943e75-0e1c-4b96-8ded-479db4a6351c","win":3,"loss":7,"save":0,"hold":0,"blown_save":0},"loss":{"preferred_name":"Jacob","first_name":"Jacob","last_name":"deGrom","jersey_number":"48","status":"A","position":"P","primary_position":"SP","id":"e5cfe3b2-6596-4f08-bba7-f107ecae63c2","win":3,"loss":4,"save":0,"hold":0,"blown_save":0}}}},{"game":{"id":"31427a39-f1e4-427c-840f-ea5f2de5db78","status":"closed","coverage":"full","game_number":1,"day_night":"D","scheduled":"2016-06-19T20:10:00+00:00","home_team":"ef64da7f-cfaf-4300-87b0-9313386b977c","away_team":"dcfd5266-00ce-442c-bc09-264cd20cf455","attendance":45931,"duration":"2:44","double_header":false,"venue":{"name":"Dodger Stadium","market":"Los Angeles","capacity":56000,"surface":"grass","address":"1000 Vin Scully Avenue","city":"Los Angeles","state":"CA","zip":"90012","country":"USA","id":"66a19c3d-24fe-477d-bee7-c6ef1b98352f","field_orientation":"NE","stadium_type":"outdoor","location":{"lat":"34.0745409","lng":"-118.2408881"}},"broadcast":{"network":"SportsNet LA"},"final":{"inning":9,"inning_half":"B"},"home":{"name":"Dodgers","market":"Los Angeles","abbr":"LAD","id":"ef64da7f-cfaf-4300-87b0-9313386b977c","runs":2,"hits":8,"errors":0,"win":37,"loss":33,"probable_pitcher":{"preferred_name":"Kenta","first_name":"Kenta","last_name":"Maeda","jersey_number":"18","id":"e66534ab-0f5b-4c55-ade3-c06bd798a77f","win":6,"loss":4,"era":2.748},"starting_pitcher":{"preferred_name":"Kenta","first_name":"Kenta","last_name":"Maeda","jersey_number":"18","id":"e66534ab-0f5b-4c55-ade3-c06bd798a77f","win":6,"loss":4,"era":2.748},"scoring":[{"number":1,"sequence":1,"runs":0,"hits":2,"errors":0,"type":"inning"},{"number":2,"sequence":2,"runs":0,"hits":0,"errors":0,"type":"inning"},{"number":3,"sequence":3,"runs":0,"hits":1,"errors":1,"type":"inning"},{"number":4,"sequence":4,"runs":0,"hits":0,"errors":0,"type":"inning"},{"number":5,"sequence":5,"runs":0,"hits":1,"errors":0,"type":"inning"},{"number":6,"sequence":6,"runs":0,"hits":1,"errors":0,"type":"inning"},{"number":7,"sequence":7,"runs":0,"hits":0,"errors":0,"type":"inning"},{"number":8,"sequence":8,"runs":1,"hits":1,"errors":0,"type":"inning"},{"number":9,"sequence":9,"runs":1,"hits":2,"errors":0,"type":"inning"}],"events":[{"hitter_id":"8a7b7092-4e7b-4112-92bf-fc5d72a83d17","pitcher_id":"19a3dd28-85dd-4ae0-969e-f4f33419ea5b","inning":8,"inning_half":"B","type":"pitch","hitter_outcome":"aHR","id":"99b70d95-3b92-4436-a6f0-fbac6e9778de","runners":[{"starting_base":0,"first_name":"Enriqué","last_name":"Hernández","preferred_name":"Kiké","jersey_number":"14","id":"8a7b7092-4e7b-4112-92bf-fc5d72a83d17"}]},{"hitter_id":"643547ae-4a60-4135-b290-88a1b2160cbb","pitcher_id":"c2a71506-19e8-4d48-9d5f-d250cd1db862","inning":9,"inning_half":"B","type":"pitch","hitter_outcome":"bB","id":"45e9a5d0-de53-4db9-b29f-b93895c9e380","runners":[{"starting_base":3,"first_name":"Scott","last_name":"Van Slyke","preferred_name":"Scott","jersey_number":"33","id":"9dec71ae-6e68-4e10-814d-a246366cff47"}]}]},"away":{"name":"Brewers","market":"Milwaukee","abbr":"MIL","id":"dcfd5266-00ce-442c-bc09-264cd20cf455","runs":1,"hits":6,"errors":1,"win":31,"loss":38,"probable_pitcher":{"preferred_name":"Matt","first_name":"Matthew","last_name":"Garza","id":"165cbd34-644f-4a27-8735-8aa8ab12aecf","win":0,"loss":0,"era":2.25},"starting_pitcher":{"preferred_name":"Matt","first_name":"Matthew","last_name":"Garza","id":"165cbd34-644f-4a27-8735-8aa8ab12aecf","win":0,"loss":0,"era":2.25},"scoring":[{"number":1,"sequence":1,"runs":1,"hits":1,"errors":0,"type":"inning"},{"number":2,"sequence":2,"runs":0,"hits":0,"errors":0,"type":"inning"},{"number":3,"sequence":3,"runs":0,"hits":1,"errors":0,"type":"inning"},{"number":4,"sequence":4,"runs":0,"hits":0,"errors":0,"type":"inning"},{"number":5,"sequence":5,"runs":0,"hits":1,"errors":0,"type":"inning"},{"number":6,"sequence":6,"runs":0,"hits":1,"errors":0,"type":"inning"},{"number":7,"sequence":7,"runs":0,"hits":2,"errors":0,"type":"inning"},{"number":8,"sequence":8,"runs":0,"hits":0,"errors":0,"type":"inning"},{"number":9,"sequence":9,"runs":0,"hits":0,"errors":0,"type":"inning"}],"events":[{"hitter_id":"d4da1a04-b306-4389-a7c1-052ef36c4d83","pitcher_id":"e66534ab-0f5b-4c55-ade3-c06bd798a77f","inning":1,"inning_half":"T","type":"pitch","hitter_outcome":"aHR","id":"782f8b2e-b94d-4f22-9082-de44b6887364","runners":[{"starting_base":0,"first_name":"Ryan","last_name":"Gennett","preferred_name":"Scooter","jersey_number":"2","id":"d4da1a04-b306-4389-a7c1-052ef36c4d83"}]}]},"pitching":{"win":{"preferred_name":"Kenley","first_name":"Kenley","last_name":"Jansen","jersey_number":"74","status":"A","position":"P","primary_position":"RP","id":"9e798b78-22d9-44df-a4c3-fc9db6c0133d","win":3,"loss":2,"save":19,"hold":0,"blown_save":3},"loss":{"preferred_name":"Tyler","first_name":"Tyler","last_name":"Thornburg","jersey_number":"47","status":"D10","position":"P","primary_position":"RP","id":"c2a71506-19e8-4d48-9d5f-d250cd1db862","win":3,"loss":2,"save":1,"hold":13,"blown_save":3},"hold":[{"preferred_name":"Blaine","first_name":"Blaine","last_name":"Boyer","jersey_number":"51","status":"A","position":"P","primary_position":"RP","id":"3b3f273e-7eb0-426d-bd8f-86fa2d4c11f3","win":1,"loss":1,"save":1,"hold":2,"blown_save":1}],"blown_save":[{"preferred_name":"Will","first_name":"William","last_name":"Smith","jersey_number":"13","status":"D10","position":"P","primary_position":"RP","id":"19a3dd28-85dd-4ae0-969e-f4f33419ea5b","win":1,"loss":1,"save":0,"hold":2,"blown_save":2}]}}},{"game":{"id":"501668a2-6016-45c6-951a-87239f318ac4","status":"closed","coverage":"full","game_number":1,"day_night":"D","scheduled":"2016-06-19T18:15:00+00:00","home_team":"833a51a9-0d84-410f-bd77-da08c3e5e26e","away_team":"575c19b7-4052-41c2-9f0a-1c5813d02f99","attendance":34659,"duration":"3:32","double_header":false,"venue":{"name":"Kauffman Stadium","market":"Kansas City","capacity":37903,"surface":"grass","address":"One Royal Way","city":"Kansas City","state":"MO","zip":"64129","country":"USA","id":"6fca95c9-7f2c-4acb-a9f3-02ef96340d2a","field_orientation":"NE","stadium_type":"outdoor","location":{"lat":"39.051465","lng":"-94.48028889999999"}},"broadcast":{"network":"FSKC"},"final":{"inning":13,"inning_half":"B"},"home":{"name":"Royals","market":"Kansas City","abbr":"KC","id":"833a51a9-0d84-410f-bd77-da08c3e5e26e","runs":2,"hits":7,"errors":0,"win":37,"loss":31,"probable_pitcher":{"preferred_name":"Chris","first_name":"Christopher","last_name":"Young","id":"14bfa54e-3df3-47c8-adf2-2400d2e2c0ec","win":2,"loss":6,"era":6.154},"starting_pitcher":{"preferred_name":"Chris","first_name":"Christopher","last_name":"Young","id":"14bfa54e-3df3-47c8-adf2-2400d2e2c0ec","win":2,"loss":6,"era":6.154},"scoring":[{"number":1,"sequence":1,"runs":0,"hits":1,"errors":0,"type":"inning"},{"number":2,"sequence":2,"runs":0,"hits":0,"errors":0,"type":"inning"},{"number":3,"sequence":3,"runs":0,"hits":0,"errors":0,"type":"inning"},{"number":4,"sequence":4,"runs":0,"hits":1,"errors":0,"type":"inning"},{"number":5,"sequence":5,"runs":1,"hits":2,"errors":0,"type":"inning"},{"number":6,"sequence":6,"runs":0,"hits":0,"errors":0,"type":"inning"},{"number":7,"sequence":7,"runs":0,"hits":0,"errors":0,"type":"inning"},{"number":8,"sequence":8,"runs":0,"hits":0,"errors":0,"type":"inning"},{"number":9,"sequence":9,"runs":0,"hits":0,"errors":0,"type":"inning"},{"number":10,"sequence":10,"runs":0,"hits":1,"errors":0,"type":"inning"},{"number":11,"sequence":11,"runs":0,"hits":0,"errors":0,"type":"inning"},{"number":12,"sequence":12,"runs":0,"hits":0,"errors":0,"type":"inning"},{"number":13,"sequence":13,"runs":1,"hits":2,"errors":1,"type":"inning"}],"events":[{"hitter_id":"cfc18051-5701-41cd-8161-3a210087000f","pitcher_id":"8f131591-cc6e-43ad-a6e2-b15963fcb6ba","inning":5,"inning_half":"B","type":"pitch","hitter_outcome":"oGO","id":"ea157191-e083-471e-a87b-d1871fd313cd","runners":[{"starting_base":3,"first_name":"Kendrys","last_name":"Morales","preferred_name":"Kendrys","jersey_number":"25","id":"d4afcfdc-b875-4163-ad7f-eb26b7228f80"}]},{"hitter_id":"77817a36-b646-42ec-94cf-95958b55c641","pitcher_id":"49f1d798-2b08-4d37-a6fb-b63701c1de4a","inning":13,"inning_half":"B","type":"pitch","hitter_outcome":"aS","id":"35f6254f-ad30-4fcd-9d46-ed9c970ae807","runners":[{"starting_base":3,"first_name":"Lorenzo","last_name":"Cain","preferred_name":"Lorenzo","jersey_number":"6","id":"3cfaa9a7-8dea-4590-8ea5-c8e1b51232cf"}]}]},"away":{"name":"Tigers","market":"Detroit","abbr":"DET","id":"575c19b7-4052-41c2-9f0a-1c5813d02f99","runs":1,"hits":5,"errors":1,"win":34,"loss":34,"probable_pitcher":{"preferred_name":"Jordan","first_name":"Jordan","last_name":"Zimmermann","jersey_number":"27","id":"8f131591-cc6e-43ad-a6e2-b15963fcb6ba","win":9,"loss":3,"era":3.462},"starting_pitcher":{"preferred_name":"Jordan","first_name":"Jordan","last_name":"Zimmermann","jersey_number":"27","id":"8f131591-cc6e-43ad-a6e2-b15963fcb6ba","win":9,"loss":3,"era":3.462},"scoring":[{"number":1,"sequence":1,"runs":0,"hits":0,"errors":0,"type":"inning"},{"number":2,"sequence":2,"runs":0,"hits":0,"errors":0,"type":"inning"},{"number":3,"sequence":3,"runs":1,"hits":2,"errors":0,"type":"inning"},{"number":4,"sequence":4,"runs":0,"hits":0,"errors":0,"type":"inning"},{"number":5,"sequence":5,"runs":0,"hits":1,"errors":0,"type":"inning"},{"number":6,"sequence":6,"runs":0,"hits":0,"errors":0,"type":"inning"},{"number":7,"sequence":7,"runs":0,"hits":0,"errors":0,"type":"inning"},{"number":8,"sequence":8,"runs":0,"hits":0,"errors":0,"type":"inning"},{"number":9,"sequence":9,"runs":0,"hits":0,"errors":0,"type":"inning"},{"number":10,"sequence":10,"runs":0,"hits":1,"errors":0,"type":"inning"},{"number":11,"sequence":11,"runs":0,"hits":0,"errors":0,"type":"inning"},{"number":12,"sequence":12,"runs":0,"hits":0,"errors":0,"type":"inning"},{"number":13,"sequence":13,"runs":0,"hits":1,"errors":0,"type":"inning"}],"events":[{"hitter_id":"fddd3a55-1d6c-44a0-9dd2-8aaaac172f92","pitcher_id":"14bfa54e-3df3-47c8-adf2-2400d2e2c0ec","inning":3,"inning_half":"T","type":"pitch","hitter_outcome":"aHR","id":"51f92c18-fa2d-48f0-9848-30611511619f","runners":[{"starting_base":0,"first_name":"Steven","last_name":"Moyà","preferred_name":"Steven","jersey_number":"33","id":"fddd3a55-1d6c-44a0-9dd2-8aaaac172f92"}]}]},"pitching":{"win":{"preferred_name":"Chien-Ming","first_name":"Chien-Ming","last_name":"Wang","jersey_number":"67","status":"FA","position":"P","primary_position":"RP","id":"efcc3d03-d3ea-4659-b7be-4f48539efd9c","win":4,"loss":0,"save":0,"hold":0,"blown_save":0},"loss":{"preferred_name":"Kyle","first_name":"Kyle","last_name":"Ryan","status":"MIN","position":"P","primary_position":"RP","id":"49f1d798-2b08-4d37-a6fb-b63701c1de4a","win":1,"loss":2,"save":0,"hold":2,"blown_save":1}}}},{"game":{"id":"85b39836-9c87-4360-b375-8b572da6b4c2","status":"closed","coverage":"full","game_number":1,"day_night":"D","scheduled":"2016-06-19T17:10:00+00:00","home_team":"80715d0d-0d2a-450f-a970-1b9a3b18c7e7","away_team":"47f490cd-2f58-4ef7-9dfd-2ad6ba6c1ae8","attendance":25269,"duration":"3:12","double_header":false,"venue":{"name":"Progressive Field","market":"Cleveland","capacity":35225,"surface":"grass","address":"2401 Ontario Street","city":"Cleveland","state":"OH","zip":"44115","country":"USA","id":"2b0ccd49-4d87-4996-ac4d-27ffc7ee4c16","field_orientation":"N","stadium_type":"outdoor","location":{"lat":"41.4957048","lng":"-81.6852732"}},"broadcast":{"network":"SportsTime Ohio"},"final":{"inning":10,"inning_half":"B"},"home":{"name":"Indians","market":"Cleveland","abbr":"CLE","id":"80715d0d-0d2a-450f-a970-1b9a3b18c7e7","runs":3,"hits":12,"errors":1,"win":37,"loss":30,"probable_pitcher":{"preferred_name":"Carlos","first_name":"Carlos","last_name":"Carrasco","jersey_number":"59","id":"683ac24d-7777-478b-8417-d0eb3cb04e83","win":2,"loss":2,"era":3.403},"starting_pitcher":{"preferred_name":"Carlos","first_name":"Carlos","last_name":"Carrasco","jersey_number":"59","id":"683ac24d-7777-478b-8417-d0eb3cb04e83","win":2,"loss":2,"era":3.403},"scoring":[{"number":1,"sequence":1,"runs":1,"hits":3,"errors":0,"type":"inning"},{"number":2,"sequence":2,"runs":0,"hits":1,"errors":0,"type":"inning"},{"number":3,"sequence":3,"runs":0,"hits":1,"errors":0,"type":"inning"},{"number":4,"sequence":4,"runs":1,"hits":1,"errors":0,"type":"inning"},{"number":5,"sequence":5,"runs":0,"hits":1,"errors":0,"type":"inning"},{"number":6,"sequence":6,"runs":0,"hits":0,"errors":0,"type":"inning"},{"number":7,"sequence":7,"runs":0,"hits":1,"errors":0,"type":"inning"},{"number":8,"sequence":8,"runs":0,"hits":1,"errors":0,"type":"inning"},{"number":9,"sequence":9,"runs":0,"hits":1,"errors":0,"type":"inning"},{"number":10,"sequence":10,"runs":1,"hits":2,"errors":0,"type":"inning"}],"events":[{"hitter_id":"60c64199-679f-466a-b0e0-ea9438abd05b","pitcher_id":"b5fe445d-6ac4-4542-a73c-69afced32a97","inning":1,"inning_half":"B","type":"pitch","hitter_outcome":"oSF","id":"99341a50-ea83-4906-92a5-8ed24238f7f8","runners":[{"starting_base":3,"first_name":"Rajai","last_name":"Davis","preferred_name":"Rajai","jersey_number":"20","id":"73478e78-5509-4851-87de-5f8ba6b548eb"}]},{"hitter_id":"081677e0-4134-4f69-a4a4-05acf060ead0","pitcher_id":"b5fe445d-6ac4-4542-a73c-69afced32a97","inning":4,"inning_half":"B","type":"pitch","hitter_outcome":"aHR","id":"4df24499-a21e-4732-bee8-df08198cf252","runners":[{"starting_base":0,"first_name":"Juan","last_name":"Uribe","preferred_name":"Juan","jersey_number":"4","id":"081677e0-4134-4f69-a4a4-05acf060ead0"}]},{"hitter_id":"17e633e5-e7a5-445c-8206-4770254ea2fd","pitcher_id":"66048306-1c8b-45ff-b5c1-ddf5157829c5","inning":10,"inning_half":"B","type":"pitch","hitter_outcome":"aS","id":"a3954691-a856-4f87-80c9-a56e0bb928a5","runners":[{"starting_base":3,"first_name":"Rajai","last_name":"Davis","preferred_name":"Rajai","jersey_number":"20","id":"73478e78-5509-4851-87de-5f8ba6b548eb"}]}]},"away":{"name":"White Sox","market":"Chicago","abbr":"CWS","id":"47f490cd-2f58-4ef7-9dfd-2ad6ba6c1ae8","runs":2,"hits":6,"errors":0,"win":33,"loss":35,"probable_pitcher":{"preferred_name":"Carlos","first_name":"Carlos","last_name":"Rodon","jersey_number":"55","id":"b5fe445d-6ac4-4542-a73c-69afced32a97","win":2,"loss":6,"era":4.284},"starting_pitcher":{"preferred_name":"Carlos","first_name":"Carlos","last_name":"Rodon","jersey_number":"55","id":"b5fe445d-6ac4-4542-a73c-69afced32a97","win":2,"loss":6,"era":4.284},"scoring":[{"number":1,"sequence":1,"runs":1,"hits":2,"errors":0,"type":"inning"},{"number":2,"sequence":2,"runs":0,"hits":0,"errors":0,"type":"inning"},{"number":3,"sequence":3,"runs":0,"hits":0,"errors":0,"type":"inning"},{"number":4,"sequence":4,"runs":1,"hits":1,"errors":0,"type":"inning"},{"number":5,"sequence":5,"runs":0,"hits":1,"errors":1,"type":"inning"},{"number":6,"sequence":6,"runs":0,"hits":0,"errors":0,"type":"inning"},{"number":7,"sequence":7,"runs":0,"hits":0,"errors":0,"type":"inning"},{"number":8,"sequence":8,"runs":0,"hits":1,"errors":0,"type":"inning"},{"number":9,"sequence":9,"runs":0,"hits":0,"errors":0,"type":"inning"},{"number":10,"sequence":10,"runs":0,"hits":1,"errors":0,"type":"inning"}],"events":[{"hitter_id":"b59c6ed2-061e-4c9b-b624-2d1aee74853c","pitcher_id":"683ac24d-7777-478b-8417-d0eb3cb04e83","inning":1,"inning_half":"T","type":"pitch","hitter_outcome":"aD","id":"690e593b-99d4-4617-a15f-153b379dd046","runners":[{"starting_base":3,"first_name":"Timothy","last_name":"Anderson","preferred_name":"Tim","jersey_number":"12","id":"cf579a96-a6f7-41a6-85a9-cf8f145ba3c7"}]},{"hitter_id":"ea7a7858-d7cf-4f4d-bea7-bfb86da44e78","pitcher_id":"683ac24d-7777-478b-8417-d0eb3cb04e83","inning":4,"inning_half":"T","type":"pitch","hitter_outcome":"aHR","id":"8d4b9f2c-1750-4ae8-8927-f7933b30af50","runners":[{"starting_base":0,"first_name":"Melky","last_name":"Cabrera","preferred_name":"Melky","jersey_number":"53","id":"ea7a7858-d7cf-4f4d-bea7-bfb86da44e78"}]}]},"pitching":{"win":{"preferred_name":"Dan","first_name":"Daniel","last_name":"Otero","jersey_number":"61","status":"A","position":"P","primary_position":"RP","id":"b58ed599-aa4d-407a-a40c-0bb703dd4610","win":2,"loss":0,"save":1,"hold":0,"blown_save":0},"loss":{"preferred_name":"David","first_name":"David","last_name":"Robertson","jersey_number":"30","status":"A","position":"P","primary_position":"RP","id":"66048306-1c8b-45ff-b5c1-ddf5157829c5","win":0,"loss":1,"save":16,"hold":0,"blown_save":2}}}}]},"_comment":"Generation started @ 2019-12-01 20:17:43 UTC ended @ 2019-12-01 20:17:43 UTC"}